Workbook
Name carroceria: familias!$D$89:$D$95
Name climatizacion: familias!$D$17:$D$30
Name combustion: familias!$D$31:$D$54
Name frenos: familias!$D$55:$D$60
Name mantenimiento: familias!$D$61:$D$88
Name motor: familias!$D$1:$D$11
Name refrigeracion: familias!$D$12:$D$16

Sheet PEDIDO WEPP
B1: DATOS CLIENTE
B2: Razón Social: | C2: Michael Leffler
B3: CIF: | C3: X-2239443-W
B4: Dirección: | C4: Peones Camineros, Portal A 2 izq. 11158. La barca de Vejer
B5: Dirección envío: | C5: Calle Cruz de la Calzada, 25. P.I. Pelagatos. 11130. Chiclana de la Frontera. Cádiz. España
B6: Teléfono: | C6: +34 640074441
B7: Correo Electrónico: | C7: michael.geonovatek@gmail.com
B8: PEDIDO | I8: Nº | J8: 2025-0001
B9: Descripción | C9: Ref. | D9: Volumen | E9: Cantidad | F9: Unidad | H9: Total | I9: Precio ud | J9: TOTAL | M9: PESO UD | N9: unidad | O9: PESO TOTAL | S9: PALET | T9: PESO | U9: UNIDADES
A10: motor | B10: Tapafugas de Aceite 300 | C10: =IF(B10="-","",VLOOKUP(B10,DATOS!$I$3:$K$200,2,FALSE)) -> 2011-300 | D10: =IF(B10="-","",CONCATENATE(VLOOKUP(C10,DATOS!$J$3:$K$200,2,FALSE)," ml")) -> 300 ml | E10: caja | F10: 2 | G10: =IF(B10="-","",IF(E10="caja",VLOOKUP(B10,DATOS!$I$3:$AC$137,21,FALSE),F10)) -> 24 | H10: =IF(B10="-","",IF(E10="caja",F10*G10,F10)) -> 48 | I10: =IF(B10="-","",VLOOKUP(B10,DATOS!$I$3:$S$138,4,FALSE)) -> 2.8 | J10: =IF(B10="-","",H10*I10) -> 134.4 | M10: =IF(B10="-","",VLOOKUP(B10,DATOS!$I$3:$AF$138,24,FALSE)) -> 0.33 | N10: caja | O10: =IF(H10="",0,M10*H10) -> 15.84 | T10: =1000-T11 -> 626.88 | U10: =1200-U11 -> 27
A11: refrigeracion | B11: Limpia Radiadores | C11: =IF(B11="-","",VLOOKUP(B11,DATOS!$I$3:$K$200,2,FALSE)) -> 2023 | D11: =IF(B11="-","",CONCATENATE(VLOOKUP(C11,DATOS!$J$3:$K$200,2,FALSE)," ml")) -> 400 ml | E11: caja | F11: 1 | G11: =IF(B11="-","",IF(E11="caja",VLOOKUP(B11,DATOS!$I$3:$AC$137,21,FALSE),F11)) -> 24 | H11: =IF(B11="-","",IF(E11="caja",F11*G11,F11)) -> 24 | I11: =IF(B11="-","",VLOOKUP(B11,DATOS!$I$3:$S$138,4,FALSE)) -> 2.75 | J11: =IF(B11="-","",H11*I11) -> 66 | M11: =IF(B11="-","",VLOOKUP(B11,DATOS!$I$3:$AF$138,24,FALSE)) -> 0.44 | O11: =IF(H11="",0,M11*H11) -> 10.56 | T11: =SUM(O10:O123) -> 373.12 | U11: =SUM(H10:H123) -> 1173
A12: climatizacion | B12: Airfresh | C12: =IF(B12="-","",VLOOKUP(B12,DATOS!$I$3:$K$200,2,FALSE)) -> 2025 | D12: =IF(B12="-","",CONCATENATE(VLOOKUP(C12,DATOS!$J$3:$K$200,2,FALSE)," ml")) -> 100 ml | E12: caja | F12: 2 | G12: =IF(B12="-","",IF(E12="caja",VLOOKUP(B12,DATOS!$I$3:$AC$137,21,FALSE),F12)) -> 24 | H12: =IF(B12="-","",IF(E12="caja",F12*G12,F12)) -> 48 | I12: =IF(B12="-","",VLOOKUP(B12,DATOS!$I$3:$S$138,4,FALSE)) -> 3.35 | J12: =IF(B12="-","",H12*I12) -> 160.8 | M12: =IF(B12="-","",VLOOKUP(B12,DATOS!$I$3:$AF$138,24,FALSE)) -> 0.11 | O12: =IF(H12="",0,M12*H12) -> 5.28
A13: carroceria | B13: Pintura de Zinc | C13: =IF(B13="-","",VLOOKUP(B13,DATOS!$I$3:$K$200,2,FALSE)) -> 2090 | D13: =IF(B13="-","",CONCATENATE(VLOOKUP(C13,DATOS!$J$3:$K$200,2,FALSE)," ml")) -> 400 ml | E13: caja | F13: 2 | G13: =IF(B13="-","",IF(E13="caja",VLOOKUP(B13,DATOS!$I$3:$AC$137,21,FALSE),F13)) -> 24 | H13: =IF(B13="-","",IF(E13="caja",F13*G13,F13)) -> 48 | I13: =IF(B13="-","",VLOOKUP(B13,DATOS!$I$3:$S$138,4,FALSE)) -> 3.5 | J13: =IF(B13="-","",H13*I13) -> 168 | M13: =IF(B13="-","",VLOOKUP(B13,DATOS!$I$3:$AF$138,24,FALSE)) -> 0.44 | O13: =IF(H13="",0,M13*H13) -> 21.12
A14: mantenimiento | B14: Lubricante Sintético Adhesivo 400 | C14: =IF(B14="-","",VLOOKUP(B14,DATOS!$I$3:$K$200,2,FALSE)) -> 2040 | D14: =IF(B14="-","",CONCATENATE(VLOOKUP(C14,DATOS!$J$3:$K$200,2,FALSE)," ml")) -> 400 ml | E14: unidad | F14: 6 | G14: =IF(B14="-","",IF(E14="caja",VLOOKUP(B14,DATOS!$I$3:$AC$137,21,FALSE),F14)) -> 6 | H14: =IF(B14="-","",IF(E14="caja",F14*G14,F14)) -> 6 | I14: =IF(B14="-","",VLOOKUP(B14,DATOS!$I$3:$S$138,4,FALSE)) -> 0 | J14: =IF(B14="-","",H14*I14) -> 0 | M14: =IF(B14="-","",VLOOKUP(B14,DATOS!$I$3:$AF$138,24,FALSE)) -> 0.44 | O14: =IF(H14="",0,M14*H14) -> 2.64
A15: motor | B15: Limpiador de Motor SF (sin disolventes) | C15: =IF(B15="-","",VLOOKUP(B15,DATOS!$I$3:$K$200,2,FALSE)) -> 2010 SF | D15: =IF(B15="-","",CONCATENATE(VLOOKUP(C15,DATOS!$J$3:$K$200,2,FALSE)," ml")) -> 300 ml | E15: unidad | F15: 6 | G15: =IF(B15="-","",IF(E15="caja",VLOOKUP(B15,DATOS!$I$3:$AC$137,21,FALSE),F15)) -> 6 | H15: =IF(B15="-","",IF(E15="caja",F15*G15,F15)) -> 6 | I15: =IF(B15="-","",VLOOKUP(B15,DATOS!$I$3:$S$138,4,FALSE)) -> 2.95 | J15: =IF(B15="-","",H15*I15) -> 17.7 | M15: =IF(B15="-","",VLOOKUP(B15,DATOS!$I$3:$AF$138,24,FALSE)) -> 0.33 | N15: caja | O15: =IF(H15="",0,M15*H15) -> 1.98
A16: motor | B16: Limpiador de Motor SF (sin disolventes) | C16: =IF(B16="-","",VLOOKUP(B16,DATOS!$I$3:$K$200,2,FALSE)) -> 2010 SF | D16: =IF(B16="-","",CONCATENATE(VLOOKUP(C16,DATOS!$J$3:$K$200,2,FALSE)," ml")) -> 300 ml | E16: unidad | F16: 6 | G16: =IF(B16="-","",IF(E16="caja",VLOOKUP(B16,DATOS!$I$3:$AC$137,21,FALSE),F16)) -> 6 | H16: =IF(B16="-","",IF(E16="caja",F16*G16,F16)) -> 6 | I16: =IF(B16="-","",VLOOKUP(B16,DATOS!$I$3:$S$138,4,FALSE)) -> 2.95 | J16: =IF(B16="-","",H16*I16) -> 17.7 | M16: =IF(B16="-","",VLOOKUP(B16,DATOS!$I$3:$AF$138,24,FALSE)) -> 0.33 | O16: =IF(H16="",0,M16*H16) -> 1.98
A17: motor | B17: Limpiador de Motor SF (sin disolventes) | C17: =IF(B17="-","",VLOOKUP(B17,DATOS!$I$3:$K$200,2,FALSE)) -> 2010 SF | D17: =IF(B17="-","",CONCATENATE(VLOOKUP(C17,DATOS!$J$3:$K$200,2,FALSE)," ml")) -> 300 ml | E17: unidad | F17: 2 | G17: =IF(B17="-","",IF(E17="caja",VLOOKUP(B17,DATOS!$I$3:$AC$137,21,FALSE),F17)) -> 2 | H17: =IF(B17="-","",IF(E17="caja",F17*G17,F17)) -> 2 | I17: =IF(B17="-","",VLOOKUP(B17,DATOS!$I$3:$S$138,4,FALSE)) -> 2.95 | J17: =IF(B17="-","",H17*I17) -> 5.9 | M17: =IF(B17="-","",VLOOKUP(B17,DATOS!$I$3:$AF$138,24,FALSE)) -> 0.33 | N17: caja | O17: =IF(H17="",0,M17*H17) -> 0.66
A18: motor | B18: Limpiador de Motor SF (sin disolventes) | C18: =IF(B18="-","",VLOOKUP(B18,DATOS!$I$3:$K$200,2,FALSE)) -> 2010 SF | D18: =IF(B18="-","",CONCATENATE(VLOOKUP(C18,DATOS!$J$3:$K$200,2,FALSE)," ml")) -> 300 ml | E18: unidad | F18: 2 | G18: =IF(B18="-","",IF(E18="caja",VLOOKUP(B18,DATOS!$I$3:$AC$137,21,FALSE),F18)) -> 2 | H18: =IF(B18="-","",IF(E18="caja",F18*G18,F18)) -> 2 | I18: =IF(B18="-","",VLOOKUP(B18,DATOS!$I$3:$S$138,4,FALSE)) -> 2.95 | J18: =IF(B18="-","",H18*I18) -> 5.9 | M18: =IF(B18="-","",VLOOKUP(B18,DATOS!$I$3:$AF$138,24,FALSE)) -> 0.33 | O18: =IF(H18="",0,M18*H18) -> 0.66
A19: motor | B19: Limpiador de Motor SF (sin disolventes) | C19: =IF(B19="-","",VLOOKUP(B19,DATOS!$I$3:$K$200,2,FALSE)) -> 2010 SF | D19: =IF(B19="-","",CONCATENATE(VLOOKUP(C19,DATOS!$J$3:$K$200,2,FALSE)," ml")) -> 300 ml | E19: caja | F19: 2 | G19: =IF(B19="-","",IF(E19="caja",VLOOKUP(B19,DATOS!$I$3:$AC$137,21,FALSE),F19)) -> 24 | H19: =IF(B19="-","",IF(E19="caja",F19*G19,F19)) -> 48 | I19: =IF(B19="-","",VLOOKUP(B19,DATOS!$I$3:$S$138,4,FALSE)) -> 2.95 | J19: =IF(B19="-","",H19*I19) -> 141.6 | M19: =IF(B19="-","",VLOOKUP(B19,DATOS!$I$3:$AF$138,24,FALSE)) -> 0.33 | N19: caja | O19: =IF(H19="",0,M19*H19) -> 15.84
A20: motor | B20: Limpiador de Motor SF (sin disolventes) | C20: =IF(B20="-","",VLOOKUP(B20,DATOS!$I$3:$K$200,2,FALSE)) -> 2010 SF | D20: =IF(B20="-","",CONCATENATE(VLOOKUP(C20,DATOS!$J$3:$K$200,2,FALSE)," ml")) -> 300 ml | E20: caja | F20: 1 | G20: =IF(B20="-","",IF(E20="caja",VLOOKUP(B20,DATOS!$I$3:$AC$137,21,FALSE),F20)) -> 24 | H20: =IF(B20="-","",IF(E20="caja",F20*G20,F20)) -> 24 | I20: =IF(B20="-","",VLOOKUP(B20,DATOS!$I$3:$S$138,4,FALSE)) -> 2.95 | J20: =IF(B20="-","",H20*I20) -> 70.8 | M20: =IF(B20="-","",VLOOKUP(B20,DATOS!$I$3:$AF$138,24,FALSE)) -> 0.33 | O20: =IF(H20="",0,M20*H20) -> 7.92
A21: motor | B21: Limpiador de Motor SF (sin disolventes) | C21: =IF(B21="-","",VLOOKUP(B21,DATOS!$I$3:$K$200,2,FALSE)) -> 2010 SF | D21: =IF(B21="-","",CONCATENATE(VLOOKUP(C21,DATOS!$J$3:$K$200,2,FALSE)," ml")) -> 300 ml | E21: unidad | F21: 12 | G21: =IF(B21="-","",IF(E21="caja",VLOOKUP(B21,DATOS!$I$3:$AC$137,21,FALSE),F21)) -> 12 | H21: =IF(B21="-","",IF(E21="caja",F21*G21,F21)) -> 12 | I21: =IF(B21="-","",VLOOKUP(B21,DATOS!$I$3:$S$138,4,FALSE)) -> 2.95 | J21: =IF(B21="-","",H21*I21) -> 35.4 | M21: =IF(B21="-","",VLOOKUP(B21,DATOS!$I$3:$AF$138,24,FALSE)) -> 0.33 | N21: caja | O21: =IF(H21="",0,M21*H21) -> 3.96
A22: motor | B22: Limpiador de Motor SF (sin disolventes) | C22: =IF(B22="-","",VLOOKUP(B22,DATOS!$I$3:$K$200,2,FALSE)) -> 2010 SF | D22: =IF(B22="-","",CONCATENATE(VLOOKUP(C22,DATOS!$J$3:$K$200,2,FALSE)," ml")) -> 300 ml | E22: unidad | F22: 6 | G22: =IF(B22="-","",IF(E22="caja",VLOOKUP(B22,DATOS!$I$3:$AC$137,21,FALSE),F22)) -> 6 | H22: =IF(B22="-","",IF(E22="caja",F22*G22,F22)) -> 6 | I22: =IF(B22="-","",VLOOKUP(B22,DATOS!$I$3:$S$138,4,FALSE)) -> 2.95 | J22: =IF(B22="-","",H22*I22) -> 17.7 | M22: =IF(B22="-","",VLOOKUP(B22,DATOS!$I$3:$AF$138,24,FALSE)) -> 0.33 | O22: =IF(H22="",0,M22*H22) -> 1.98
A23: motor | B23: Limpiador de Motor SF (sin disolventes) | C23: =IF(B23="-","",VLOOKUP(B23,DATOS!$I$3:$K$200,2,FALSE)) -> 2010 SF | D23: =IF(B23="-","",CONCATENATE(VLOOKUP(C23,DATOS!$J$3:$K$200,2,FALSE)," ml")) -> 300 ml | E23: unidad | F23: 2 | G23: =IF(B23="-","",IF(E23="caja",VLOOKUP(B23,DATOS!$I$3:$AC$137,21,FALSE),F23)) -> 2 | H23: =IF(B23="-","",IF(E23="caja",F23*G23,F23)) -> 2 | I23: =IF(B23="-","",VLOOKUP(B23,DATOS!$I$3:$S$138,4,FALSE)) -> 2.95 | J23: =IF(B23="-","",H23*I23) -> 5.9 | M23: =IF(B23="-","",VLOOKUP(B23,DATOS!$I$3:$AF$138,24,FALSE)) -> 0.33 | O23: =IF(H23="",0,M23*H23) -> 0.66
A24: motor | B24: Limpiador de Motor SF (sin disolventes) | C24: =IF(B24="-","",VLOOKUP(B24,DATOS!$I$3:$K$200,2,FALSE)) -> 2010 SF | D24: =IF(B24="-","",CONCATENATE(VLOOKUP(C24,DATOS!$J$3:$K$200,2,FALSE)," ml")) -> 300 ml | E24: unidad | F24: 6 | G24: =IF(B24="-","",IF(E24="caja",VLOOKUP(B24,DATOS!$I$3:$AC$137,21,FALSE),F24)) -> 6 | H24: =IF(B24="-","",IF(E24="caja",F24*G24,F24)) -> 6 | I24: =IF(B24="-","",VLOOKUP(B24,DATOS!$I$3:$S$138,4,FALSE)) -> 2.95 | J24: =IF(B24="-","",H24*I24) -> 17.7 | M24: =IF(B24="-","",VLOOKUP(B24,DATOS!$I$3:$AF$138,24,FALSE)) -> 0.33 | N24: caja | O24: =IF(H24="",0,M24*H24) -> 1.98
A25: motor | B25: Limpiador de Motor SF (sin disolventes) | C25: =IF(B25="-","",VLOOKUP(B25,DATOS!$I$3:$K$200,2,FALSE)) -> 2010 SF | D25: =IF(B25="-","",CONCATENATE(VLOOKUP(C25,DATOS!$J$3:$K$200,2,FALSE)," ml")) -> 300 ml | E25: caja | F25: 1 | G25: =IF(B25="-","",IF(E25="caja",VLOOKUP(B25,DATOS!$I$3:$AC$137,21,FALSE),F25)) -> 24 | H25: =IF(B25="-","",IF(E25="caja",F25*G25,F25)) -> 24 | I25: =IF(B25="-","",VLOOKUP(B25,DATOS!$I$3:$S$138,4,FALSE)) -> 2.95 | J25: =IF(B25="-","",H25*I25) -> 70.8 | M25: =IF(B25="-","",VLOOKUP(B25,DATOS!$I$3:$AF$138,24,FALSE)) -> 0.33 | O25: =IF(H25="",0,M25*H25) -> 7.92
A26: motor | B26: Limpiador de Motor SF (sin disolventes) | C26: =IF(B26="-","",VLOOKUP(B26,DATOS!$I$3:$K$200,2,FALSE)) -> 2010 SF | D26: =IF(B26="-","",CONCATENATE(VLOOKUP(C26,DATOS!$J$3:$K$200,2,FALSE)," ml")) -> 300 ml | E26: unidad | F26: 4 | G26: =IF(B26="-","",IF(E26="caja",VLOOKUP(B26,DATOS!$I$3:$AC$137,21,FALSE),F26)) -> 4 | H26: =IF(B26="-","",IF(E26="caja",F26*G26,F26)) -> 4 | I26: =IF(B26="-","",VLOOKUP(B26,DATOS!$I$3:$S$138,4,FALSE)) -> 2.95 | J26: =IF(B26="-","",H26*I26) -> 11.8 | M26: =IF(B26="-","",VLOOKUP(B26,DATOS!$I$3:$AF$138,24,FALSE)) -> 0.33 | O26: =IF(H26="",0,M26*H26) -> 1.32
A27: motor | B27: Limpiador de Motor SF (sin disolventes) | C27: =IF(B27="-","",VLOOKUP(B27,DATOS!$I$3:$K$200,2,FALSE)) -> 2010 SF | D27: =IF(B27="-","",CONCATENATE(VLOOKUP(C27,DATOS!$J$3:$K$200,2,FALSE)," ml")) -> 300 ml | E27: unidad | F27: 6 | G27: =IF(B27="-","",IF(E27="caja",VLOOKUP(B27,DATOS!$I$3:$AC$137,21,FALSE),F27)) -> 6 | H27: =IF(B27="-","",IF(E27="caja",F27*G27,F27)) -> 6 | I27: =IF(B27="-","",VLOOKUP(B27,DATOS!$I$3:$S$138,4,FALSE)) -> 2.95 | J27: =IF(B27="-","",H27*I27) -> 17.7 | M27: =IF(B27="-","",VLOOKUP(B27,DATOS!$I$3:$AF$138,24,FALSE)) -> 0.33 | O27: =IF(H27="",0,M27*H27) -> 1.98
A28: motor | B28: Limpiador de Motor SF (sin disolventes) | C28: =IF(B28="-","",VLOOKUP(B28,DATOS!$I$3:$K$200,2,FALSE)) -> 2010 SF | D28: =IF(B28="-","",CONCATENATE(VLOOKUP(C28,DATOS!$J$3:$K$200,2,FALSE)," ml")) -> 300 ml | E28: caja | F28: 1 | G28: =IF(B28="-","",IF(E28="caja",VLOOKUP(B28,DATOS!$I$3:$AC$137,21,FALSE),F28)) -> 24 | H28: =IF(B28="-","",IF(E28="caja",F28*G28,F28)) -> 24 | I28: =IF(B28="-","",VLOOKUP(B28,DATOS!$I$3:$S$138,4,FALSE)) -> 2.95 | J28: =IF(B28="-","",H28*I28) -> 70.8 | M28: =IF(B28="-","",VLOOKUP(B28,DATOS!$I$3:$AF$138,24,FALSE)) -> 0.33 | O28: =IF(H28="",0,M28*H28) -> 7.92
A29: motor | B29: Limpiador de Motor SF (sin disolventes) | C29: =IF(B29="-","",VLOOKUP(B29,DATOS!$I$3:$K$200,2,FALSE)) -> 2010 SF | D29: =IF(B29="-","",CONCATENATE(VLOOKUP(C29,DATOS!$J$3:$K$200,2,FALSE)," ml")) -> 300 ml | E29: unidad | F29: 2 | G29: =IF(B29="-","",IF(E29="caja",VLOOKUP(B29,DATOS!$I$3:$AC$137,21,FALSE),F29)) -> 2 | H29: =IF(B29="-","",IF(E29="caja",F29*G29,F29)) -> 2 | I29: =IF(B29="-","",VLOOKUP(B29,DATOS!$I$3:$S$138,4,FALSE)) -> 2.95 | J29: =IF(B29="-","",H29*I29) -> 5.9 | M29: =IF(B29="-","",VLOOKUP(B29,DATOS!$I$3:$AF$138,24,FALSE)) -> 0.33 | N29: caja | O29: =IF(H29="",0,M29*H29) -> 0.66
I30: subtotal | J30: =SUM(J10:J29) -> 1042.5
B32: PEDIDO | I32: Nº | J32: =J8 -> 2025-0001
B33: Descripción | C33: Ref. | D33: Volumen | E33: Cantidad | F33: Unidad | H33: Total | I33: Precio ud | J33: TOTAL
A34: motor | B34: Indicador de Fuga de A/C 250 | C34: =IF(B34="-","",VLOOKUP(B34,DATOS!$I$3:$K$200,2,FALSE)) -> 7050250 | D34: =IF(B34="-","",CONCATENATE(VLOOKUP(C34,DATOS!$J$3:$K$200,2,FALSE)," ml")) -> 250 ml | E34: unidad | F34: 2 | G34: =IF(B34="-","",IF(E34="caja",VLOOKUP(B34,DATOS!$I$3:$AC$137,21,FALSE),F34)) -> 2 | H34: =IF(B34="-","",IF(E34="caja",F34*G34,F34)) -> 2 | I34: =IF(B34="-","",VLOOKUP(B34,DATOS!$I$3:$S$138,4,FALSE)) -> 12.9 | J34: =IF(B34="-","",H34*I34) -> 25.8 | M34: =IF(B34="-","",VLOOKUP(B34,DATOS!$I$3:$AF$138,24,FALSE)) -> 0.275 | N34: caja | O34: =IF(H34="",0,M34*H34) -> 0.55
A35: refrigeracion | B35: Lubricante Universal POE 68 con Indicador UV | C35: =IF(B35="-","",VLOOKUP(B35,DATOS!$I$3:$K$200,2,FALSE)) -> 7035001 | D35: =IF(B35="-","",CONCATENATE(VLOOKUP(C35,DATOS!$J$3:$K$200,2,FALSE)," ml")) -> 1000 ml | E35: unidad | F35: 2 | G35: =IF(B35="-","",IF(E35="caja",VLOOKUP(B35,DATOS!$I$3:$AC$137,21,FALSE),F35)) -> 2 | H35: =IF(B35="-","",IF(E35="caja",F35*G35,F35)) -> 2 | I35: =IF(B35="-","",VLOOKUP(B35,DATOS!$I$3:$S$138,4,FALSE)) -> 13.85 | J35: =IF(B35="-","",H35*I35) -> 27.7 | M35: =IF(B35="-","",VLOOKUP(B35,DATOS!$I$3:$AF$138,24,FALSE)) -> 1.1 | N35: caja | O35: =IF(H35="",0,M35*H35) -> 2.2
A36: climatizacion | B36: Limpiador Intensivo Diésel | C36: =IF(B36="-","",VLOOKUP(B36,DATOS!$I$3:$K$200,2,FALSE)) -> 2030 | D36: =IF(B36="-","",CONCATENATE(VLOOKUP(C36,DATOS!$J$3:$K$200,2,FALSE)," ml")) -> 500 ml | E36: caja | F36: 2 | G36: =IF(B36="-","",IF(E36="caja",VLOOKUP(B36,DATOS!$I$3:$AC$137,21,FALSE),F36)) -> 24 | H36: =IF(B36="-","",IF(E36="caja",F36*G36,F36)) -> 48 | I36: =IF(B36="-","",VLOOKUP(B36,DATOS!$I$3:$S$138,4,FALSE)) -> 3.65 | J36: =IF(B36="-","",H36*I36) -> 175.2 | M36: =IF(B36="-","",VLOOKUP(B36,DATOS!$I$3:$AF$138,24,FALSE)) -> 0.55 | N36: caja | O36: =IF(H36="",0,M36*H36) -> 26.4
A37: carroceria | B37: Limpiador de Admisión de Aire Diésel | C37: =IF(B37="-","",VLOOKUP(B37,DATOS!$I$3:$K$200,2,FALSE)) -> 2130 | D37: =IF(B37="-","",CONCATENATE(VLOOKUP(C37,DATOS!$J$3:$K$200,2,FALSE)," ml")) -> 400 ml | E37: unidad | F37: 2 | G37: =IF(B37="-","",IF(E37="caja",VLOOKUP(B37,DATOS!$I$3:$AC$137,21,FALSE),F37)) -> 2 | H37: =IF(B37="-","",IF(E37="caja",F37*G37,F37)) -> 2 | I37: =IF(B37="-","",VLOOKUP(B37,DATOS!$I$3:$S$138,4,FALSE)) -> 3.95 | J37: =IF(B37="-","",H37*I37) -> 7.9 | M37: =IF(B37="-","",VLOOKUP(B37,DATOS!$I$3:$AF$138,24,FALSE)) -> 0.44 | N37: caja | O37: =IF(H37="",0,M37*H37) -> 0.88
A38: mantenimiento | B38: Limpiador Turbo EGR Aspiración | C38: =IF(B38="-","",VLOOKUP(B38,DATOS!$I$3:$K$200,2,FALSE)) -> 2230 | D38: =IF(B38="-","",CONCATENATE(VLOOKUP(C38,DATOS!$J$3:$K$200,2,FALSE)," ml")) -> 400 ml | E38: unidad | F38: 4 | G38: =IF(B38="-","",IF(E38="caja",VLOOKUP(B38,DATOS!$I$3:$AC$137,21,FALSE),F38)) -> 4 | H38: =IF(B38="-","",IF(E38="caja",F38*G38,F38)) -> 4 | I38: =IF(B38="-","",VLOOKUP(B38,DATOS!$I$3:$S$138,4,FALSE)) -> 6.5 | J38: =IF(B38="-","",H38*I38) -> 26 | M38: =IF(B38="-","",VLOOKUP(B38,DATOS!$I$3:$AF$138,24,FALSE)) -> 0.44 | N38: caja | O38: =IF(H38="",0,M38*H38) -> 1.76
A39: motor | B39: Limpiador de Válvulas de Mariposa y Carburadores | C39: =IF(B39="-","",VLOOKUP(B39,DATOS!$I$3:$K$200,2,FALSE)) -> 2031 | D39: =IF(B39="-","",CONCATENATE(VLOOKUP(C39,DATOS!$J$3:$K$200,2,FALSE)," ml")) -> 400 ml | E39: unidad | F39: 4 | G39: =IF(B39="-","",IF(E39="caja",VLOOKUP(B39,DATOS!$I$3:$AC$137,21,FALSE),F39)) -> 4 | H39: =IF(B39="-","",IF(E39="caja",F39*G39,F39)) -> 4 | I39: =IF(B39="-","",VLOOKUP(B39,DATOS!$I$3:$S$138,4,FALSE)) -> 3.5 | J39: =IF(B39="-","",H39*I39) -> 14 | M39: =IF(B39="-","",VLOOKUP(B39,DATOS!$I$3:$AF$138,24,FALSE)) -> 0.44 | N39: caja | O39: =IF(H39="",0,M39*H39) -> 1.76
A40: motor | B40: Protector Diésel 300 | C40: =IF(B40="-","",VLOOKUP(B40,DATOS!$I$3:$K$200,2,FALSE)) -> 2032-300 | D40: =IF(B40="-","",CONCATENATE(VLOOKUP(C40,DATOS!$J$3:$K$200,2,FALSE)," ml")) -> 300 ml | E40: caja | F40: 2 | G40: =IF(B40="-","",IF(E40="caja",VLOOKUP(B40,DATOS!$I$3:$AC$137,21,FALSE),F40)) -> 24 | H40: =IF(B40="-","",IF(E40="caja",F40*G40,F40)) -> 48 | I40: =IF(B40="-","",VLOOKUP(B40,DATOS!$I$3:$S$138,4,FALSE)) -> 2.55 | J40: =IF(B40="-","",H40*I40) -> 122.4 | M40: =IF(B40="-","",VLOOKUP(B40,DATOS!$I$3:$AF$138,24,FALSE)) -> 0.33 | N40: caja | O40: =IF(H40="",0,M40*H40) -> 15.84
A41: motor | B41: Diésel Limpieza Completa | C41: =IF(B41="-","",VLOOKUP(B41,DATOS!$I$3:$K$200,2,FALSE)) -> 2032+ | D41: =IF(B41="-","",CONCATENATE(VLOOKUP(C41,DATOS!$J$3:$K$200,2,FALSE)," ml")) -> 250 ml | E41: caja | F41: 2 | G41: =IF(B41="-","",IF(E41="caja",VLOOKUP(B41,DATOS!$I$3:$AC$137,21,FALSE),F41)) -> 24 | H41: =IF(B41="-","",IF(E41="caja",F41*G41,F41)) -> 48 | I41: =IF(B41="-","",VLOOKUP(B41,DATOS!$I$3:$S$138,4,FALSE)) -> 3.6 | J41: =IF(B41="-","",H41*I41) -> 172.8 | M41: =IF(B41="-","",VLOOKUP(B41,DATOS!$I$3:$AF$138,24,FALSE)) -> 0.275 | N41: caja | O41: =IF(H41="",0,M41*H41) -> 13.2
A42: motor | B42: Protector SCR 50 | C42: =IF(B42="-","",VLOOKUP(B42,DATOS!$I$3:$K$200,2,FALSE)) -> 732 | D42: =IF(B42="-","",CONCATENATE(VLOOKUP(C42,DATOS!$J$3:$K$200,2,FALSE)," ml")) -> 50 ml | E42: unidad | F42: 20 | G42: =IF(B42="-","",IF(E42="caja",VLOOKUP(B42,DATOS!$I$3:$AC$137,21,FALSE),F42)) -> 20 | H42: =IF(B42="-","",IF(E42="caja",F42*G42,F42)) -> 20 | I42: =IF(B42="-","",VLOOKUP(B42,DATOS!$I$3:$S$138,4,FALSE)) -> 1.2 | J42: =IF(B42="-","",H42*I42) -> 24 | M42: =IF(B42="-","",VLOOKUP(B42,DATOS!$I$3:$AF$138,24,FALSE)) -> 0.055 | N42: caja | O42: =IF(H42="",0,M42*H42) -> 1.1
A43: motor | B43: Limpiador DPF Turbo 300 | C43: =IF(B43="-","",VLOOKUP(B43,DATOS!$I$3:$K$200,2,FALSE)) -> 2132-300 | D43: =IF(B43="-","",CONCATENATE(VLOOKUP(C43,DATOS!$J$3:$K$200,2,FALSE)," ml")) -> 300 ml | E43: caja | F43: 4 | G43: =IF(B43="-","",IF(E43="caja",VLOOKUP(B43,DATOS!$I$3:$AC$137,21,FALSE),F43)) -> 24 | H43: =IF(B43="-","",IF(E43="caja",F43*G43,F43)) -> 96 | I43: =IF(B43="-","",VLOOKUP(B43,DATOS!$I$3:$S$138,4,FALSE)) -> 3.9 | J43: =IF(B43="-","",H43*I43) -> 374.4 | M43: =IF(B43="-","",VLOOKUP(B43,DATOS!$I$3:$AF$138,24,FALSE)) -> 0.33 | N43: caja | O43: =IF(H43="",0,M43*H43) -> 31.68
A44: motor | B44: Limpiador Directo DPF | C44: =IF(B44="-","",VLOOKUP(B44,DATOS!$I$3:$K$200,2,FALSE)) -> 2232 | D44: =IF(B44="-","",CONCATENATE(VLOOKUP(C44,DATOS!$J$3:$K$200,2,FALSE)," ml")) -> 500 ml | E44: unidad | F44: 1 | G44: =IF(B44="-","",IF(E44="caja",VLOOKUP(B44,DATOS!$I$3:$AC$137,21,FALSE),F44)) -> 1 | H44: =IF(B44="-","",IF(E44="caja",F44*G44,F44)) -> 1 | I44: =IF(B44="-","",VLOOKUP(B44,DATOS!$I$3:$S$138,4,FALSE)) -> 6.85 | J44: =IF(B44="-","",H44*I44) -> 6.85 | M44: =IF(B44="-","",VLOOKUP(B44,DATOS!$I$3:$AF$138,24,FALSE)) -> 0.55 | N44: caja | O44: =IF(H44="",0,M44*H44) -> 0.55
A45: motor | B45: Sonda para pistola 39000 | C45: =IF(B45="-","",VLOOKUP(B45,DATOS!$I$3:$K$200,2,FALSE)) -> 39001 | D45: =IF(B45="-","",CONCATENATE(VLOOKUP(C45,DATOS!$J$3:$K$200,2,FALSE)," ml")) -> - ml | E45: unidad | F45: 1 | G45: =IF(B45="-","",IF(E45="caja",VLOOKUP(B45,DATOS!$I$3:$AC$137,21,FALSE),F45)) -> 1 | H45: =IF(B45="-","",IF(E45="caja",F45*G45,F45)) -> 1 | I45: =IF(B45="-","",VLOOKUP(B45,DATOS!$I$3:$S$138,4,FALSE)) -> 20 | J45: =IF(B45="-","",H45*I45) -> 20 | M45: =IF(B45="-","",VLOOKUP(B45,DATOS!$I$3:$AF$138,24,FALSE)) -> 0.11 | N45: caja | O45: =IF(H45="",0,M45*H45) -> 0.11
... A61: motor | B61: Aceite Adhesivo de Mantenimiento | C61: =IF(B61="-","",VLOOKUP(B61,DATOS!$I$3:$K$200,2,FALSE)) -> 2043 | D61: =IF(B61="-","",CONCATENATE(VLOOKUP(C61,DATOS!$J$3:$K$200,2,FALSE)," ml")) -> 400 ml | E61: unidad | F61: 4 | G61: =IF(B61="-","",IF(E61="caja",VLOOKUP(B61,DATOS!$I$3:$AC$137,21,FALSE),F61)) -> 4 | H61: =IF(B61="-","",IF(E61="caja",F61*G61,F61)) -> 4 | I61: =IF(B61="-","",VLOOKUP(B61,DATOS!$I$3:$S$138,4,FALSE)) -> 3.15 | J61: =IF(B61="-","",H61*I61) -> 12.6 | M61: =IF(B61="-","",VLOOKUP(B61,DATOS!$I$3:$AF$138,24,FALSE)) -> 0.44 | N61: caja | O61: =IF(H61="",0,M61*H61) -> 1.76
I62: subtotal | J62: =SUM(J34:J61) -> 1718.05
B63: PEDIDO | I63: Nº | J63: =J8 -> 2025-0001
B64: Descripción | C64: Ref. | D64: Volumen | E64: Cantidad | F64: Unidad | H64: Total | I64: Precio ud | J64: TOTAL
A65: motor | B65: Grasa de Silicona | C65: =IF(B65="-","",VLOOKUP(B65,DATOS!$I$3:$K$200,2,FALSE)) -> 2045 | D65: =IF(B65="-","",CONCATENATE(VLOOKUP(C65,DATOS!$J$3:$K$200,2,FALSE)," ml")) -> 400 ml | E65: unidad | F65: 2 | G65: =IF(B65="-","",IF(E65="caja",VLOOKUP(B65,DATOS!$I$3:$AC$137,21,FALSE),F65)) -> 2 | H65: =IF(B65="-","",IF(E65="caja",F65*G65,F65)) -> 2 | I65: =IF(B65="-","",VLOOKUP(B65,DATOS!$I$3:$S$138,4,FALSE)) -> 3.9 | J65: =IF(B65="-","",H65*I65) -> 7.8 | M65: =IF(B65="-","",VLOOKUP(B65,DATOS!$I$3:$AF$138,24,FALSE)) -> 0.44 | N65: caja | O65: =IF(H65="",0,M65*H65) -> 0.88
A66: refrigeracion | B66: Desbloqueante Activo | C66: =IF(B66="-","",VLOOKUP(B66,DATOS!$I$3:$K$200,2,FALSE)) -> 2246 | D66: =IF(B66="-","",CONCATENATE(VLOOKUP(C66,DATOS!$J$3:$K$200,2,FALSE)," ml")) -> 400 ml | E66: caja | F66: 2 | G66: =IF(B66="-","",IF(E66="caja",VLOOKUP(B66,DATOS!$I$3:$AC$137,21,FALSE),F66)) -> 24 | H66: =IF(B66="-","",IF(E66="caja",F66*G66,F66)) -> 48 | I66: =IF(B66="-","",VLOOKUP(B66,DATOS!$I$3:$S$138,4,FALSE)) -> 3.75 | J66: =IF(B66="-","",H66*I66) -> 180 | M66: =IF(B66="-","",VLOOKUP(B66,DATOS!$I$3:$AF$138,24,FALSE)) -> 0.44 | N66: caja | O66: =IF(H66="",0,M66*H66) -> 21.12
A67: climatizacion | B67: Aerosol de Silicona | C67: =IF(B67="-","",VLOOKUP(B67,DATOS!$I$3:$K$200,2,FALSE)) -> 2047 | D67: =IF(B67="-","",CONCATENATE(VLOOKUP(C67,DATOS!$J$3:$K$200,2,FALSE)," ml")) -> 400 ml | E67: unidad | F67: 4 | G67: =IF(B67="-","",IF(E67="caja",VLOOKUP(B67,DATOS!$I$3:$AC$137,21,FALSE),F67)) -> 4 | H67: =IF(B67="-","",IF(E67="caja",F67*G67,F67)) -> 4 | I67: =IF(B67="-","",VLOOKUP(B67,DATOS!$I$3:$S$138,4,FALSE)) -> 2.5 | J67: =IF(B67="-","",H67*I67) -> 10 | M67: =IF(B67="-","",VLOOKUP(B67,DATOS!$I$3:$AF$138,24,FALSE)) -> 0.44 | N67: caja | O67: =IF(H67="",0,M67*H67) -> 1.76
A68: carroceria | B68: Desbloqueante MOS2 | C68: =IF(B68="-","",VLOOKUP(B68,DATOS!$I$3:$K$200,2,FALSE)) -> 2048 | D68: =IF(B68="-","",CONCATENATE(VLOOKUP(C68,DATOS!$J$3:$K$200,2,FALSE)," ml")) -> 400 ml | E68: unidad | F68: 4 | G68: =IF(B68="-","",IF(E68="caja",VLOOKUP(B68,DATOS!$I$3:$AC$137,21,FALSE),F68)) -> 4 | H68: =IF(B68="-","",IF(E68="caja",F68*G68,F68)) -> 4 | I68: =IF(B68="-","",VLOOKUP(B68,DATOS!$I$3:$S$138,4,FALSE)) -> 2.35 | J68: =IF(B68="-","",H68*I68) -> 9.4 | M68: =IF(B68="-","",VLOOKUP(B68,DATOS!$I$3:$AF$138,24,FALSE)) -> 0.44 | N68: caja | O68: =IF(H68="",0,M68*H68) -> 1.76
A69: mantenimiento | B69: Aerosol para Interiores | C69: =IF(B69="-","",VLOOKUP(B69,DATOS!$I$3:$K$200,2,FALSE)) -> 2053 | D69: =IF(B69="-","",CONCATENATE(VLOOKUP(C69,DATOS!$J$3:$K$200,2,FALSE)," ml")) -> 400 ml | E69: caja | F69: 1 | G69: =IF(B69="-","",IF(E69="caja",VLOOKUP(B69,DATOS!$I$3:$AC$137,21,FALSE),F69)) -> 24 | H69: =IF(B69="-","",IF(E69="caja",F69*G69,F69)) -> 24 | I69: =IF(B69="-","",VLOOKUP(B69,DATOS!$I$3:$S$138,4,FALSE)) -> 3.5 | J69: =IF(B69="-","",H69*I69) -> 84 | M69: =IF(B69="-","",VLOOKUP(B69,DATOS!$I$3:$AF$138,24,FALSE)) -> 0.44 | N69: caja | O69: =IF(H69="",0,M69*H69) -> 10.56
A70: motor | B70: Aerosol de Aceite con PTFE | C70: =IF(B70="-","",VLOOKUP(B70,DATOS!$I$3:$K$200,2,FALSE)) -> 2054 | D70: =IF(B70="-","",CONCATENATE(VLOOKUP(C70,DATOS!$J$3:$K$200,2,FALSE)," ml")) -> 400 ml | E70: unidad | F70: 4 | G70: =IF(B70="-","",IF(E70="caja",VLOOKUP(B70,DATOS!$I$3:$AC$137,21,FALSE),F70)) -> 4 | H70: =IF(B70="-","",IF(E70="caja",F70*G70,F70)) -> 4 | I70: =IF(B70="-","",VLOOKUP(B70,DATOS!$I$3:$S$138,4,FALSE)) -> 4.8 | J70: =IF(B70="-","",H70*I70) -> 19.2 | M70: =IF(B70="-","",VLOOKUP(B70,DATOS!$I$3:$AF$138,24,FALSE)) -> 0.44 | N70: caja | O70: =IF(H70="",0,M70*H70) -> 1.76
A71: motor | B71: Aerosol de Grasa con PTFE | C71: =IF(B71="-","",VLOOKUP(B71,DATOS!$I$3:$K$200,2,FALSE)) -> 2056 | D71: =IF(B71="-","",CONCATENATE(VLOOKUP(C71,DATOS!$J$3:$K$200,2,FALSE)," ml")) -> 400 ml | E71: unidad | F71: 4 | G71: =IF(B71="-","",IF(E71="caja",VLOOKUP(B71,DATOS!$I$3:$AC$137,21,FALSE),F71)) -> 4 | H71: =IF(B71="-","",IF(E71="caja",F71*G71,F71)) -> 4 | I71: =IF(B71="-","",VLOOKUP(B71,DATOS!$I$3:$S$138,4,FALSE)) -> 4.8 | J71: =IF(B71="-","",H71*I71) -> 19.2 | M71: =IF(B71="-","",VLOOKUP(B71,DATOS!$I$3:$AF$138,24,FALSE)) -> 0.44 | N71: caja | O71: =IF(H71="",0,M71*H71) -> 1.76
A72: motor | B72: Aerosol de Cobre | C72: =IF(B72="-","",VLOOKUP(B72,DATOS!$I$3:$K$200,2,FALSE)) -> 2059 | D72: =IF(B72="-","",CONCATENATE(VLOOKUP(C72,DATOS!$J$3:$K$200,2,FALSE)," ml")) -> 400 ml | E72: unidad | F72: 4 | G72: =IF(B72="-","",IF(E72="caja",VLOOKUP(B72,DATOS!$I$3:$AC$137,21,FALSE),F72)) -> 4 | H72: =IF(B72="-","",IF(E72="caja",F72*G72,F72)) -> 4 | I72: =IF(B72="-","",VLOOKUP(B72,DATOS!$I$3:$S$138,4,FALSE)) -> 3.9 | J72: =IF(B72="-","",H72*I72) -> 15.6 | M72: =IF(B72="-","",VLOOKUP(B72,DATOS!$I$3:$AF$138,24,FALSE)) -> 0.44 | N72: caja | O72: =IF(H72="",0,M72*H72) -> 1.76
A73: motor | B73: Limpiador de Frenos sin Acetona 400 | C73: =IF(B73="-","",VLOOKUP(B73,DATOS!$I$3:$K$200,2,FALSE)) -> 2060 | D73: =IF(B73="-","",CONCATENATE(VLOOKUP(C73,DATOS!$J$3:$K$200,2,FALSE)," ml")) -> 400 ml | E73: caja | F73: 1 | G73: =IF(B73="-","",IF(E73="caja",VLOOKUP(B73,DATOS!$I$3:$AC$137,21,FALSE),F73)) -> 12 | H73: =IF(B73="-","",IF(E73="caja",F73*G73,F73)) -> 12 | I73: =IF(B73="-","",VLOOKUP(B73,DATOS!$I$3:$S$138,4,FALSE)) -> 1.9 | J73: =IF(B73="-","",H73*I73) -> 22.8 | M73: =IF(B73="-","",VLOOKUP(B73,DATOS!$I$3:$AF$138,24,FALSE)) -> 0.66 | N73: caja | O73: =IF(H73="",0,M73*H73) -> 7.92
A74: motor | B74: Limpiador Universal | C74: =IF(B74="-","",VLOOKUP(B74,DATOS!$I$3:$K$200,2,FALSE)) -> 2117 | D74: =IF(B74="-","",CONCATENATE(VLOOKUP(C74,DATOS!$J$3:$K$200,2,FALSE)," ml")) -> 500 ml | E74: unidad | F74: 4 | G74: =IF(B74="-","",IF(E74="caja",VLOOKUP(B74,DATOS!$I$3:$AC$137,21,FALSE),F74)) -> 4 | H74: =IF(B74="-","",IF(E74="caja",F74*G74,F74)) -> 4 | I74: =IF(B74="-","",VLOOKUP(B74,DATOS!$I$3:$S$138,4,FALSE)) -> 0 | J74: =IF(B74="-","",H74*I74) -> 0 | M74: =IF(B74="-","",VLOOKUP(B74,DATOS!$I$3:$AF$138,24,FALSE)) -> 0.55 | N74: caja | O74: =IF(H74="",0,M74*H74) -> 2.2
A75: motor | B75: Limpiacristales | C75: =IF(B75="-","",VLOOKUP(B75,DATOS!$I$3:$K$200,2,FALSE)) -> 2061 | D75: =IF(B75="-","",CONCATENATE(VLOOKUP(C75,DATOS!$J$3:$K$200,2,FALSE)," ml")) -> 500 ml | E75: unidad | F75: 4 | G75: =IF(B75="-","",IF(E75="caja",VLOOKUP(B75,DATOS!$I$3:$AC$137,21,FALSE),F75)) -> 4 | H75: =IF(B75="-","",IF(E75="caja",F75*G75,F75)) -> 4 | I75: =IF(B75="-","",VLOOKUP(B75,DATOS!$I$3:$S$138,4,FALSE)) -> 3.2 | J75: =IF(B75="-","",H75*I75) -> 12.8 | M75: =IF(B75="-","",VLOOKUP(B75,DATOS!$I$3:$AF$138,24,FALSE)) -> 0.55 | N75: caja | O75: =IF(H75="",0,M75*H75) -> 2.2
A76: motor | B76: Limpiacontactos | C76: =IF(B76="-","",VLOOKUP(B76,DATOS!$I$3:$K$200,2,FALSE)) -> 2070 | D76: =IF(B76="-","",CONCATENATE(VLOOKUP(C76,DATOS!$J$3:$K$200,2,FALSE)," ml")) -> 400 ml | E76: unidad | F76: 4 | G76: =IF(B76="-","",IF(E76="caja",VLOOKUP(B76,DATOS!$I$3:$AC$137,21,FALSE),F76)) -> 4 | H76: =IF(B76="-","",IF(E76="caja",F76*G76,F76)) -> 4 | I76: =IF(B76="-","",VLOOKUP(B76,DATOS!$I$3:$S$138,4,FALSE)) -> 3.45 | J76: =IF(B76="-","",H76*I76) -> 13.8 | M76: =IF(B76="-","",VLOOKUP(B76,DATOS!$I$3:$AF$138,24,FALSE)) -> 0.44 | N76: caja | O76: =IF(H76="",0,M76*H76) -> 1.76
... A92: motor | B92: Guantes 8 | C92: =IF(B92="-","",VLOOKUP(B92,DATOS!$I$3:$K$200,2,FALSE)) -> 20648-08 | D92: =IF(B92="-","",CONCATENATE(VLOOKUP(C92,DATOS!$J$3:$K$200,2,FALSE)," ml")) -> - ml | E92: unidad | F92: 12 | G92: =IF(B92="-","",IF(E92="caja",VLOOKUP(B92,DATOS!$I$3:$AC$137,21,FALSE),F92)) -> 12 | H92: =IF(B92="-","",IF(E92="caja",F92*G92,F92)) -> 12 | I92: =IF(B92="-","",VLOOKUP(B92,DATOS!$I$3:$S$138,4,FALSE)) -> 0.95 | J92: =IF(B92="-","",H92*I92) -> 11.4 | M92: =IF(B92="-","",VLOOKUP(B92,DATOS!$I$3:$AF$138,24,FALSE)) -> 0.11 | N92: caja | O92: =IF(H92="",0,M92*H92) -> 1.32
I93: subtotal | J93: =SUM(J65:J92) -> 766.85
B94: PEDIDO | I94: Nº | J94: =J8 -> 2025-0001
B95: Descripción | C95: Ref. | D95: Volumen | E95: Cantidad | F95: Unidad | H95: Total | I95: Precio ud | J95: TOTAL
A96: motor | B96: Guantes 9 | C96: =IF(B96="-","",VLOOKUP(B96,DATOS!$I$3:$K$200,2,FALSE)) -> 20648-09 | D96: =IF(B96="-","",CONCATENATE(VLOOKUP(C96,DATOS!$J$3:$K$200,2,FALSE)," ml")) -> - ml | E96: unidad | F96: 12 | G96: =IF(B96="-","",IF(E96="caja",VLOOKUP(B96,DATOS!$I$3:$AC$137,21,FALSE),F96)) -> 12 | H96: =IF(B96="-","",IF(E96="caja",F96*G96,F96)) -> 12 | I96: =IF(B96="-","",VLOOKUP(B96,DATOS!$I$3:$S$138,4,FALSE)) -> 0.95 | J96: =IF(B96="-","",H96*I96) -> 11.4 | M96: =IF(B96="-","",VLOOKUP(B96,DATOS!$I$3:$AF$138,24,FALSE)) -> 0.11 | N96: caja | O96: =IF(H96="",0,M96*H96) -> 1.32
A97: refrigeracion | B97: Guantes 10 | C97: =IF(B97="-","",VLOOKUP(B97,DATOS!$I$3:$K$200,2,FALSE)) -> 20648-10 | D97: =IF(B97="-","",CONCATENATE(VLOOKUP(C97,DATOS!$J$3:$K$200,2,FALSE)," ml")) -> - ml | E97: unidad | F97: 12 | G97: =IF(B97="-","",IF(E97="caja",VLOOKUP(B97,DATOS!$I$3:$AC$137,21,FALSE),F97)) -> 12 | H97: =IF(B97="-","",IF(E97="caja",F97*G97,F97)) -> 12 | I97: =IF(B97="-","",VLOOKUP(B97,DATOS!$I$3:$S$138,4,FALSE)) -> 0.95 | J97: =IF(B97="-","",H97*I97) -> 11.4 | M97: =IF(B97="-","",VLOOKUP(B97,DATOS!$I$3:$AF$138,24,FALSE)) -> 0.11 | N97: caja | O97: =IF(H97="",0,M97*H97) -> 1.32
A98: climatizacion | B98: - | C98: =IF(B98="-","",VLOOKUP(B98,DATOS!$I$3:$K$200,2,FALSE)) | D98: =IF(B98="-","",CONCATENATE(VLOOKUP(C98,DATOS!$J$3:$K$200,2,FALSE)," ml")) | G98: =IF(B98="-","",IF(E98="caja",VLOOKUP(B98,DATOS!$I$3:$AC$137,21,FALSE),F98)) | H98: =IF(B98="-","",IF(E98="caja",F98*G98,F98)) | I98: =IF(B98="-","",VLOOKUP(B98,DATOS!$I$3:$S$138,4,FALSE)) | J98: =IF(B98="-","",H98*I98) | M98: =IF(B98="-","",VLOOKUP(B98,DATOS!$I$3:$AF$138,24,FALSE)) | N98: caja | O98: =IF(H98="",0,M98*H98) -> 0
A99: carroceria | B99: - | C99: =IF(B99="-","",VLOOKUP(B99,DATOS!$I$3:$K$200,2,FALSE)) | D99: =IF(B99="-","",CONCATENATE(VLOOKUP(C99,DATOS!$J$3:$K$200,2,FALSE)," ml")) | G99: =IF(B99="-","",IF(E99="caja",VLOOKUP(B99,DATOS!$I$3:$AC$137,21,FALSE),F99)) | H99: =IF(B99="-","",IF(E99="caja",F99*G99,F99)) | I99: =IF(B99="-","",VLOOKUP(B99,DATOS!$I$3:$S$138,4,FALSE)) | J99: =IF(B99="-","",H99*I99) | M99: =IF(B99="-","",VLOOKUP(B99,DATOS!$I$3:$AF$138,24,FALSE)) | N99: caja | O99: =IF(H99="",0,M99*H99) -> 0
A100: mantenimiento | B100: - | C100: =IF(B100="-","",VLOOKUP(B100,DATOS!$I$3:$K$200,2,FALSE)) | D100: =IF(B100="-","",CONCATENATE(VLOOKUP(C100,DATOS!$J$3:$K$200,2,FALSE)," ml")) | G100: =IF(B100="-","",IF(E100="caja",VLOOKUP(B100,DATOS!$I$3:$AC$137,21,FALSE),F100)) | H100: =IF(B100="-","",IF(E100="caja",F100*G100,F100)) | I100: =IF(B100="-","",VLOOKUP(B100,DATOS!$I$3:$S$138,4,FALSE)) | J100: =IF(B100="-","",H100*I100) | M100: =IF(B100="-","",VLOOKUP(B100,DATOS!$I$3:$AF$138,24,FALSE)) | N100: caja | O100: =IF(H100="",0,M100*H100) -> 0
A101: motor | B101: - | C101: =IF(B101="-","",VLOOKUP(B101,DATOS!$I$3:$K$200,2,FALSE)) | D101: =IF(B101="-","",CONCATENATE(VLOOKUP(C101,DATOS!$J$3:$K$200,2,FALSE)," ml")) | G101: =IF(B101="-","",IF(E101="caja",VLOOKUP(B101,DATOS!$I$3:$AC$137,21,FALSE),F101)) | H101: =IF(B101="-","",IF(E101="caja",F101*G101,F101)) | I101: =IF(B101="-","",VLOOKUP(B101,DATOS!$I$3:$S$138,4,FALSE)) | J101: =IF(B101="-","",H101*I101) | M101: =IF(B101="-","",VLOOKUP(B101,DATOS!$I$3:$AF$138,24,FALSE)) | N101: caja | O101: =IF(H101="",0,M101*H101) -> 0
A102: motor | B102: - | C102: =IF(B102="-","",VLOOKUP(B102,DATOS!$I$3:$K$200,2,FALSE)) | D102: =IF(B102="-","",CONCATENATE(VLOOKUP(C102,DATOS!$J$3:$K$200,2,FALSE)," ml")) | G102: =IF(B102="-","",IF(E102="caja",VLOOKUP(B102,DATOS!$I$3:$AC$137,21,FALSE),F102)) | H102: =IF(B102="-","",IF(E102="caja",F102*G102,F102)) | I102: =IF(B102="-","",VLOOKUP(B102,DATOS!$I$3:$S$138,4,FALSE)) | J102: =IF(B102="-","",H102*I102) | M102: =IF(B102="-","",VLOOKUP(B102,DATOS!$I$3:$AF$138,24,FALSE)) | N102: caja | O102: =IF(H102="",0,M102*H102) -> 0
A103: motor | B103: - | C103: =IF(B103="-","",VLOOKUP(B103,DATOS!$I$3:$K$200,2,FALSE)) | D103: =IF(B103="-","",CONCATENATE(VLOOKUP(C103,DATOS!$J$3:$K$200,2,FALSE)," ml")) | G103: =IF(B103="-","",IF(E103="caja",VLOOKUP(B103,DATOS!$I$3:$AC$137,21,FALSE),F103)) | H103: =IF(B103="-","",IF(E103="caja",F103*G103,F103)) | I103: =IF(B103="-","",VLOOKUP(B103,DATOS!$I$3:$S$138,4,FALSE)) | J103: =IF(B103="-","",H103*I103) | M103: =IF(B103="-","",VLOOKUP(B103,DATOS!$I$3:$AF$138,24,FALSE)) | N103: caja | O103: =IF(H103="",0,M103*H103) -> 0
A104: motor | B104: - | C104: =IF(B104="-","",VLOOKUP(B104,DATOS!$I$3:$K$200,2,FALSE)) | D104: =IF(B104="-","",CONCATENATE(VLOOKUP(C104,DATOS!$J$3:$K$200,2,FALSE)," ml")) | G104: =IF(B104="-","",IF(E104="caja",VLOOKUP(B104,DATOS!$I$3:$AC$137,21,FALSE),F104)) | H104: =IF(B104="-","",IF(E104="caja",F104*G104,F104)) | I104: =IF(B104="-","",VLOOKUP(B104,DATOS!$I$3:$S$138,4,FALSE)) | J104: =IF(B104="-","",H104*I104) | M104: =IF(B104="-","",VLOOKUP(B104,DATOS!$I$3:$AF$138,24,FALSE)) | N104: caja | O104: =IF(H104="",0,M104*H104) -> 0
A105: motor | B105: - | C105: =IF(B105="-","",VLOOKUP(B105,DATOS!$I$3:$K$200,2,FALSE)) | D105: =IF(B105="-","",CONCATENATE(VLOOKUP(C105,DATOS!$J$3:$K$200,2,FALSE)," ml")) | G105: =IF(B105="-","",IF(E105="caja",VLOOKUP(B105,DATOS!$I$3:$AC$137,21,FALSE),F105)) | H105: =IF(B105="-","",IF(E105="caja",F105*G105,F105)) | I105: =IF(B105="-","",VLOOKUP(B105,DATOS!$I$3:$S$138,4,FALSE)) | J105: =IF(B105="-","",H105*I105) | M105: =IF(B105="-","",VLOOKUP(B105,DATOS!$I$3:$AF$138,24,FALSE)) | N105: caja | O105: =IF(H105="",0,M105*H105) -> 0
A106: motor | B106: - | C106: =IF(B106="-","",VLOOKUP(B106,DATOS!$I$3:$K$200,2,FALSE)) | D106: =IF(B106="-","",CONCATENATE(VLOOKUP(C106,DATOS!$J$3:$K$200,2,FALSE)," ml")) | G106: =IF(B106="-","",IF(E106="caja",VLOOKUP(B106,DATOS!$I$3:$AC$137,21,FALSE),F106)) | H106: =IF(B106="-","",IF(E106="caja",F106*G106,F106)) | I106: =IF(B106="-","",VLOOKUP(B106,DATOS!$I$3:$S$138,4,FALSE)) | J106: =IF(B106="-","",H106*I106) | M106: =IF(B106="-","",VLOOKUP(B106,DATOS!$I$3:$AF$138,24,FALSE)) | N106: caja | O106: =IF(H106="",0,M106*H106) -> 0
A107: motor | B107: - | C107: =IF(B107="-","",VLOOKUP(B107,DATOS!$I$3:$K$200,2,FALSE)) | D107: =IF(B107="-","",CONCATENATE(VLOOKUP(C107,DATOS!$J$3:$K$200,2,FALSE)," ml")) | G107: =IF(B107="-","",IF(E107="caja",VLOOKUP(B107,DATOS!$I$3:$AC$137,21,FALSE),F107)) | H107: =IF(B107="-","",IF(E107="caja",F107*G107,F107)) | I107: =IF(B107="-","",VLOOKUP(B107,DATOS!$I$3:$S$138,4,FALSE)) | J107: =IF(B107="-","",H107*I107) | M107: =IF(B107="-","",VLOOKUP(B107,DATOS!$I$3:$AF$138,24,FALSE)) | N107: caja | O107: =IF(H107="",0,M107*H107) -> 0
A108: motor | B108: - | C108: =IF(B108="-","",VLOOKUP(B108,DATOS!$I$3:$K$200,2,FALSE)) | D108: =IF(B108="-","",CONCATENATE(VLOOKUP(C108,DATOS!$J$3:$K$200,2,FALSE)," ml")) | G108: =IF(B108="-","",IF(E108="caja",VLOOKUP(B108,DATOS!$I$3:$AC$137,21,FALSE),F108)) | H108: =IF(B108="-","",IF(E108="caja",F108*G108,F108)) | I108: =IF(B108="-","",VLOOKUP(B108,DATOS!$I$3:$S$138,4,FALSE)) | J108: =IF(B108="-","",H108*I108) | M108: =IF(B108="-","",VLOOKUP(B108,DATOS!$I$3:$AF$138,24,FALSE)) | N108: caja | O108: =IF(H108="",0,M108*H108) -> 0
A109: motor | B109: - | C109: =IF(B109="-","",VLOOKUP(B109,DATOS!$I$3:$K$200,2,FALSE)) | D109: =IF(B109="-","",CONCATENATE(VLOOKUP(C109,DATOS!$J$3:$K$200,2,FALSE)," ml")) | G109: =IF(B109="-","",IF(E109="caja",VLOOKUP(B109,DATOS!$I$3:$AC$137,21,FALSE),F109)) | H109: =IF(B109="-","",IF(E109="caja",F109*G109,F109)) | I109: =IF(B109="-","",VLOOKUP(B109,DATOS!$I$3:$S$138,4,FALSE)) | J109: =IF(B109="-","",H109*I109) | M109: =IF(B109="-","",VLOOKUP(B109,DATOS!$I$3:$AF$138,24,FALSE)) | N109: caja | O109: =IF(H109="",0,M109*H109) -> 0
... A123: motor | B123: - | C123: =IF(B123="-","",VLOOKUP(B123,DATOS!$I$3:$K$200,2,FALSE)) | D123: =IF(B123="-","",CONCATENATE(VLOOKUP(C123,DATOS!$J$3:$K$200,2,FALSE)," ml")) | G123: =IF(B123="-","",IF(E123="caja",VLOOKUP(B123,DATOS!$I$3:$AC$137,21,FALSE),F123)) | H123: =IF(B123="-","",IF(E123="caja",F123*G123,F123)) | I123: =IF(B123="-","",VLOOKUP(B123,DATOS!$I$3:$S$138,4,FALSE)) | J123: =IF(B123="-","",H123*I123) | M123: =IF(B123="-","",VLOOKUP(B123,DATOS!$I$3:$AF$138,24,FALSE)) | N123: caja | O123: =IF(H123="",0,M123*H123) -> 0
I124: Total | J124: =SUM(J96:J123)+J93+J62+J30 -> 3550.2

Sheet PEDIDO WEPP ALEMAN
B1: DATOS CLIENTE
B2: Razón Social: | D2: ='PEDIDO WEPP'!C2 -> Michael Leffler
B3: CIF: | D3: ='PEDIDO WEPP'!C3 -> X-2239443-W
B4: Dirección: | D4: ='PEDIDO WEPP'!C4 -> Peones Camineros, Portal A 2 izq. 11158. La barca de Vejer
B5: Dirección envío: | D5: ='PEDIDO WEPP'!C5 -> Calle Cruz de la Calzada, 25. P.I. Pelagatos. 11130. Chiclana de la Frontera. Cádiz. España
B6: Teléfono: | D6: ='PEDIDO WEPP'!C6 -> +34 640074441
B7: Correo Electrónico: | D7: ='PEDIDO WEPP'!C7 -> michael.geonovatek@gmail.com
B8: PEDIDO | I8: Nº | J8: ='PEDIDO WEPP'!J8 -> 2025-0001
B9: Ref. | C9: PRODUKT | D9: Volumen | G9: STÜCK | H9: Total | I9: Einzelpreis | J9: TOTAL
B10: ='PEDIDO WEPP'!C10 -> 2011-300 | C10: =IF(B10="","",VLOOKUP(B10,DATOS!$F$3:$H$139,3,FALSE)) -> Ölstopp Additiv | D10: =IF(B10="","",'PEDIDO WEPP'!D10) -> 300 ml | E10: =IF(B10="","",'PEDIDO WEPP'!E10) -> caja | F10: =IF(E10="CAJA","KISTE",IF(E10="unidad","STÜCK","")) -> KISTE | G10: =IF(B10="","",'PEDIDO WEPP'!F10) -> 2 | H10: =IF(B10="","",'PEDIDO WEPP'!H10) -> 48 | I10: =IF(B10="","",'PEDIDO WEPP'!I10) -> 2.8 | J10: =IF(B10="","",'PEDIDO WEPP'!J10) -> 134.4
B11: ='PEDIDO WEPP'!C11 -> 2023 | C11: =IF(B11="","",VLOOKUP(B11,DATOS!$F$3:$H$139,3,FALSE)) -> Kühlerreinigung | D11: =IF(B11="","",'PEDIDO WEPP'!D11) -> 400 ml | E11: =IF(B11="","",'PEDIDO WEPP'!E11) -> caja | F11: =IF(E11="CAJA","KISTE",IF(E11="unidad","STÜCK","")) -> KISTE | G11: =IF(B11="","",'PEDIDO WEPP'!F11) -> 1 | H11: =IF(B11="","",'PEDIDO WEPP'!H11) -> 24 | I11: =IF(B11="","",'PEDIDO WEPP'!I11) -> 2.75 | J11: =IF(B11="","",'PEDIDO WEPP'!J11) -> 66
B12: ='PEDIDO WEPP'!C12 -> 2025 | C12: =IF(B12="","",VLOOKUP(B12,DATOS!$F$3:$H$139,3,FALSE)) -> Airfresh | D12: =IF(B12="","",'PEDIDO WEPP'!D12) -> 100 ml | E12: =IF(B12="","",'PEDIDO WEPP'!E12) -> caja | F12: =IF(E12="CAJA","KISTE",IF(E12="unidad","STÜCK","")) -> KISTE | G12: =IF(B12="","",'PEDIDO WEPP'!F12) -> 2 | H12: =IF(B12="","",'PEDIDO WEPP'!H12) -> 48 | I12: =IF(B12="","",'PEDIDO WEPP'!I12) -> 3.35 | J12: =IF(B12="","",'PEDIDO WEPP'!J12) -> 160.8
B13: ='PEDIDO WEPP'!C13 -> 2090 | C13: =IF(B13="","",VLOOKUP(B13,DATOS!$F$3:$H$139,3,FALSE)) -> Metallschutz Spray | D13: =IF(B13="","",'PEDIDO WEPP'!D13) -> 400 ml | E13: =IF(B13="","",'PEDIDO WEPP'!E13) -> caja | F13: =IF(E13="CAJA","KISTE",IF(E13="unidad","STÜCK","")) -> KISTE | G13: =IF(B13="","",'PEDIDO WEPP'!F13) -> 2 | H13: =IF(B13="","",'PEDIDO WEPP'!H13) -> 48 | I13: =IF(B13="","",'PEDIDO WEPP'!I13) -> 3.5 | J13: =IF(B13="","",'PEDIDO WEPP'!J13) -> 168
B14: ='PEDIDO WEPP'!C14 -> 2040 | C14: =IF(B14="","",VLOOKUP(B14,DATOS!$F$3:$H$139,3,FALSE)) -> Haftsynthese | D14: =IF(B14="","",'PEDIDO WEPP'!D14) -> 400 ml | E14: =IF(B14="","",'PEDIDO WEPP'!E14) -> unidad | F14: =IF(E14="CAJA","KISTE",IF(E14="unidad","STÜCK","")) -> STÜCK | G14: =IF(B14="","",'PEDIDO WEPP'!F14) -> 6 | H14: =IF(B14="","",'PEDIDO WEPP'!H14) -> 6 | I14: =IF(B14="","",'PEDIDO WEPP'!I14) -> 0 | J14: =IF(B14="","",'PEDIDO WEPP'!J14) -> 0
B15: ='PEDIDO WEPP'!C15 -> 2010 SF | C15: =IF(B15="","",VLOOKUP(B15,DATOS!$F$3:$H$139,3,FALSE)) -> Motor System Reiniger (Lösungsmittelfrei) | D15: =IF(B15="","",'PEDIDO WEPP'!D15) -> 300 ml | E15: =IF(B15="","",'PEDIDO WEPP'!E15) -> unidad | F15: =IF(E15="CAJA","KISTE",IF(E15="unidad","STÜCK","")) -> STÜCK | G15: =IF(B15="","",'PEDIDO WEPP'!F15) -> 6 | H15: =IF(B15="","",'PEDIDO WEPP'!H15) -> 6 | I15: =IF(B15="","",'PEDIDO WEPP'!I15) -> 2.95 | J15: =IF(B15="","",'PEDIDO WEPP'!J15) -> 17.7
B16: ='PEDIDO WEPP'!C16 -> 2010 SF | C16: =IF(B16="","",VLOOKUP(B16,DATOS!$F$3:$H$139,3,FALSE)) -> Motor System Reiniger (Lösungsmittelfrei) | D16: =IF(B16="","",'PEDIDO WEPP'!D16) -> 300 ml | E16: =IF(B16="","",'PEDIDO WEPP'!E16) -> unidad | F16: =IF(E16="CAJA","KISTE",IF(E16="unidad","STÜCK","")) -> STÜCK | G16: =IF(B16="","",'PEDIDO WEPP'!F16) -> 6 | H16: =IF(B16="","",'PEDIDO WEPP'!H16) -> 6 | I16: =IF(B16="","",'PEDIDO WEPP'!I16) -> 2.95 | J16: =IF(B16="","",'PEDIDO WEPP'!J16) -> 17.7
B17: ='PEDIDO WEPP'!C17 -> 2010 SF | C17: =IF(B17="","",VLOOKUP(B17,DATOS!$F$3:$H$139,3,FALSE)) -> Motor System Reiniger (Lösungsmittelfrei) | D17: =IF(B17="","",'PEDIDO WEPP'!D17) -> 300 ml | E17: =IF(B17="","",'PEDIDO WEPP'!E17) -> unidad | F17: =IF(E17="CAJA","KISTE",IF(E17="unidad","STÜCK","")) -> STÜCK | G17: =IF(B17="","",'PEDIDO WEPP'!F17) -> 2 | H17: =IF(B17="","",'PEDIDO WEPP'!H17) -> 2 | I17: =IF(B17="","",'PEDIDO WEPP'!I17) -> 2.95 | J17: =IF(B17="","",'PEDIDO WEPP'!J17) -> 5.9
B18: ='PEDIDO WEPP'!C18 -> 2010 SF | C18: =IF(B18="","",VLOOKUP(B18,DATOS!$F$3:$H$139,3,FALSE)) -> Motor System Reiniger (Lösungsmittelfrei) | D18: =IF(B18="","",'PEDIDO WEPP'!D18) -> 300 ml | E18: =IF(B18="","",'PEDIDO WEPP'!E18) -> unidad | F18: =IF(E18="CAJA","KISTE",IF(E18="unidad","STÜCK","")) -> STÜCK | G18: =IF(B18="","",'PEDIDO WEPP'!F18) -> 2 | H18: =IF(B18="","",'PEDIDO WEPP'!H18) -> 2 | I18: =IF(B18="","",'PEDIDO WEPP'!I18) -> 2.95 | J18: =IF(B18="","",'PEDIDO WEPP'!J18) -> 5.9
B19: ='PEDIDO WEPP'!C19 -> 2010 SF | C19: =IF(B19="","",VLOOKUP(B19,DATOS!$F$3:$H$139,3,FALSE)) -> Motor System Reiniger (Lösungsmittelfrei) | D19: =IF(B19="","",'PEDIDO WEPP'!D19) -> 300 ml | E19: =IF(B19="","",'PEDIDO WEPP'!E19) -> caja | F19: =IF(E19="CAJA","KISTE",IF(E19="unidad","STÜCK","")) -> KISTE | G19: =IF(B19="","",'PEDIDO WEPP'!F19) -> 2 | H19: =IF(B19="","",'PEDIDO WEPP'!H19) -> 48 | I19: =IF(B19="","",'PEDIDO WEPP'!I19) -> 2.95 | J19: =IF(B19="","",'PEDIDO WEPP'!J19) -> 141.6
B20: ='PEDIDO WEPP'!C20 -> 2010 SF | C20: =IF(B20="","",VLOOKUP(B20,DATOS!$F$3:$H$139,3,FALSE)) -> Motor System Reiniger (Lösungsmittelfrei) | D20: =IF(B20="","",'PEDIDO WEPP'!D20) -> 300 ml | E20: =IF(B20="","",'PEDIDO WEPP'!E20) -> caja | F20: =IF(E20="CAJA","KISTE",IF(E20="unidad","STÜCK","")) -> KISTE | G20: =IF(B20="","",'PEDIDO WEPP'!F20) -> 1 | H20: =IF(B20="","",'PEDIDO WEPP'!H20) -> 24 | I20: =IF(B20="","",'PEDIDO WEPP'!I20) -> 2.95 | J20: =IF(B20="","",'PEDIDO WEPP'!J20) -> 70.8
B21: ='PEDIDO WEPP'!C21 -> 2010 SF | C21: =IF(B21="","",VLOOKUP(B21,DATOS!$F$3:$H$139,3,FALSE)) -> Motor System Reiniger (Lösungsmittelfrei) | D21: =IF(B21="","",'PEDIDO WEPP'!D21) -> 300 ml | E21: =IF(B21="","",'PEDIDO WEPP'!E21) -> unidad | F21: =IF(E21="CAJA","KISTE",IF(E21="unidad","STÜCK","")) -> STÜCK | G21: =IF(B21="","",'PEDIDO WEPP'!F21) -> 12 | H21: =IF(B21="","",'PEDIDO WEPP'!H21) -> 12 | I21: =IF(B21="","",'PEDIDO WEPP'!I21) -> 2.95 | J21: =IF(B21="","",'PEDIDO WEPP'!J21) -> 35.4
... B29: ='PEDIDO WEPP'!C29 -> 2010 SF | C29: =IF(B29="","",VLOOKUP(B29,DATOS!$F$3:$H$139,3,FALSE)) -> Motor System Reiniger (Lösungsmittelfrei) | D29: =IF(B29="","",'PEDIDO WEPP'!D29) -> 300 ml | E29: =IF(B29="","",'PEDIDO WEPP'!E29) -> unidad | F29: =IF(E29="CAJA","KISTE",IF(E29="unidad","STÜCK","")) -> STÜCK | G29: =IF(B29="","",'PEDIDO WEPP'!F29) -> 2 | H29: =IF(B29="","",'PEDIDO WEPP'!H29) -> 2 | I29: =IF(B29="","",'PEDIDO WEPP'!I29) -> 2.95 | J29: =IF(B29="","",'PEDIDO WEPP'!J29) -> 5.9
J30: =SUM(J10:J29) -> 1042.5
B32: PEDIDO | I32: Nº | J32: ='PEDIDO WEPP'!J32 -> 2025-0001
B33: Ref. | C33: PRODUKT | D33: Volumen | E33: Cantidad | G33: STÜCK | H33: Total | I33: Einzelpreis | J33: TOTAL
B34: ='PEDIDO WEPP'!C34 -> 7050250 | C34: =IF(B34="","",VLOOKUP(B34,DATOS!$F$3:$H$139,3,FALSE)) -> AC Leckindikator | D34: =IF(B34="","",'PEDIDO WEPP'!D34) -> 250 ml | E34: =IF(B34="","",'PEDIDO WEPP'!E34) -> unidad | F34: =IF(E34="CAJA","KISTE",IF(E34="unidad","STÜCK","")) -> STÜCK | G34: =IF(B34="","",'PEDIDO WEPP'!F34) -> 2 | H34: =IF(B34="","",'PEDIDO WEPP'!H34) -> 2 | I34: =IF(B34="","",'PEDIDO WEPP'!I34) -> 12.9 | J34: =IF(B34="","",'PEDIDO WEPP'!J34) -> 25.8
B35: ='PEDIDO WEPP'!C35 -> 7035001 | C35: =IF(B35="","",VLOOKUP(B35,DATOS!$F$3:$H$139,3,FALSE)) -> POE 68 + UV | D35: =IF(B35="","",'PEDIDO WEPP'!D35) -> 1000 ml | E35: =IF(B35="","",'PEDIDO WEPP'!E35) -> unidad | F35: =IF(E35="CAJA","KISTE",IF(E35="unidad","STÜCK","")) -> STÜCK | G35: =IF(B35="","",'PEDIDO WEPP'!F35) -> 2 | H35: =IF(B35="","",'PEDIDO WEPP'!H35) -> 2 | I35: =IF(B35="","",'PEDIDO WEPP'!I35) -> 13.85 | J35: =IF(B35="","",'PEDIDO WEPP'!J35) -> 27.7
B36: ='PEDIDO WEPP'!C36 -> 2030 | C36: =IF(B36="","",VLOOKUP(B36,DATOS!$F$3:$H$139,3,FALSE)) -> Diesel Intensiv Reiniger | D36: =IF(B36="","",'PEDIDO WEPP'!D36) -> 500 ml | E36: =IF(B36="","",'PEDIDO WEPP'!E36) -> caja | F36: =IF(E36="CAJA","KISTE",IF(E36="unidad","STÜCK","")) -> KISTE | G36: =IF(B36="","",'PEDIDO WEPP'!F36) -> 2 | H36: =IF(B36="","",'PEDIDO WEPP'!H36) -> 48 | I36: =IF(B36="","",'PEDIDO WEPP'!I36) -> 3.65 | J36: =IF(B36="","",'PEDIDO WEPP'!J36) -> 175.2
B37: ='PEDIDO WEPP'!C37 -> 2130 | C37: =IF(B37="","",VLOOKUP(B37,DATOS!$F$3:$H$139,3,FALSE)) -> Diesel Einlass Reiniger Spray | D37: =IF(B37="","",'PEDIDO WEPP'!D37) -> 400 ml | E37: =IF(B37="","",'PEDIDO WEPP'!E37) -> unidad | F37: =IF(E37="CAJA","KISTE",IF(E37="unidad","STÜCK","")) -> STÜCK | G37: =IF(B37="","",'PEDIDO WEPP'!F37) -> 2 | H37: =IF(B37="","",'PEDIDO WEPP'!H37) -> 2 | I37: =IF(B37="","",'PEDIDO WEPP'!I37) -> 3.95 | J37: =IF(B37="","",'PEDIDO WEPP'!J37) -> 7.9
B38: ='PEDIDO WEPP'!C38 -> 2230 | C38: =IF(B38="","",VLOOKUP(B38,DATOS!$F$3:$H$139,3,FALSE)) -> Turbo AGR Ansaugreiniger | D38: =IF(B38="","",'PEDIDO WEPP'!D38) -> 400 ml | E38: =IF(B38="","",'PEDIDO WEPP'!E38) -> unidad | F38: =IF(E38="CAJA","KISTE",IF(E38="unidad","STÜCK","")) -> STÜCK | G38: =IF(B38="","",'PEDIDO WEPP'!F38) -> 4 | H38: =IF(B38="","",'PEDIDO WEPP'!H38) -> 4 | I38: =IF(B38="","",'PEDIDO WEPP'!I38) -> 6.5 | J38: =IF(B38="","",'PEDIDO WEPP'!J38) -> 26
B39: ='PEDIDO WEPP'!C39 -> 2031 | C39: =IF(B39="","",VLOOKUP(B39,DATOS!$F$3:$H$139,3,FALSE)) -> Drosselklappen + Vergaserreiniger | D39: =IF(B39="","",'PEDIDO WEPP'!D39) -> 400 ml | E39: =IF(B39="","",'PEDIDO WEPP'!E39) -> unidad | F39: =IF(E39="CAJA","KISTE",IF(E39="unidad","STÜCK","")) -> STÜCK | G39: =IF(B39="","",'PEDIDO WEPP'!F39) -> 4 | H39: =IF(B39="","",'PEDIDO WEPP'!H39) -> 4 | I39: =IF(B39="","",'PEDIDO WEPP'!I39) -> 3.5 | J39: =IF(B39="","",'PEDIDO WEPP'!J39) -> 14
B40: ='PEDIDO WEPP'!C40 -> 2032-300 | C40: =IF(B40="","",VLOOKUP(B40,DATOS!$F$3:$H$139,3,FALSE)) -> Diesel System Schutz | D40: =IF(B40="","",'PEDIDO WEPP'!D40) -> 300 ml | E40: =IF(B40="","",'PEDIDO WEPP'!E40) -> caja | F40: =IF(E40="CAJA","KISTE",IF(E40="unidad","STÜCK","")) -> KISTE | G40: =IF(B40="","",'PEDIDO WEPP'!F40) -> 2 | H40: =IF(B40="","",'PEDIDO WEPP'!H40) -> 48 | I40: =IF(B40="","",'PEDIDO WEPP'!I40) -> 2.55 | J40: =IF(B40="","",'PEDIDO WEPP'!J40) -> 122.4
B41: ='PEDIDO WEPP'!C41 -> 2032+ | C41: =IF(B41="","",VLOOKUP(B41,DATOS!$F$3:$H$139,3,FALSE)) -> Diesel Complete Clean | D41: =IF(B41="","",'PEDIDO WEPP'!D41) -> 250 ml | E41: =IF(B41="","",'PEDIDO WEPP'!E41) -> caja | F41: =IF(E41="CAJA","KISTE",IF(E41="unidad","STÜCK","")) -> KISTE | G41: =IF(B41="","",'PEDIDO WEPP'!F41) -> 2 | H41: =IF(B41="","",'PEDIDO WEPP'!H41) -> 48 | I41: =IF(B41="","",'PEDIDO WEPP'!I41) -> 3.6 | J41: =IF(B41="","",'PEDIDO WEPP'!J41) -> 172.8
B42: ='PEDIDO WEPP'!C42 -> 732 | C42: =IF(B42="","",VLOOKUP(B42,DATOS!$F$3:$H$139,3,FALSE)) -> SCR Schutz | D42: =IF(B42="","",'PEDIDO WEPP'!D42) -> 50 ml | E42: =IF(B42="","",'PEDIDO WEPP'!E42) -> unidad | F42: =IF(E42="CAJA","KISTE",IF(E42="unidad","STÜCK","")) -> STÜCK | G42: =IF(B42="","",'PEDIDO WEPP'!F42) -> 20 | H42: =IF(B42="","",'PEDIDO WEPP'!H42) -> 20 | I42: =IF(B42="","",'PEDIDO WEPP'!I42) -> 1.2 | J42: =IF(B42="","",'PEDIDO WEPP'!J42) -> 24
B43: ='PEDIDO WEPP'!C43 -> 2132-300 | C43: =IF(B43="","",VLOOKUP(B43,DATOS!$F$3:$H$139,3,FALSE)) -> DPF/ Turbo Cleaner | D43: =IF(B43="","",'PEDIDO WEPP'!D43) -> 300 ml | E43: =IF(B43="","",'PEDIDO WEPP'!E43) -> caja | F43: =IF(E43="CAJA","KISTE",IF(E43="unidad","STÜCK","")) -> KISTE | G43: =IF(B43="","",'PEDIDO WEPP'!F43) -> 4 | H43: =IF(B43="","",'PEDIDO WEPP'!H43) -> 96 | I43: =IF(B43="","",'PEDIDO WEPP'!I43) -> 3.9 | J43: =IF(B43="","",'PEDIDO WEPP'!J43) -> 374.4
B44: ='PEDIDO WEPP'!C44 -> 2232 | C44: =IF(B44="","",VLOOKUP(B44,DATOS!$F$3:$H$139,3,FALSE)) -> DPF Direct Cleaner | D44: =IF(B44="","",'PEDIDO WEPP'!D44) -> 500 ml | E44: =IF(B44="","",'PEDIDO WEPP'!E44) -> unidad | F44: =IF(E44="CAJA","KISTE",IF(E44="unidad","STÜCK","")) -> STÜCK | G44: =IF(B44="","",'PEDIDO WEPP'!F44) -> 1 | H44: =IF(B44="","",'PEDIDO WEPP'!H44) -> 1 | I44: =IF(B44="","",'PEDIDO WEPP'!I44) -> 6.85 | J44: =IF(B44="","",'PEDIDO WEPP'!J44) -> 6.85
B45: ='PEDIDO WEPP'!C45 -> 39001 | C45: =IF(B45="","",VLOOKUP(B45,DATOS!$F$3:$H$139,3,FALSE)) -> Hohlraumschlauch | D45: =IF(B45="","",'PEDIDO WEPP'!D45) -> - ml | E45: =IF(B45="","",'PEDIDO WEPP'!E45) -> unidad | F45: =IF(E45="CAJA","KISTE",IF(E45="unidad","STÜCK","")) -> STÜCK | G45: =IF(B45="","",'PEDIDO WEPP'!F45) -> 1 | H45: =IF(B45="","",'PEDIDO WEPP'!H45) -> 1 | I45: =IF(B45="","",'PEDIDO WEPP'!I45) -> 20 | J45: =IF(B45="","",'PEDIDO WEPP'!J45) -> 20
... B61: ='PEDIDO WEPP'!C61 -> 2043 | C61: =IF(B61="","",VLOOKUP(B61,DATOS!$F$3:$H$139,3,FALSE)) -> Wartungs Haftöl | D61: =IF(B61="","",'PEDIDO WEPP'!D61) -> 400 ml | E61: =IF(B61="","",'PEDIDO WEPP'!E61) -> unidad | F61: =IF(E61="CAJA","KISTE",IF(E61="unidad","STÜCK","")) -> STÜCK | G61: =IF(B61="","",'PEDIDO WEPP'!F61) -> 4 | H61: =IF(B61="","",'PEDIDO WEPP'!H61) -> 4 | I61: =IF(B61="","",'PEDIDO WEPP'!I61) -> 3.15 | J61: =IF(B61="","",'PEDIDO WEPP'!J61) -> 12.6
J62: =SUM(J34:J61) -> 1718.05
B63: PEDIDO | I63: Nº | J63: ='PEDIDO WEPP'!J63 -> 2025-0001
B64: Ref. | C64: PRODUKT | D64: Volumen | E64: Cantidad | G64: STÜCK | H64: Total | I64: Einzelpreis | J64: TOTAL
B65: ='PEDIDO WEPP'!C65 -> 2045 | C65: =IF(B65="","",VLOOKUP(B65,DATOS!$F$3:$H$139,3,FALSE)) -> Silikon Gleitfett | D65: =IF(B65="","",'PEDIDO WEPP'!D65) -> 400 ml | E65: =IF(B65="","",'PEDIDO WEPP'!E65) -> unidad | F65: =IF(E65="CAJA","KISTE",IF(E65="unidad","STÜCK","")) -> STÜCK | G65: =IF(B65="","",'PEDIDO WEPP'!F65) -> 2 | H65: =IF(B65="","",'PEDIDO WEPP'!H65) -> 2 | I65: =IF(B65="","",'PEDIDO WEPP'!I65) -> 3.9 | J65: =IF(B65="","",'PEDIDO WEPP'!J65) -> 7.8
B66: ='PEDIDO WEPP'!C66 -> 2246 | C66: =IF(B66="","",VLOOKUP(B66,DATOS!$F$3:$H$139,3,FALSE)) -> Super Rostlöser Active | D66: =IF(B66="","",'PEDIDO WEPP'!D66) -> 400 ml | E66: =IF(B66="","",'PEDIDO WEPP'!E66) -> caja | F66: =IF(E66="CAJA","KISTE",IF(E66="unidad","STÜCK","")) -> KISTE | G66: =IF(B66="","",'PEDIDO WEPP'!F66) -> 2 | H66: =IF(B66="","",'PEDIDO WEPP'!H66) -> 48 | I66: =IF(B66="","",'PEDIDO WEPP'!I66) -> 3.75 | J66: =IF(B66="","",'PEDIDO WEPP'!J66) -> 180
B67: ='PEDIDO WEPP'!C67 -> 2047 | C67: =IF(B67="","",VLOOKUP(B67,DATOS!$F$3:$H$139,3,FALSE)) -> Silikonspray | D67: =IF(B67="","",'PEDIDO WEPP'!D67) -> 400 ml | E67: =IF(B67="","",'PEDIDO WEPP'!E67) -> unidad | F67: =IF(E67="CAJA","KISTE",IF(E67="unidad","STÜCK","")) -> STÜCK | G67: =IF(B67="","",'PEDIDO WEPP'!F67) -> 4 | H67: =IF(B67="","",'PEDIDO WEPP'!H67) -> 4 | I67: =IF(B67="","",'PEDIDO WEPP'!I67) -> 2.5 | J67: =IF(B67="","",'PEDIDO WEPP'!J67) -> 10
B68: ='PEDIDO WEPP'!C68 -> 2048 | C68: =IF(B68="","",VLOOKUP(B68,DATOS!$F$3:$H$139,3,FALSE)) -> Rostlöser MOS2 | D68: =IF(B68="","",'PEDIDO WEPP'!D68) -> 400 ml | E68: =IF(B68="","",'PEDIDO WEPP'!E68) -> unidad | F68: =IF(E68="CAJA","KISTE",IF(E68="unidad","STÜCK","")) -> STÜCK | G68: =IF(B68="","",'PEDIDO WEPP'!F68) -> 4 | H68: =IF(B68="","",'PEDIDO WEPP'!H68) -> 4 | I68: =IF(B68="","",'PEDIDO WEPP'!I68) -> 2.35 | J68: =IF(B68="","",'PEDIDO WEPP'!J68) -> 9.4
B69: ='PEDIDO WEPP'!C69 -> 2053 | C69: =IF(B69="","",VLOOKUP(B69,DATOS!$F$3:$H$139,3,FALSE)) -> Innenraumspray | D69: =IF(B69="","",'PEDIDO WEPP'!D69) -> 400 ml | E69: =IF(B69="","",'PEDIDO WEPP'!E69) -> caja | F69: =IF(E69="CAJA","KISTE",IF(E69="unidad","STÜCK","")) -> KISTE | G69: =IF(B69="","",'PEDIDO WEPP'!F69) -> 1 | H69: =IF(B69="","",'PEDIDO WEPP'!H69) -> 24 | I69: =IF(B69="","",'PEDIDO WEPP'!I69) -> 3.5 | J69: =IF(B69="","",'PEDIDO WEPP'!J69) -> 84
B70: ='PEDIDO WEPP'!C70 -> 2054 | C70: =IF(B70="","",VLOOKUP(B70,DATOS!$F$3:$H$139,3,FALSE)) -> Ölspray Mit PTFE | D70: =IF(B70="","",'PEDIDO WEPP'!D70) -> 400 ml | E70: =IF(B70="","",'PEDIDO WEPP'!E70) -> unidad | F70: =IF(E70="CAJA","KISTE",IF(E70="unidad","STÜCK","")) -> STÜCK | G70: =IF(B70="","",'PEDIDO WEPP'!F70) -> 4 | H70: =IF(B70="","",'PEDIDO WEPP'!H70) -> 4 | I70: =IF(B70="","",'PEDIDO WEPP'!I70) -> 4.8 | J70: =IF(B70="","",'PEDIDO WEPP'!J70) -> 19.2
B71: ='PEDIDO WEPP'!C71 -> 2056 | C71: =IF(B71="","",VLOOKUP(B71,DATOS!$F$3:$H$139,3,FALSE)) -> Fettspray Mit PTFE | D71: =IF(B71="","",'PEDIDO WEPP'!D71) -> 400 ml | E71: =IF(B71="","",'PEDIDO WEPP'!E71) -> unidad | F71: =IF(E71="CAJA","KISTE",IF(E71="unidad","STÜCK","")) -> STÜCK | G71: =IF(B71="","",'PEDIDO WEPP'!F71) -> 4 | H71: =IF(B71="","",'PEDIDO WEPP'!H71) -> 4 | I71: =IF(B71="","",'PEDIDO WEPP'!I71) -> 4.8 | J71: =IF(B71="","",'PEDIDO WEPP'!J71) -> 19.2
B72: ='PEDIDO WEPP'!C72 -> 2059 | C72: =IF(B72="","",VLOOKUP(B72,DATOS!$F$3:$H$139,3,FALSE)) -> Kupferspray | D72: =IF(B72="","",'PEDIDO WEPP'!D72) -> 400 ml | E72: =IF(B72="","",'PEDIDO WEPP'!E72) -> unidad | F72: =IF(E72="CAJA","KISTE",IF(E72="unidad","STÜCK","")) -> STÜCK | G72: =IF(B72="","",'PEDIDO WEPP'!F72) -> 4 | H72: =IF(B72="","",'PEDIDO WEPP'!H72) -> 4 | I72: =IF(B72="","",'PEDIDO WEPP'!I72) -> 3.9 | J72: =IF(B72="","",'PEDIDO WEPP'!J72) -> 15.6
B73: ='PEDIDO WEPP'!C73 -> 2060 | C73: =IF(B73="","",VLOOKUP(B73,DATOS!$F$3:$H$139,3,FALSE)) -> Bremsenreiniger Acetonfrei | D73: =IF(B73="","",'PEDIDO WEPP'!D73) -> 400 ml | E73: =IF(B73="","",'PEDIDO WEPP'!E73) -> caja | F73: =IF(E73="CAJA","KISTE",IF(E73="unidad","STÜCK","")) -> KISTE | G73: =IF(B73="","",'PEDIDO WEPP'!F73) -> 1 | H73: =IF(B73="","",'PEDIDO WEPP'!H73) -> 12 | I73: =IF(B73="","",'PEDIDO WEPP'!I73) -> 1.9 | J73: =IF(B73="","",'PEDIDO WEPP'!J73) -> 22.8
B74: ='PEDIDO WEPP'!C74 -> 2117 | C74: =IF(B74="","",VLOOKUP(B74,DATOS!$F$3:$H$139,3,FALSE)) -> Sicherheitsreiniger | D74: =IF(B74="","",'PEDIDO WEPP'!D74) -> 500 ml | E74: =IF(B74="","",'PEDIDO WEPP'!E74) -> unidad | F74: =IF(E74="CAJA","KISTE",IF(E74="unidad","STÜCK","")) -> STÜCK | G74: =IF(B74="","",'PEDIDO WEPP'!F74) -> 4 | H74: =IF(B74="","",'PEDIDO WEPP'!H74) -> 4 | I74: =IF(B74="","",'PEDIDO WEPP'!I74) -> 0 | J74: =IF(B74="","",'PEDIDO WEPP'!J74) -> 0
B75: ='PEDIDO WEPP'!C75 -> 2061 | C75: =IF(B75="","",VLOOKUP(B75,DATOS!$F$3:$H$139,3,FALSE)) -> Multi Komplex Reiniger (Scheiben) | D75: =IF(B75="","",'PEDIDO WEPP'!D75) -> 500 ml | E75: =IF(B75="","",'PEDIDO WEPP'!E75) -> unidad | F75: =IF(E75="CAJA","KISTE",IF(E75="unidad","STÜCK","")) -> STÜCK | G75: =IF(B75="","",'PEDIDO WEPP'!F75) -> 4 | H75: =IF(B75="","",'PEDIDO WEPP'!H75) -> 4 | I75: =IF(B75="","",'PEDIDO WEPP'!I75) -> 3.2 | J75: =IF(B75="","",'PEDIDO WEPP'!J75) -> 12.8
B76: ='PEDIDO WEPP'!C76 -> 2070 | C76: =IF(B76="","",VLOOKUP(B76,DATOS!$F$3:$H$139,3,FALSE)) -> Elektronik Reiniger Spray | D76: =IF(B76="","",'PEDIDO WEPP'!D76) -> 400 ml | E76: =IF(B76="","",'PEDIDO WEPP'!E76) -> unidad | F76: =IF(E76="CAJA","KISTE",IF(E76="unidad","STÜCK","")) -> STÜCK | G76: =IF(B76="","",'PEDIDO WEPP'!F76) -> 4 | H76: =IF(B76="","",'PEDIDO WEPP'!H76) -> 4 | I76: =IF(B76="","",'PEDIDO WEPP'!I76) -> 3.45 | J76: =IF(B76="","",'PEDIDO WEPP'!J76) -> 13.8
... B92: ='PEDIDO WEPP'!C92 -> 20648-08 | C92: =IF(B92="","",VLOOKUP(B92,DATOS!$F$3:$H$139,3,FALSE)) -> Hand Schuhe 8 | D92: =IF(B92="","",'PEDIDO WEPP'!D92) -> - ml | E92: =IF(B92="","",'PEDIDO WEPP'!E92) -> unidad | F92: =IF(E92="CAJA","KISTE",IF(E92="unidad","STÜCK","")) -> STÜCK | G92: =IF(B92="","",'PEDIDO WEPP'!F92) -> 12 | H92: =IF(B92="","",'PEDIDO WEPP'!H92) -> 12 | I92: =IF(B92="","",'PEDIDO WEPP'!I92) -> 0.95 | J92: =IF(B92="","",'PEDIDO WEPP'!J92) -> 11.4
J93: =SUM(J65:J92) -> 766.85
B94: PEDIDO | I94: Nº | J94: ='PEDIDO WEPP'!J94 -> 2025-0001
B95: Ref. | C95: PRODUKT | D95: Volumen | E95: Cantidad | G95: STÜCK | H95: Total | I95: Einzelpreis | J95: TOTAL
B96: ='PEDIDO WEPP'!C96 -> 20648-09 | C96: =IF(B96="","",VLOOKUP(B96,DATOS!$F$3:$H$139,3,FALSE)) -> Hand Schuhe 9 | D96: =IF(B96="","",'PEDIDO WEPP'!D96) -> - ml | E96: =IF(B96="","",'PEDIDO WEPP'!E96) -> unidad | F96: =IF(E96="CAJA","KISTE",IF(E96="unidad","STÜCK","")) -> STÜCK | G96: =IF(B96="","",'PEDIDO WEPP'!F96) -> 12 | H96: =IF(B96="","",'PEDIDO WEPP'!H96) -> 12 | I96: =IF(B96="","",'PEDIDO WEPP'!I96) -> 0.95 | J96: =IF(B96="","",'PEDIDO WEPP'!J96) -> 11.4
B97: ='PEDIDO WEPP'!C97 -> 20648-10 | C97: =IF(B97="","",VLOOKUP(B97,DATOS!$F$3:$H$139,3,FALSE)) -> Hand Schuhe 10 | D97: =IF(B97="","",'PEDIDO WEPP'!D97) -> - ml | E97: =IF(B97="","",'PEDIDO WEPP'!E97) -> unidad | F97: =IF(E97="CAJA","KISTE",IF(E97="unidad","STÜCK","")) -> STÜCK | G97: =IF(B97="","",'PEDIDO WEPP'!F97) -> 12 | H97: =IF(B97="","",'PEDIDO WEPP'!H97) -> 12 | I97: =IF(B97="","",'PEDIDO WEPP'!I97) -> 0.95 | J97: =IF(B97="","",'PEDIDO WEPP'!J97) -> 11.4
B98: ='PEDIDO WEPP'!C98 | C98: =IF(B98="","",VLOOKUP(B98,DATOS!$F$3:$H$139,3,FALSE)) | D98: =IF(B98="","",'PEDIDO WEPP'!D98) | E98: =IF(B98="","",'PEDIDO WEPP'!E98) | F98: =IF(E98="CAJA","KISTE",IF(E98="unidad","STÜCK","")) | G98: =IF(B98="","",'PEDIDO WEPP'!F98) | H98: =IF(B98="","",'PEDIDO WEPP'!H98) | I98: =IF(B98="","",'PEDIDO WEPP'!I98) | J98: =IF(B98="","",'PEDIDO WEPP'!J98)
B99: ='PEDIDO WEPP'!C99 | C99: =IF(B99="","",VLOOKUP(B99,DATOS!$F$3:$H$139,3,FALSE)) | D99: =IF(B99="","",'PEDIDO WEPP'!D99) | E99: =IF(B99="","",'PEDIDO WEPP'!E99) | F99: =IF(E99="CAJA","KISTE",IF(E99="unidad","STÜCK","")) | G99: =IF(B99="","",'PEDIDO WEPP'!F99) | H99: =IF(B99="","",'PEDIDO WEPP'!H99) | I99: =IF(B99="","",'PEDIDO WEPP'!I99) | J99: =IF(B99="","",'PEDIDO WEPP'!J99)
B100: ='PEDIDO WEPP'!C100 | C100: =IF(B100="","",VLOOKUP(B100,DATOS!$F$3:$H$139,3,FALSE)) | D100: =IF(B100="","",'PEDIDO WEPP'!D100) | E100: =IF(B100="","",'PEDIDO WEPP'!E100) | F100: =IF(E100="CAJA","KISTE",IF(E100="unidad","STÜCK","")) | G100: =IF(B100="","",'PEDIDO WEPP'!F100) | H100: =IF(B100="","",'PEDIDO WEPP'!H100) | I100: =IF(B100="","",'PEDIDO WEPP'!I100) | J100: =IF(B100="","",'PEDIDO WEPP'!J100)
B101: ='PEDIDO WEPP'!C101 | C101: =IF(B101="","",VLOOKUP(B101,DATOS!$F$3:$H$139,3,FALSE)) | D101: =IF(B101="","",'PEDIDO WEPP'!D101) | E101: =IF(B101="","",'PEDIDO WEPP'!E101) | F101: =IF(E101="CAJA","KISTE",IF(E101="unidad","STÜCK","")) | G101: =IF(B101="","",'PEDIDO WEPP'!F101) | H101: =IF(B101="","",'PEDIDO WEPP'!H101) | I101: =IF(B101="","",'PEDIDO WEPP'!I101) | J101: =IF(B101="","",'PEDIDO WEPP'!J101)
B102: ='PEDIDO WEPP'!C102 | C102: =IF(B102="","",VLOOKUP(B102,DATOS!$F$3:$H$139,3,FALSE)) | D102: =IF(B102="","",'PEDIDO WEPP'!D102) | E102: =IF(B102="","",'PEDIDO WEPP'!E102) | F102: =IF(E102="CAJA","KISTE",IF(E102="unidad","STÜCK","")) | G102: =IF(B102="","",'PEDIDO WEPP'!F102) | H102: =IF(B102="","",'PEDIDO WEPP'!H102) | I102: =IF(B102="","",'PEDIDO WEPP'!I102) | J102: =IF(B102="","",'PEDIDO WEPP'!J102)
B103: ='PEDIDO WEPP'!C103 | C103: =IF(B103="","",VLOOKUP(B103,DATOS!$F$3:$H$139,3,FALSE)) | D103: =IF(B103="","",'PEDIDO WEPP'!D103) | E103: =IF(B103="","",'PEDIDO WEPP'!E103) | F103: =IF(E103="CAJA","KISTE",IF(E103="unidad","STÜCK","")) | G103: =IF(B103="","",'PEDIDO WEPP'!F103) | H103: =IF(B103="","",'PEDIDO WEPP'!H103) | I103: =IF(B103="","",'PEDIDO WEPP'!I103) | J103: =IF(B103="","",'PEDIDO WEPP'!J103)
B104: ='PEDIDO WEPP'!C104 | C104: =IF(B104="","",VLOOKUP(B104,DATOS!$F$3:$H$139,3,FALSE)) | D104: =IF(B104="","",'PEDIDO WEPP'!D104) | E104: =IF(B104="","",'PEDIDO WEPP'!E104) | F104: =IF(E104="CAJA","KISTE",IF(E104="unidad","STÜCK","")) | G104: =IF(B104="","",'PEDIDO WEPP'!F104) | H104: =IF(B104="","",'PEDIDO WEPP'!H104) | I104: =IF(B104="","",'PEDIDO WEPP'!I104) | J104: =IF(B104="","",'PEDIDO WEPP'!J104)
B105: ='PEDIDO WEPP'!C105 | C105: =IF(B105="","",VLOOKUP(B105,DATOS!$F$3:$H$139,3,FALSE)) | D105: =IF(B105="","",'PEDIDO WEPP'!D105) | E105: =IF(B105="","",'PEDIDO WEPP'!E105) | F105: =IF(E105="CAJA","KISTE",IF(E105="unidad","STÜCK","")) | G105: =IF(B105="","",'PEDIDO WEPP'!F105) | H105: =IF(B105="","",'PEDIDO WEPP'!H105) | I105: =IF(B105="","",'PEDIDO WEPP'!I105) | J105: =IF(B105="","",'PEDIDO WEPP'!J105)
B106: ='PEDIDO WEPP'!C106 | C106: =IF(B106="","",VLOOKUP(B106,DATOS!$F$3:$H$139,3,FALSE)) | D106: =IF(B106="","",'PEDIDO WEPP'!D106) | E106: =IF(B106="","",'PEDIDO WEPP'!E106) | F106: =IF(E106="CAJA","KISTE",IF(E106="unidad","STÜCK","")) | G106: =IF(B106="","",'PEDIDO WEPP'!F106) | H106: =IF(B106="","",'PEDIDO WEPP'!H106) | I106: =IF(B106="","",'PEDIDO WEPP'!I106) | J106: =IF(B106="","",'PEDIDO WEPP'!J106)
B107: ='PEDIDO WEPP'!C107 | C107: =IF(B107="","",VLOOKUP(B107,DATOS!$F$3:$H$139,3,FALSE)) | D107: =IF(B107="","",'PEDIDO WEPP'!D107) | E107: =IF(B107="","",'PEDIDO WEPP'!E107) | F107: =IF(E107="CAJA","KISTE",IF(E107="unidad","STÜCK","")) | G107: =IF(B107="","",'PEDIDO WEPP'!F107) | H107: =IF(B107="","",'PEDIDO WEPP'!H107) | I107: =IF(B107="","",'PEDIDO WEPP'!I107) | J107: =IF(B107="","",'PEDIDO WEPP'!J107)
... B123: ='PEDIDO WEPP'!C123 | C123: =IF(B123="","",VLOOKUP(B123,DATOS!$F$3:$H$139,3,FALSE)) | D123: =IF(B123="","",'PEDIDO WEPP'!D123) | E123: =IF(B123="","",'PEDIDO WEPP'!E123) | F123: =IF(E123="CAJA","KISTE",IF(E123="unidad","STÜCK","")) | G123: =IF(B123="","",'PEDIDO WEPP'!F123) | H123: =IF(B123="","",'PEDIDO WEPP'!H123) | I123: =IF(B123="","",'PEDIDO WEPP'!I123) | J123: =IF(B123="","",'PEDIDO WEPP'!J123)
J124: =SUM(J96:J123)+J93+J62+J30 -> 3550.2

Sheet CLIENTE PEDIDO
B1: DATOS CLIENTE
B2: Razón Social:
B3: CIF:
B4: Dirección:
B5: Dirección envío:
B6: Teléfono:
B7: Correo Electrónico:
B8: FACTURA PROFORMA | I8: Nº | M8: 2025-1
B9: Descripción | C9: Ref. | D9: Volumen | E9: Cantidad | F9: Unidad | G9: ocultar | H9: Total | I9: Precio ud | J9: ocultar | K9: ocultar | L9: ocultar | M9: Dto(%) | N9: ocultar | O9: Total B.I. | V9: unidad
A10: motor | B10: Limpiador de Motor SF (sin disolventes) | C10: =IF(B10="-","",VLOOKUP(B10,DATOS!$I$3:$K$200,2,FALSE)) -> 2010 SF | D10: =IF(B10="-","",CONCATENATE(VLOOKUP(C10,DATOS!$J$3:$K$200,2,FALSE)," ml")) -> 300 ml | E10: unidad | F10: 12 | G10: =IF(B10="-","",IF(E10="caja",VLOOKUP(B10,DATOS!$I$3:$AC$137,21,FALSE),F10)) -> 12 | H10: =IF(B10="-","",IF(E10="caja",F10*G10,F10)) -> 12 | I10: =IF(B10="-","",VLOOKUP(B10,DATOS!$I$3:$S$138,11,FALSE)) -> 10.285 | J10: =IF(B10="-","",H10*I10) -> 123.42 | K10: =VLOOKUP(B10,DATOS!$I$3:$AD$138,19,FALSE) -> 8 | L10: =IF(E10="caja",VLOOKUP(B10,DATOS!$I$3:$AD$138,22,FALSE),VLOOKUP(B10,DATOS!$I$3:$AD$138,20,FALSE)) -> 5 | M10: =IF(B10="-","",IF(E10="caja",L10,IF(F10>K10,L10,"0"))) -> 5 | N10: =IF(B10="-","",(100-M10)/100) -> 0.95 | O10: =IF(B10="-","",J10*N10) -> 117.249 | Q10: =I10*0.21*N10 -> 2.0518575 | R10: =I10*N10+Q10 -> 11.822608 | S10: =R10*H10 -> 141.87129 | V10: caja
A11: refrigeracion | B11: Protector del Sistema de Refrigeración | C11: =IF(B11="-","",VLOOKUP(B11,DATOS!$I$3:$K$200,2,FALSE)) -> 2020 | D11: =IF(B11="-","",CONCATENATE(VLOOKUP(C11,DATOS!$J$3:$K$200,2,FALSE)," ml")) -> 300 ml | E11: caja | F11: 1 | G11: =IF(B11="-","",IF(E11="caja",VLOOKUP(B11,DATOS!$I$3:$AC$137,21,FALSE),F11)) -> 24 | H11: =IF(B11="-","",IF(E11="caja",F11*G11,F11)) -> 24 | I11: =IF(B11="-","",VLOOKUP(B11,DATOS!$I$3:$S$138,11,FALSE)) -> 8.47 | J11: =IF(B11="-","",H11*I11) -> 203.28 | K11: =VLOOKUP(B11,DATOS!$I$3:$AD$138,19,FALSE) -> 8 | L11: =IF(E11="caja",VLOOKUP(B11,DATOS!$I$3:$AD$138,22,FALSE),VLOOKUP(B11,DATOS!$I$3:$AD$138,20,FALSE)) -> 15 | M11: =IF(B11="-","",IF(E11="caja",L11,IF(F11>K11,L11,"0"))) -> 15 | N11: =IF(B11="-","",(100-M11)/100) -> 0.85 | O11: =IF(B11="-","",J11*N11) -> 172.788 | Q11: =I11*0.21*N11 -> 1.511895 | R11: =I11*N11+Q11 -> 8.711395 | S11: =R11*H11 -> 209.07348
A12: climatizacion | B12: Airfresh Menta | C12: =IF(B12="-","",VLOOKUP(B12,DATOS!$I$3:$K$200,2,FALSE)) -> 2125 | D12: =IF(B12="-","",CONCATENATE(VLOOKUP(C12,DATOS!$J$3:$K$200,2,FALSE)," ml")) -> 100 ml | E12: caja | F12: 1 | G12: =IF(B12="-","",IF(E12="caja",VLOOKUP(B12,DATOS!$I$3:$AC$137,21,FALSE),F12)) -> 24 | H12: =IF(B12="-","",IF(E12="caja",F12*G12,F12)) -> 24 | I12: =IF(B12="-","",VLOOKUP(B12,DATOS!$I$3:$S$138,11,FALSE)) -> 10.175 | J12: =IF(B12="-","",H12*I12) -> 244.2 | K12: =VLOOKUP(B12,DATOS!$I$3:$AD$138,19,FALSE) -> 8 | L12: =IF(E12="caja",VLOOKUP(B12,DATOS!$I$3:$AD$138,22,FALSE),VLOOKUP(B12,DATOS!$I$3:$AD$138,20,FALSE)) -> 15 | M12: =IF(B12="-","",IF(E12="caja",L12,IF(F12>K12,L12,"0"))) -> 15 | N12: =IF(B12="-","",(100-M12)/100) -> 0.85 | O12: =IF(B12="-","",J12*N12) -> 207.57 | Q12: =I12*0.21*N12 -> 1.8162375 | R12: =I12*N12+Q12 -> 10.464987 | S12: =R12*H12 -> 251.1597
A13: combustion | B13: Limpiador Intensivo Diésel | C13: =IF(B13="-","",VLOOKUP(B13,DATOS!$I$3:$K$200,2,FALSE)) -> 2030 | D13: =IF(B13="-","",CONCATENATE(VLOOKUP(C13,DATOS!$J$3:$K$200,2,FALSE)," ml")) -> 500 ml | E13: unidad | F13: 3 | G13: =IF(B13="-","",IF(E13="caja",VLOOKUP(B13,DATOS!$I$3:$AC$137,21,FALSE),F13)) -> 3 | H13: =IF(B13="-","",IF(E13="caja",F13*G13,F13)) -> 3 | I13: =IF(B13="-","",VLOOKUP(B13,DATOS!$I$3:$S$138,11,FALSE)) -> 9.955 | J13: =IF(B13="-","",H13*I13) -> 29.865 | K13: =VLOOKUP(B13,DATOS!$I$3:$AD$138,19,FALSE) -> 8 | L13: =IF(E13="caja",VLOOKUP(B13,DATOS!$I$3:$AD$138,22,FALSE),VLOOKUP(B13,DATOS!$I$3:$AD$138,20,FALSE)) -> 5 | M13: =IF(B13="-","",IF(E13="caja",L13,IF(F13>K13,L13,"0"))) -> 0 | N13: =IF(B13="-","",(100-M13)/100) -> 1 | O13: =IF(B13="-","",J13*N13) -> 29.865 | Q13: =I13*0.21*N13 -> 2.09055 | R13: =I13*N13+Q13 -> 12.04555 | S13: =R13*H13 -> 36.13665
A14: frenos | B14: Frenos Hi Tec | C14: =IF(B14="-","",VLOOKUP(B14,DATOS!$I$3:$K$200,2,FALSE)) -> 255 | D14: =IF(B14="-","",CONCATENATE(VLOOKUP(C14,DATOS!$J$3:$K$200,2,FALSE)," ml")) -> 400 ml | E14: unidad | F14: 5 | G14: =IF(B14="-","",IF(E14="caja",VLOOKUP(B14,DATOS!$I$3:$AC$137,21,FALSE),F14)) -> 5 | H14: =IF(B14="-","",IF(E14="caja",F14*G14,F14)) -> 5 | I14: =IF(B14="-","",VLOOKUP(B14,DATOS!$I$3:$S$138,11,FALSE)) -> 11.66 | J14: =IF(B14="-","",H14*I14) -> 58.3 | K14: =VLOOKUP(B14,DATOS!$I$3:$AD$138,19,FALSE) -> 8 | L14: =IF(E14="caja",VLOOKUP(B14,DATOS!$I$3:$AD$138,22,FALSE),VLOOKUP(B14,DATOS!$I$3:$AD$138,20,FALSE)) -> 5 | M14: =IF(B14="-","",IF(E14="caja",L14,IF(F14>K14,L14,"0"))) -> 0 | N14: =IF(B14="-","",(100-M14)/100) -> 1 | O14: =IF(B14="-","",J14*N14) -> 58.3 | Q14: =I14*0.21*N14 -> 2.4486 | R14: =I14*N14+Q14 -> 14.1086 | S14: =R14*H14 -> 70.543
A15: mantenimiento | B15: - | C15: =IF(B15="-","",VLOOKUP(B15,DATOS!$I$3:$K$200,2,FALSE)) | D15: =IF(B15="-","",CONCATENATE(VLOOKUP(C15,DATOS!$J$3:$K$200,2,FALSE)," ml")) | G15: =IF(B15="-","",IF(E15="caja",VLOOKUP(B15,DATOS!$I$3:$AC$137,21,FALSE),F15)) | H15: =IF(B15="-","",IF(E15="caja",F15*G15,F15)) | I15: =IF(B15="-","",VLOOKUP(B15,DATOS!$I$3:$S$138,11,FALSE)) | J15: =IF(B15="-","",H15*I15) | K15: =VLOOKUP(B15,DATOS!$I$3:$AD$138,19,FALSE) -> 0 | L15: =IF(E15="caja",VLOOKUP(B15,DATOS!$I$3:$AD$138,22,FALSE),VLOOKUP(B15,DATOS!$I$3:$AD$138,20,FALSE)) -> 5 | M15: =IF(B15="-","",IF(E15="caja",L15,IF(F15>K15,L15,"0"))) | N15: =IF(B15="-","",(100-M15)/100) | O15: =IF(B15="-","",J15*N15)
A16: carroceria | B16: - | C16: =IF(B16="-","",VLOOKUP(B16,DATOS!$I$3:$K$200,2,FALSE)) | D16: =IF(B16="-","",CONCATENATE(VLOOKUP(C16,DATOS!$J$3:$K$200,2,FALSE)," ml")) | G16: =IF(B16="-","",IF(E16="caja",VLOOKUP(B16,DATOS!$I$3:$AC$137,21,FALSE),F16)) | H16: =IF(B16="-","",IF(E16="caja",F16*G16,F16)) | I16: =IF(B16="-","",VLOOKUP(B16,DATOS!$I$3:$S$138,11,FALSE)) | J16: =IF(B16="-","",H16*I16) | K16: =VLOOKUP(B16,DATOS!$I$3:$AD$138,19,FALSE) -> 0 | L16: =IF(E16="caja",VLOOKUP(B16,DATOS!$I$3:$AD$138,22,FALSE),VLOOKUP(B16,DATOS!$I$3:$AD$138,20,FALSE)) -> 5 | M16: =IF(B16="-","",IF(E16="caja",L16,IF(F16>K16,L16,"0"))) | N16: =IF(B16="-","",(100-M16)/100) | O16: =IF(B16="-","",J16*N16)
A17: refrigeracion | B17: - | C17: =IF(B17="-","",VLOOKUP(B17,DATOS!$I$3:$K$200,2,FALSE)) | D17: =IF(B17="-","",CONCATENATE(VLOOKUP(C17,DATOS!$J$3:$K$200,2,FALSE)," ml")) | G17: =IF(B17="-","",IF(E17="caja",VLOOKUP(B17,DATOS!$I$3:$AC$137,21,FALSE),F17)) | H17: =IF(B17="-","",IF(E17="caja",F17*G17,F17)) | I17: =IF(B17="-","",VLOOKUP(B17,DATOS!$I$3:$S$138,11,FALSE)) | J17: =IF(B17="-","",H17*I17) | K17: =VLOOKUP(B17,DATOS!$I$3:$AD$138,19,FALSE) -> 0 | L17: =IF(E17="caja",VLOOKUP(B17,DATOS!$I$3:$AD$138,22,FALSE),VLOOKUP(B17,DATOS!$I$3:$AD$138,20,FALSE)) -> 5 | M17: =IF(B17="-","",IF(E17="caja",L17,IF(F17>K17,L17,"0"))) | N17: =IF(B17="-","",(100-M17)/100) | O17: =IF(B17="-","",J17*N17)
A18: climatizacion | B18: - | C18: =IF(B18="-","",VLOOKUP(B18,DATOS!$I$3:$K$200,2,FALSE)) | D18: =IF(B18="-","",CONCATENATE(VLOOKUP(C18,DATOS!$J$3:$K$200,2,FALSE)," ml")) | G18: =IF(B18="-","",IF(E18="caja",VLOOKUP(B18,DATOS!$I$3:$AC$137,21,FALSE),F18)) | H18: =IF(B18="-","",IF(E18="caja",F18*G18,F18)) | I18: =IF(B18="-","",VLOOKUP(B18,DATOS!$I$3:$S$138,11,FALSE)) | J18: =IF(B18="-","",H18*I18) | K18: =VLOOKUP(B18,DATOS!$I$3:$AD$138,19,FALSE) -> 0 | L18: =IF(E18="caja",VLOOKUP(B18,DATOS!$I$3:$AD$138,22,FALSE),VLOOKUP(B18,DATOS!$I$3:$AD$138,20,FALSE)) -> 5 | M18: =IF(B18="-","",IF(E18="caja",L18,IF(F18>K18,L18,"0"))) | N18: =IF(B18="-","",(100-M18)/100) | O18: =IF(B18="-","",J18*N18)
A19: motor | B19: - | C19: =IF(B19="-","",VLOOKUP(B19,DATOS!$I$3:$K$200,2,FALSE)) | D19: =IF(B19="-","",CONCATENATE(VLOOKUP(C19,DATOS!$J$3:$K$200,2,FALSE)," ml")) | G19: =IF(B19="-","",IF(E19="caja",VLOOKUP(B19,DATOS!$I$3:$AC$137,21,FALSE),F19)) | H19: =IF(B19="-","",IF(E19="caja",F19*G19,F19)) | I19: =IF(B19="-","",VLOOKUP(B19,DATOS!$I$3:$S$138,11,FALSE)) | J19: =IF(B19="-","",H19*I19) | K19: =VLOOKUP(B19,DATOS!$I$3:$AD$138,19,FALSE) -> 0 | L19: =IF(E19="caja",VLOOKUP(B19,DATOS!$I$3:$AD$138,22,FALSE),VLOOKUP(B19,DATOS!$I$3:$AD$138,20,FALSE)) -> 5 | M19: =IF(B19="-","",IF(E19="caja",L19,IF(F19>K19,L19,"0"))) | N19: =IF(B19="-","",(100-M19)/100) | O19: =IF(B19="-","",J19*N19)
A20: refrigeracion | B20: - | C20: =IF(B20="-","",VLOOKUP(B20,DATOS!$I$3:$K$200,2,FALSE)) | D20: =IF(B20="-","",CONCATENATE(VLOOKUP(C20,DATOS!$J$3:$K$200,2,FALSE)," ml")) | G20: =IF(B20="-","",IF(E20="caja",VLOOKUP(B20,DATOS!$I$3:$AC$137,21,FALSE),F20)) | H20: =IF(B20="-","",IF(E20="caja",F20*G20,F20)) | I20: =IF(B20="-","",VLOOKUP(B20,DATOS!$I$3:$S$138,11,FALSE)) | J20: =IF(B20="-","",H20*I20) | K20: =VLOOKUP(B20,DATOS!$I$3:$AD$138,19,FALSE) -> 0 | L20: =IF(E20="caja",VLOOKUP(B20,DATOS!$I$3:$AD$138,22,FALSE),VLOOKUP(B20,DATOS!$I$3:$AD$138,20,FALSE)) -> 5 | M20: =IF(B20="-","",IF(E20="caja",L20,IF(F20>K20,L20,"0"))) | N20: =IF(B20="-","",(100-M20)/100) | O20: =IF(B20="-","",J20*N20)
A21: climatizacion | B21: - | C21: =IF(B21="-","",VLOOKUP(B21,DATOS!$I$3:$K$200,2,FALSE)) | D21: =IF(B21="-","",CONCATENATE(VLOOKUP(C21,DATOS!$J$3:$K$200,2,FALSE)," ml")) | G21: =IF(B21="-","",IF(E21="caja",VLOOKUP(B21,DATOS!$I$3:$AC$137,21,FALSE),F21)) | H21: =IF(B21="-","",IF(E21="caja",F21*G21,F21)) | I21: =IF(B21="-","",VLOOKUP(B21,DATOS!$I$3:$S$138,11,FALSE)) | J21: =IF(B21="-","",H21*I21) | K21: =VLOOKUP(B21,DATOS!$I$3:$AD$138,19,FALSE) -> 0 | L21: =IF(E21="caja",VLOOKUP(B21,DATOS!$I$3:$AD$138,22,FALSE),VLOOKUP(B21,DATOS!$I$3:$AD$138,20,FALSE)) -> 5 | M21: =IF(B21="-","",IF(E21="caja",L21,IF(F21>K21,L21,"0"))) | N21: =IF(B21="-","",(100-M21)/100) | O21: =IF(B21="-","",J21*N21)
A22: motor | B22: - | C22: =IF(B22="-","",VLOOKUP(B22,DATOS!$I$3:$K$200,2,FALSE)) | D22: =IF(B22="-","",CONCATENATE(VLOOKUP(C22,DATOS!$J$3:$K$200,2,FALSE)," ml")) | G22: =IF(B22="-","",IF(E22="caja",VLOOKUP(B22,DATOS!$I$3:$AC$137,21,FALSE),F22)) | H22: =IF(B22="-","",IF(E22="caja",F22*G22,F22)) | I22: =IF(B22="-","",VLOOKUP(B22,DATOS!$I$3:$S$138,11,FALSE)) | J22: =IF(B22="-","",H22*I22) | K22: =VLOOKUP(B22,DATOS!$I$3:$AD$138,19,FALSE) -> 0 | L22: =IF(E22="caja",VLOOKUP(B22,DATOS!$I$3:$AD$138,22,FALSE),VLOOKUP(B22,DATOS!$I$3:$AD$138,20,FALSE)) -> 5 | M22: =IF(B22="-","",IF(E22="caja",L22,IF(F22>K22,L22,"0"))) | N22: =IF(B22="-","",(100-M22)/100) | O22: =IF(B22="-","",J22*N22)
A23: refrigeracion | B23: - | C23: =IF(B23="-","",VLOOKUP(B23,DATOS!$I$3:$K$200,2,FALSE)) | D23: =IF(B23="-","",CONCATENATE(VLOOKUP(C23,DATOS!$J$3:$K$200,2,FALSE)," ml")) | G23: =IF(B23="-","",IF(E23="caja",VLOOKUP(B23,DATOS!$I$3:$AC$137,21,FALSE),F23)) | H23: =IF(B23="-","",IF(E23="caja",F23*G23,F23)) | I23: =IF(B23="-","",VLOOKUP(B23,DATOS!$I$3:$S$138,11,FALSE)) | J23: =IF(B23="-","",H23*I23) | K23: =VLOOKUP(B23,DATOS!$I$3:$AD$138,19,FALSE) -> 0 | L23: =IF(E23="caja",VLOOKUP(B23,DATOS!$I$3:$AD$138,22,FALSE),VLOOKUP(B23,DATOS!$I$3:$AD$138,20,FALSE)) -> 5 | M23: =IF(B23="-","",IF(E23="caja",L23,IF(F23>K23,L23,"0"))) | N23: =IF(B23="-","",(100-M23)/100) | O23: =IF(B23="-","",J23*N23)
A24: climatizacion | B24: - | C24: =IF(B24="-","",VLOOKUP(B24,DATOS!$I$3:$K$200,2,FALSE)) | D24: =IF(B24="-","",CONCATENATE(VLOOKUP(C24,DATOS!$J$3:$K$200,2,FALSE)," ml")) | G24: =IF(B24="-","",IF(E24="caja",VLOOKUP(B24,DATOS!$I$3:$AC$137,21,FALSE),F24)) | H24: =IF(B24="-","",IF(E24="caja",F24*G24,F24)) | I24: =IF(B24="-","",VLOOKUP(B24,DATOS!$I$3:$S$138,11,FALSE)) | J24: =IF(B24="-","",H24*I24) | K24: =VLOOKUP(B24,DATOS!$I$3:$AD$138,19,FALSE) -> 0 | L24: =IF(E24="caja",VLOOKUP(B24,DATOS!$I$3:$AD$138,22,FALSE),VLOOKUP(B24,DATOS!$I$3:$AD$138,20,FALSE)) -> 5 | M24: =IF(B24="-","",IF(E24="caja",L24,IF(F24>K24,L24,"0"))) | N24: =IF(B24="-","",(100-M24)/100) | O24: =IF(B24="-","",J24*N24)
M25: TOTAL B.I. | O25: =SUM(O10:O24) -> 585.772 | Q25: =SUM(Q10:Q24) -> 9.91914 | R25: =SUM(R10:R24) -> 57.15314 | S25: =SUM(S10:S24) -> 708.78412
M26: I.V.A. (21%) | N26: 0.21 | O26: =O25*0.21 -> 123.01212
O27: =O25+O26 -> 708.78412
B29: Michael Leffler | C29: Peones Camineros, Portal A 2 izq. 11158. La barca de Vejer
B30: X-0000000000-W | D30: 600 100 100 | F30: pedidos@wepp.es
B31: CCC | C31: 2100 1789 0100 0000 0001

Sheet CLIENTE FACTURA
A1: DATOS CLIENTE
A2: Razón Social:
A3: CIF:
A4: Dirección:
A5: Dirección envío:
A6: Teléfono:
A7: Correo Electrónico:
A8: FACTURA | G8: Nº | H8: 2025-1
A9: Descripción | B9: Ref. | C9: Volumen | D9: Cantidad | E9: Unidad | F9: Total | G9: Precio ud | H9: Dto(%) | I9: Total B.I.
A10: ='CLIENTE PEDIDO'!B10 -> Limpiador de Motor SF (sin disolventes) | B10: ='CLIENTE PEDIDO'!C10 -> 2010 SF | C10: ='CLIENTE PEDIDO'!D10 -> 300 ml | D10: =IF(A10="-","",'CLIENTE PEDIDO'!E10) -> unidad | E10: =IF(A10="-","",'CLIENTE PEDIDO'!F10) -> 12 | F10: ='CLIENTE PEDIDO'!H10 -> 12 | G10: ='CLIENTE PEDIDO'!I10 -> 10.285 | H10: ='CLIENTE PEDIDO'!M10 -> 5 | I10: ='CLIENTE PEDIDO'!O10 -> 117.249
A11: ='CLIENTE PEDIDO'!B11 -> Protector del Sistema de Refrigeración | B11: ='CLIENTE PEDIDO'!C11 -> 2020 | C11: ='CLIENTE PEDIDO'!D11 -> 300 ml | D11: =IF(A11="-","",'CLIENTE PEDIDO'!E11) -> caja | E11: =IF(A11="-","",'CLIENTE PEDIDO'!F11) -> 1 | F11: ='CLIENTE PEDIDO'!H11 -> 24 | G11: ='CLIENTE PEDIDO'!I11 -> 8.47 | H11: ='CLIENTE PEDIDO'!M11 -> 15 | I11: ='CLIENTE PEDIDO'!O11 -> 172.788
A12: ='CLIENTE PEDIDO'!B12 -> Airfresh Menta | B12: ='CLIENTE PEDIDO'!C12 -> 2125 | C12: ='CLIENTE PEDIDO'!D12 -> 100 ml | D12: =IF(A12="-","",'CLIENTE PEDIDO'!E12) -> caja | E12: =IF(A12="-","",'CLIENTE PEDIDO'!F12) -> 1 | F12: ='CLIENTE PEDIDO'!H12 -> 24 | G12: ='CLIENTE PEDIDO'!I12 -> 10.175 | H12: ='CLIENTE PEDIDO'!M12 -> 15 | I12: ='CLIENTE PEDIDO'!O12 -> 207.57
A13: ='CLIENTE PEDIDO'!B13 -> Limpiador Intensivo Diésel | B13: ='CLIENTE PEDIDO'!C13 -> 2030 | C13: ='CLIENTE PEDIDO'!D13 -> 500 ml | D13: =IF(A13="-","",'CLIENTE PEDIDO'!E13) -> unidad | E13: =IF(A13="-","",'CLIENTE PEDIDO'!F13) -> 3 | F13: ='CLIENTE PEDIDO'!H13 -> 3 | G13: ='CLIENTE PEDIDO'!I13 -> 9.955 | H13: ='CLIENTE PEDIDO'!M13 -> 0 | I13: ='CLIENTE PEDIDO'!O13 -> 29.865
A14: ='CLIENTE PEDIDO'!B14 -> Frenos Hi Tec | B14: ='CLIENTE PEDIDO'!C14 -> 255 | C14: ='CLIENTE PEDIDO'!D14 -> 400 ml | D14: =IF(A14="-","",'CLIENTE PEDIDO'!E14) -> unidad | E14: =IF(A14="-","",'CLIENTE PEDIDO'!F14) -> 5 | F14: ='CLIENTE PEDIDO'!H14 -> 5 | G14: ='CLIENTE PEDIDO'!I14 -> 11.66 | H14: ='CLIENTE PEDIDO'!M14 -> 0 | I14: ='CLIENTE PEDIDO'!O14 -> 58.3
A15: ='CLIENTE PEDIDO'!B15 -> - | B15: ='CLIENTE PEDIDO'!C15 | C15: ='CLIENTE PEDIDO'!D15 | D15: =IF(A15="-","",'CLIENTE PEDIDO'!E15) | E15: =IF(A15="-","",'CLIENTE PEDIDO'!F15) | F15: ='CLIENTE PEDIDO'!H15 | G15: ='CLIENTE PEDIDO'!I15 | H15: ='CLIENTE PEDIDO'!M15 | I15: ='CLIENTE PEDIDO'!O15
A16: ='CLIENTE PEDIDO'!B16 -> - | B16: ='CLIENTE PEDIDO'!C16 | C16: ='CLIENTE PEDIDO'!D16 | D16: =IF(A16="-","",'CLIENTE PEDIDO'!E16) | E16: =IF(A16="-","",'CLIENTE PEDIDO'!F16) | F16: ='CLIENTE PEDIDO'!H16 | G16: ='CLIENTE PEDIDO'!I16 | H16: ='CLIENTE PEDIDO'!M16 | I16: ='CLIENTE PEDIDO'!O16
A17: ='CLIENTE PEDIDO'!B17 -> - | B17: ='CLIENTE PEDIDO'!C17 | C17: ='CLIENTE PEDIDO'!D17 | D17: =IF(A17="-","",'CLIENTE PEDIDO'!E17) | E17: =IF(A17="-","",'CLIENTE PEDIDO'!F17) | F17: ='CLIENTE PEDIDO'!H17 | G17: ='CLIENTE PEDIDO'!I17 | H17: ='CLIENTE PEDIDO'!M17 | I17: ='CLIENTE PEDIDO'!O17
A18: ='CLIENTE PEDIDO'!B18 -> - | B18: ='CLIENTE PEDIDO'!C18 | C18: ='CLIENTE PEDIDO'!D18 | D18: =IF(A18="-","",'CLIENTE PEDIDO'!E18) | E18: =IF(A18="-","",'CLIENTE PEDIDO'!F18) | F18: ='CLIENTE PEDIDO'!H18 | G18: ='CLIENTE PEDIDO'!I18 | H18: ='CLIENTE PEDIDO'!M18 | I18: ='CLIENTE PEDIDO'!O18
A19: ='CLIENTE PEDIDO'!B19 -> - | B19: ='CLIENTE PEDIDO'!C19 | C19: ='CLIENTE PEDIDO'!D19 | D19: =IF(A19="-","",'CLIENTE PEDIDO'!E19) | E19: =IF(A19="-","",'CLIENTE PEDIDO'!F19) | F19: ='CLIENTE PEDIDO'!H19 | G19: ='CLIENTE PEDIDO'!I19 | H19: ='CLIENTE PEDIDO'!M19 | I19: ='CLIENTE PEDIDO'!O19
A20: ='CLIENTE PEDIDO'!B20 -> - | B20: ='CLIENTE PEDIDO'!C20 | C20: ='CLIENTE PEDIDO'!D20 | D20: =IF(A20="-","",'CLIENTE PEDIDO'!E20) | E20: =IF(A20="-","",'CLIENTE PEDIDO'!F20) | F20: ='CLIENTE PEDIDO'!H20 | G20: ='CLIENTE PEDIDO'!I20 | H20: ='CLIENTE PEDIDO'!M20 | I20: ='CLIENTE PEDIDO'!O20
A21: ='CLIENTE PEDIDO'!B21 -> - | B21: ='CLIENTE PEDIDO'!C21 | C21: ='CLIENTE PEDIDO'!D21 | D21: =IF(A21="-","",'CLIENTE PEDIDO'!E21) | E21: =IF(A21="-","",'CLIENTE PEDIDO'!F21) | F21: ='CLIENTE PEDIDO'!H21 | G21: ='CLIENTE PEDIDO'!I21 | H21: ='CLIENTE PEDIDO'!M21 | I21: ='CLIENTE PEDIDO'!O21
... A24: ='CLIENTE PEDIDO'!B24 -> - | B24: ='CLIENTE PEDIDO'!C24 | C24: ='CLIENTE PEDIDO'!D24 | D24: =IF(A24="-","",'CLIENTE PEDIDO'!E24) | E24: =IF(A24="-","",'CLIENTE PEDIDO'!F24) | F24: ='CLIENTE PEDIDO'!H24 | G24: ='CLIENTE PEDIDO'!I24 | H24: ='CLIENTE PEDIDO'!M24 | I24: ='CLIENTE PEDIDO'!O24
H25: TOTAL B.I. | I25: =SUM(I10:I24) -> 585.772
H26: I.V.A. (21%) | I26: =I25*0.21 -> 123.01212
I27: =I25+I26 -> 708.78412
A29: Michael Leffler | B29: Peones Camineros, Portal A 2 izq. 11158. La barca de Vejer
A30: X-0000000000-W | C30: 600 100 100 | E30: pedidos@wepp.es
A31: CCC | B31: 2100 1789 0100 0000 0001

Sheet FACTURA COMERCIAL
A1: DATOS COMERCIAL
A2: Razón Social:
A3: CIF:
A4: Dirección:
A5: Dirección envío:
A6: Teléfono:
A7: Correo Electrónico:
A8: FACTURA | G8: Nº | H8: 2025-1
A9: Descripción | B9: Ref. | C9: Volumen | D9: Cantidad | E9: Unidad | F9: Total | G9: Precio ud | H9: Dto(%) | I9: ocultar | J9: B.I.
A10: ='CLIENTE PEDIDO'!B10 -> Limpiador de Motor SF (sin disolventes) | B10: ='CLIENTE PEDIDO'!C10 -> 2010 SF | C10: ='CLIENTE PEDIDO'!D10 -> 300 ml | D10: =IF(A10="-","",'CLIENTE PEDIDO'!E10) -> unidad | E10: =IF(A10="-","",'CLIENTE PEDIDO'!F10) -> 12 | F10: ='CLIENTE PEDIDO'!H10 -> 12 | G10: =IF(A10="-","",VLOOKUP(A10,DATOS!$I$3:$W$138,15,FALSE)) -> 2.2 | H10: =IF(A10="-","",('CLIENTE PEDIDO'!M10)/2) -> 2.5 | I10: =(100-H10)/100 -> 0.975 | J10: =IF(A10="-","",F10*G10*I10) -> 25.74
A11: ='CLIENTE PEDIDO'!B11 -> Protector del Sistema de Refrigeración | B11: ='CLIENTE PEDIDO'!C11 -> 2020 | C11: ='CLIENTE PEDIDO'!D11 -> 300 ml | D11: =IF(A11="-","",'CLIENTE PEDIDO'!E11) -> caja | E11: =IF(A11="-","",'CLIENTE PEDIDO'!F11) -> 1 | F11: ='CLIENTE PEDIDO'!H11 -> 24 | G11: =IF(A11="-","",VLOOKUP(A11,DATOS!$I$3:$W$138,15,FALSE)) -> 1.4 | H11: =IF(A11="-","",('CLIENTE PEDIDO'!M11)/2) -> 7.5 | I11: ='CLIENTE PEDIDO'!N11 -> 0.85 | J11: =IF(A11="-","",F11*G11*I11) -> 28.56
A12: ='CLIENTE PEDIDO'!B12 -> Airfresh Menta | B12: ='CLIENTE PEDIDO'!C12 -> 2125 | C12: ='CLIENTE PEDIDO'!D12 -> 100 ml | D12: =IF(A12="-","",'CLIENTE PEDIDO'!E12) -> caja | E12: =IF(A12="-","",'CLIENTE PEDIDO'!F12) -> 1 | F12: ='CLIENTE PEDIDO'!H12 -> 24 | G12: =IF(A12="-","",VLOOKUP(A12,DATOS!$I$3:$W$138,15,FALSE)) -> 2 | H12: =IF(A12="-","",('CLIENTE PEDIDO'!M12)/2) -> 7.5 | I12: ='CLIENTE PEDIDO'!N12 -> 0.85 | J12: =IF(A12="-","",F12*G12*I12) -> 40.8
A13: ='CLIENTE PEDIDO'!B13 -> Limpiador Intensivo Diésel | B13: ='CLIENTE PEDIDO'!C13 -> 2030 | C13: ='CLIENTE PEDIDO'!D13 -> 500 ml | D13: =IF(A13="-","",'CLIENTE PEDIDO'!E13) -> unidad | E13: =IF(A13="-","",'CLIENTE PEDIDO'!F13) -> 3 | F13: ='CLIENTE PEDIDO'!H13 -> 3 | G13: =IF(A13="-","",VLOOKUP(A13,DATOS!$I$3:$W$138,15,FALSE)) -> 1.8 | H13: =IF(A13="-","",('CLIENTE PEDIDO'!M13)/2) -> 0 | I13: ='CLIENTE PEDIDO'!N13 -> 1 | J13: =IF(A13="-","",F13*G13*I13) -> 5.4
A14: ='CLIENTE PEDIDO'!B14 -> Frenos Hi Tec | B14: ='CLIENTE PEDIDO'!C14 -> 255 | C14: ='CLIENTE PEDIDO'!D14 -> 400 ml | D14: =IF(A14="-","",'CLIENTE PEDIDO'!E14) -> unidad | E14: =IF(A14="-","",'CLIENTE PEDIDO'!F14) -> 5 | F14: ='CLIENTE PEDIDO'!H14 -> 5 | G14: =IF(A14="-","",VLOOKUP(A14,DATOS!$I$3:$W$138,15,FALSE)) -> 2.38 | H14: =IF(A14="-","",('CLIENTE PEDIDO'!M14)/2) -> 0 | I14: ='CLIENTE PEDIDO'!N14 -> 1 | J14: =IF(A14="-","",F14*G14*I14) -> 11.9
A15: ='CLIENTE PEDIDO'!B15 -> - | B15: ='CLIENTE PEDIDO'!C15 | C15: ='CLIENTE PEDIDO'!D15 | D15: =IF(A15="-","",'CLIENTE PEDIDO'!E15) | E15: =IF(A15="-","",'CLIENTE PEDIDO'!F15) | F15: ='CLIENTE PEDIDO'!H15 | G15: =IF(A15="-","",VLOOKUP(A15,DATOS!$I$3:$W$138,15,FALSE)) | H15: =IF(A15="-","",('CLIENTE PEDIDO'!M15)/2) | I15: ='CLIENTE PEDIDO'!N15 | J15: =IF(A15="-","",F15*G15*I15)
A16: ='CLIENTE PEDIDO'!B16 -> - | B16: ='CLIENTE PEDIDO'!C16 | C16: ='CLIENTE PEDIDO'!D16 | D16: =IF(A16="-","",'CLIENTE PEDIDO'!E16) | E16: =IF(A16="-","",'CLIENTE PEDIDO'!F16) | F16: ='CLIENTE PEDIDO'!H16 | G16: =IF(A16="-","",VLOOKUP(A16,DATOS!$I$3:$W$138,15,FALSE)) | H16: =IF(A16="-","",('CLIENTE PEDIDO'!M16)/2) | I16: ='CLIENTE PEDIDO'!N16 | J16: =IF(A16="-","",F16*G16*I16)
A17: ='CLIENTE PEDIDO'!B17 -> - | B17: ='CLIENTE PEDIDO'!C17 | C17: ='CLIENTE PEDIDO'!D17 | D17: =IF(A17="-","",'CLIENTE PEDIDO'!E17) | E17: =IF(A17="-","",'CLIENTE PEDIDO'!F17) | F17: ='CLIENTE PEDIDO'!H17 | G17: =IF(A17="-","",VLOOKUP(A17,DATOS!$I$3:$W$138,15,FALSE)) | H17: =IF(A17="-","",('CLIENTE PEDIDO'!M17)/2) | I17: ='CLIENTE PEDIDO'!N17 | J17: =IF(A17="-","",F17*G17*I17)
A18: ='CLIENTE PEDIDO'!B18 -> - | B18: ='CLIENTE PEDIDO'!C18 | C18: ='CLIENTE PEDIDO'!D18 | D18: =IF(A18="-","",'CLIENTE PEDIDO'!E18) | E18: =IF(A18="-","",'CLIENTE PEDIDO'!F18) | F18: ='CLIENTE PEDIDO'!H18 | G18: =IF(A18="-","",VLOOKUP(A18,DATOS!$I$3:$W$138,15,FALSE)) | H18: =IF(A18="-","",('CLIENTE PEDIDO'!M18)/2) | I18: ='CLIENTE PEDIDO'!N18 | J18: =IF(A18="-","",F18*G18*I18)
A19: ='CLIENTE PEDIDO'!B19 -> - | B19: ='CLIENTE PEDIDO'!C19 | C19: ='CLIENTE PEDIDO'!D19 | D19: =IF(A19="-","",'CLIENTE PEDIDO'!E19) | E19: =IF(A19="-","",'CLIENTE PEDIDO'!F19) | F19: ='CLIENTE PEDIDO'!H19 | G19: =IF(A19="-","",VLOOKUP(A19,DATOS!$I$3:$W$138,15,FALSE)) | H19: =IF(A19="-","",('CLIENTE PEDIDO'!M19)/2) | I19: ='CLIENTE PEDIDO'!N19 | J19: =IF(A19="-","",F19*G19*I19)
A20: ='CLIENTE PEDIDO'!B20 -> - | B20: ='CLIENTE PEDIDO'!C20 | C20: ='CLIENTE PEDIDO'!D20 | D20: =IF(A20="-","",'CLIENTE PEDIDO'!E20) | E20: =IF(A20="-","",'CLIENTE PEDIDO'!F20) | F20: ='CLIENTE PEDIDO'!H20 | G20: =IF(A20="-","",VLOOKUP(A20,DATOS!$I$3:$W$138,15,FALSE)) | H20: =IF(A20="-","",('CLIENTE PEDIDO'!M20)/2) | I20: ='CLIENTE PEDIDO'!N20 | J20: =IF(A20="-","",F20*G20*I20)
A21: ='CLIENTE PEDIDO'!B21 -> - | B21: ='CLIENTE PEDIDO'!C21 | C21: ='CLIENTE PEDIDO'!D21 | D21: =IF(A21="-","",'CLIENTE PEDIDO'!E21) | E21: =IF(A21="-","",'CLIENTE PEDIDO'!F21) | F21: ='CLIENTE PEDIDO'!H21 | G21: =IF(A21="-","",VLOOKUP(A21,DATOS!$I$3:$W$138,15,FALSE)) | H21: =IF(A21="-","",('CLIENTE PEDIDO'!M21)/2) | I21: ='CLIENTE PEDIDO'!N21 | J21: =IF(A21="-","",F21*G21*I21)
A22: ='CLIENTE PEDIDO'!B22 -> - | B22: ='CLIENTE PEDIDO'!C22 | C22: ='CLIENTE PEDIDO'!D22 | D22: =IF(A22="-","",'CLIENTE PEDIDO'!E22) | E22: =IF(A22="-","",'CLIENTE PEDIDO'!F22) | F22: ='CLIENTE PEDIDO'!H22 | G22: =IF(A22="-","",VLOOKUP(A22,DATOS!$I$3:$W$138,15,FALSE)) | H22: =IF(A22="-","",('CLIENTE PEDIDO'!M22)/2) | I22: ='CLIENTE PEDIDO'!N22 | J22: =IF(A22="-","",F22*G22*I22)
... A24: ='CLIENTE PEDIDO'!B24 -> - | B24: ='CLIENTE PEDIDO'!C24 | C24: ='CLIENTE PEDIDO'!D24 | D24: =IF(A24="-","",'CLIENTE PEDIDO'!E24) | E24: =IF(A24="-","",'CLIENTE PEDIDO'!F24) | F24: ='CLIENTE PEDIDO'!H24 | G24: =IF(A24="-","",VLOOKUP(A24,DATOS!$I$3:$W$138,15,FALSE)) | H24: =IF(A24="-","",('CLIENTE PEDIDO'!M24)/2) | I24: ='CLIENTE PEDIDO'!N24 | J24: =IF(A24="-","",F24*G24*I24)
H25: ='CLIENTE FACTURA'!H25 -> TOTAL B.I. | J25: =SUM(J10:J24) -> 112.4
H26: ='CLIENTE FACTURA'!H26 -> I.V.A. (21%) | I26: 0.21 | J26: =J25*0.21 -> 23.604
J27: =J25+J26 -> 136.004
A29: Michael Leffler | B29: Peones Camineros, Portal A 2 izq. 11158. La barca de Vejer
A30: X-0000000000-W | C30: 600 100 100 | E30: pedidos@wepp.es
A31: CCC | B31: 2100 1789 0100 0000 0001

Sheet DATOS
A1: 1 | B1: 2 | E1: 3 | F1: 4 | G1: 5 | H1: 6 | I1: 7 | J1: 8 | K1: 9 | L1: 10 | M1: 11 | N1: 12 | O1: 13 | P1: 14 | Q1: 15 | R1: 16 | S1: 17 | T1: 18 | U1: 19 | V1: 20 | W1: 21 | X1: 22 | Y1: 23 | Z1: 24 | AB1: 25 | AC1: 26 | AD1: 27 | AE1: 28 | AF1: 29 | AG1: 30 | AH1: 31 | AI1: 32 | AJ1: 33 | AK1: 34 | AL1: 35 | AM1: 36
A2: proveedor | B2: documento | C2: clase | E2: relevancia | F2: referencia | H2: Aleman | I2: Español | J2: =F2 -> referencia | K2: =G2 -> 0 | L2: COSTO | M2: PORTE UD | N2: ADUANA | O2: EMBALAJE | P2: MANIPULACIÓN | Q2: COSTO REAL | R2: PRECIO TALLER | S2: PRECIO TALLER +10 | T2: PRECIO CLIENTE | U2: BENEFICIO TOTAL | V2: BENEFICIO MIO | W2: BENEFICIO COMERCIAL | X2: BENEFICIO % | Z2: unidad | AA2: cantidad minima | AB2: dto unidad | AC2: unidades caja | AD2: dto caja | AE2: Volumen (L) | AF2: PESO (Kg) | AG2: PESO CAJA (Kg) | AH2: AUXILIAR COSTO+TRANSPORTE | AI2: TRANSPORTE | AJ2: Pedido unidad | AK2: Pedido caja | AL2: Palet | AM2: Precio Pedido
A3: WEPP | B3: C | C3: 1 | D3: =IF(C3=1,"Motor y Transmisión",IF(C3=2,"Refrigeración",IF(C3=3,"Climatización",IF(C3=4,"Sistema de Combustión",IF(C3=5,"Frenos",IF(C3=6,"Mantenimiento y Cuidado",IF(C3=7,"Carrocería",""))))))) -> Motor y Transmisión | E3: 1 | F3: 2010 SF | G3: =AE3*1000 -> 300 | H3: Motor System Reiniger (Lösungsmittelfrei) | I3: Limpiador de Motor SF (sin disolventes) | J3: =F3 -> 2010 SF | K3: =G3 -> 300 | L3: 2.95 | M3: 0.3 | N3: 0 | O3: 0.3 | P3: 0.3 | Q3: =+L3+M3+N3+O3+P3 -> 3.85 | R3: 9.35 | S3: =R3*1.1 -> 10.285 | T3: 16.85 | U3: =R3-Q3 -> 5.5 | V3: =U3*0.6 -> 3.3 | W3: =U3*0.4 -> 2.2 | Z3: 1 | AA3: =INT(AC3/3) -> 8 | AB3: 5 | AC3: 24 | AD3: =IF(AC3=24,15,IF(AC3=12,10,0)) -> 15 | AE3: 0.3 | AF3: =AE3*1.1 -> 0.33 | AG3: =AF3*AC3 -> 7.92 | AI3: 1 | AK3: 2
A4: WEPP | B4: C | C4: 1 | D4: =IF(C4=1,"Motor y Transmisión",IF(C4=2,"Refrigeración",IF(C4=3,"Climatización",IF(C4=4,"Sistema de Combustión",IF(C4=5,"Frenos",IF(C4=6,"Mantenimiento y Cuidado",IF(C4=7,"Carrocería",""))))))) -> Motor y Transmisión | E4: 1 | F4: 2110 | G4: =AE4*1000 -> 300 | H4: Motor Intensiv Reiniger | I4: Limpiador Intensivo de Motor | J4: =F4 -> 2110 | K4: =G4 -> 300 | L4: 4.78 | M4: 0.3 | N4: 0 | O4: 0.3 | P4: 0.3 | Q4: =+L4+M4+N4+O4+P4 -> 5.68 | R4: 12.85 | S4: =R4*1.1 -> 14.135 | T4: 21.35 | U4: =R4-Q4 -> 7.17 | V4: =U4*0.6 -> 4.302 | W4: =U4*0.4 -> 2.868 | Z4: 1 | AA4: =INT(AC4/3) -> 8 | AB4: 5 | AC4: 24 | AD4: =IF(AC4=24,15,IF(AC4=12,10,0)) -> 15 | AE4: 0.3 | AF4: =AE4*1.1 -> 0.33 | AG4: =AF4*AC4 -> 7.92 | AI4: 2 | AK4: 2
A5: WEPP | B5: C | C5: 1 | D5: =IF(C5=1,"Motor y Transmisión",IF(C5=2,"Refrigeración",IF(C5=3,"Climatización",IF(C5=4,"Sistema de Combustión",IF(C5=5,"Frenos",IF(C5=6,"Mantenimiento y Cuidado",IF(C5=7,"Carrocería",""))))))) -> Motor y Transmisión | E5: 1 | F5: 2011 | G5: =AE5*1000 -> 400 | H5: Ölstopp Additiv | I5: Tapafugas de Aceite 400 | J5: =F5 -> 2011 | K5: =G5 -> 400 | L5: 3.3 | M5: 0.3 | N5: 0 | O5: 0.3 | P5: 0.3 | Q5: =+L5+M5+N5+O5+P5 -> 4.2 | R5: 9.7 | S5: =R5*1.1 -> 10.67 | T5: 14.4 | U5: =R5-Q5 -> 5.5 | V5: =U5*0.6 -> 3.3 | W5: =U5*0.4 -> 2.2 | Z5: 1 | AA5: =INT(AC5/3) -> 8 | AB5: 5 | AC5: 24 | AD5: =IF(AC5=24,15,IF(AC5=12,10,0)) -> 15 | AE5: 0.4 | AF5: =AE5*1.1 -> 0.44 | AG5: =AF5*AC5 -> 10.56 | AI5: 3 | AK5: 2
A6: WEPP | B6: C | C6: 1 | D6: =IF(C6=1,"Motor y Transmisión",IF(C6=2,"Refrigeración",IF(C6=3,"Climatización",IF(C6=4,"Sistema de Combustión",IF(C6=5,"Frenos",IF(C6=6,"Mantenimiento y Cuidado",IF(C6=7,"Carrocería",""))))))) -> Motor y Transmisión | E6: 1 | F6: 2011-300 | G6: =AE6*1000 -> 300 | H6: Ölstopp Additiv | I6: Tapafugas de Aceite 300 | J6: =F6 -> 2011-300 | K6: =G6 -> 300 | L6: 2.8 | M6: 0.3 | N6: 0 | O6: 0.3 | P6: 0.3 | Q6: =+L6+M6+N6+O6+P6 -> 3.7 | R6: 7.5 | S6: =R6*1.1 -> 8.25 | T6: 13.45 | U6: =R6-Q6 -> 3.8 | V6: =U6*0.6 -> 2.28 | W6: =U6*0.4 -> 1.52 | Z6: 1 | AA6: =INT(AC6/3) -> 8 | AB6: 5 | AC6: 24 | AD6: =IF(AC6=24,15,IF(AC6=12,10,0)) -> 15 | AE6: 0.3 | AF6: =AE6*1.1 -> 0.33 | AG6: =AF6*AC6 -> 7.92
A7: WEPP | B7: C | C7: 1 | D7: =IF(C7=1,"Motor y Transmisión",IF(C7=2,"Refrigeración",IF(C7=3,"Climatización",IF(C7=4,"Sistema de Combustión",IF(C7=5,"Frenos",IF(C7=6,"Mantenimiento y Cuidado",IF(C7=7,"Carrocería",""))))))) -> Motor y Transmisión | E7: 1 | F7: 2111 | G7: =AE7*1000 -> 300 | H7: Motor Verschleiss Schutz | I7: Protector Contra el Desgaste del Motor | J7: =F7 -> 2111 | K7: =G7 -> 300 | L7: 3.95 | M7: 0.3 | N7: 0 | O7: 0.3 | P7: 0.3 | Q7: =+L7+M7+N7+O7+P7 -> 4.85 | R7: 10.05 | S7: =R7*1.1 -> 11.055 | T7: 18.1 | U7: =R7-Q7 -> 5.2 | V7: =U7*0.6 -> 3.12 | W7: =U7*0.4 -> 2.08 | Z7: 1 | AA7: =INT(AC7/3) -> 8 | AB7: 5 | AC7: 24 | AD7: =IF(AC7=24,15,IF(AC7=12,10,0)) -> 15 | AE7: 0.3 | AF7: =AE7*1.1 -> 0.33 | AG7: =AF7*AC7 -> 7.92 | AI7: 4 | AK7: 2
A8: WEPP | B8: C | C8: 1 | D8: =IF(C8=1,"Motor y Transmisión",IF(C8=2,"Refrigeración",IF(C8=3,"Climatización",IF(C8=4,"Sistema de Combustión",IF(C8=5,"Frenos",IF(C8=6,"Mantenimiento y Cuidado",IF(C8=7,"Carrocería",""))))))) -> Motor y Transmisión | E8: 1 | F8: 2012 | G8: =AE8*1000 -> 100 | H8: Getriebeöladditiv | I8: Aditivos para Aceites de Transmisión | J8: =F8 -> 2012 | K8: =G8 -> 100 | L8: 3.85 | M8: 0.3 | N8: 0 | O8: 0.3 | P8: 0.3 | Q8: =+L8+M8+N8+O8+P8 -> 4.75 | R8: 8.95 | S8: =R8*1.1 -> 9.845 | T8: 14.8 | U8: =R8-Q8 -> 4.2 | V8: =U8*0.6 -> 2.52 | W8: =U8*0.4 -> 1.68 | Z8: 1 | AA8: =INT(AC8/3) -> 8 | AB8: 5 | AC8: 24 | AD8: =IF(AC8=24,15,IF(AC8=12,10,0)) -> 15 | AE8: 0.1 | AF8: =AE8*1.1 -> 0.11 | AG8: =AF8*AC8 -> 2.64 | AI8: 5
A9: WEPP | B9: C | C9: 1 | D9: =IF(C9=1,"Motor y Transmisión",IF(C9=2,"Refrigeración",IF(C9=3,"Climatización",IF(C9=4,"Sistema de Combustión",IF(C9=5,"Frenos",IF(C9=6,"Mantenimiento y Cuidado",IF(C9=7,"Carrocería",""))))))) -> Motor y Transmisión | E9: 1 | F9: 2013 | G9: =AE9*1000 -> 300 | H9: ATF Cleaner | I9: Limpiador de ATF | J9: =F9 -> 2013 | K9: =G9 -> 300 | L9: 3.9 | M9: 0.3 | N9: 0 | O9: 0.3 | P9: 0.3 | Q9: =+L9+M9+N9+O9+P9 -> 4.8 | R9: 11.3 | S9: =R9*1.1 -> 12.43 | T9: 18.1 | U9: =R9-Q9 -> 6.5 | V9: =U9*0.6 -> 3.9 | W9: =U9*0.4 -> 2.6 | Z9: 1 | AA9: =INT(AC9/3) -> 8 | AB9: 5 | AC9: 24 | AD9: =IF(AC9=24,15,IF(AC9=12,10,0)) -> 15 | AE9: 0.3 | AF9: =AE9*1.1 -> 0.33 | AG9: =AF9*AC9 -> 7.92 | AI9: 6
A10: WEPP | B10: C | C10: 1 | D10: =IF(C10=1,"Motor y Transmisión",IF(C10=2,"Refrigeración",IF(C10=3,"Climatización",IF(C10=4,"Sistema de Combustión",IF(C10=5,"Frenos",IF(C10=6,"Mantenimiento y Cuidado",IF(C10=7,"Carrocería",""))))))) -> Motor y Transmisión | E10: 1 | F10: 2014 | G10: =AE10*1000 -> 300 | H10: ATF Protection | I10: Protector ATF | J10: =F10 -> 2014 | K10: =G10 -> 300 | L10: 4.3 | M10: 0.3 | N10: 0 | O10: 0.3 | P10: 0.3 | Q10: =+L10+M10+N10+O10+P10 -> 5.2 | R10: 14.5 | S10: =R10*1.1 -> 15.95 | T10: 23 | U10: =R10-Q10 -> 9.3 | V10: =U10*0.6 -> 5.58 | W10: =U10*0.4 -> 3.72 | Z10: 1 | AA10: =INT(AC10/3) -> 8 | AB10: 5 | AC10: 24 | AD10: =IF(AC10=24,15,IF(AC10=12,10,0)) -> 15 | AE10: 0.3 | AF10: =AE10*1.1 -> 0.33 | AG10: =AF10*AC10 -> 7.92 | AI10: 7
A11: WEPP | B11: C | C11: 1 | D11: =IF(C11=1,"Motor y Transmisión",IF(C11=2,"Refrigeración",IF(C11=3,"Climatización",IF(C11=4,"Sistema de Combustión",IF(C11=5,"Frenos",IF(C11=6,"Mantenimiento y Cuidado",IF(C11=7,"Carrocería",""))))))) -> Motor y Transmisión | E11: 0 | F11: 2015 | G11: =AE11*1000 -> 300 | H11: Power Steering Cleaner | I11: Limpiador de Dirección Asistida | J11: =F11 -> 2015 | K11: =G11 -> 300 | L11: 3.7 | M11: 0.3 | N11: 0 | O11: 0.3 | P11: 0.3 | Q11: =+L11+M11+N11+O11+P11 -> 4.6 | R11: 11 | S11: =R11*1.1 -> 12.1 | T11: 17.7 | U11: =R11-Q11 -> 6.4 | V11: =U11*0.6 -> 3.84 | W11: =U11*0.4 -> 2.56 | Z11: 1 | AA11: =INT(AC11/3) -> 8 | AB11: 5 | AC11: 24 | AD11: =IF(AC11=24,15,IF(AC11=12,10,0)) -> 15 | AE11: 0.3 | AF11: =AE11*1.1 -> 0.33 | AG11: =AF11*AC11 -> 7.92 | AI11: 8
A12: WEPP | B12: C | C12: 1 | D12: =IF(C12=1,"Motor y Transmisión",IF(C12=2,"Refrigeración",IF(C12=3,"Climatización",IF(C12=4,"Sistema de Combustión",IF(C12=5,"Frenos",IF(C12=6,"Mantenimiento y Cuidado",IF(C12=7,"Carrocería",""))))))) -> Motor y Transmisión | E12: 0 | F12: 2016 | G12: =AE12*1000 -> 100 | H12: Power Steering Protection | I12: Protector de la Dirección Asistida | J12: =F12 -> 2016 | K12: =G12 -> 100 | L12: 2.85 | M12: 0.3 | N12: 0 | O12: 0.3 | P12: 0.3 | Q12: =+L12+M12+N12+O12+P12 -> 3.75 | R12: 8.9 | S12: =R12*1.1 -> 9.79 | T12: 14.25 | U12: =R12-Q12 -> 5.15 | V12: =U12*0.6 -> 3.09 | W12: =U12*0.4 -> 2.06 | Z12: 1 | AA12: =INT(AC12/3) -> 8 | AB12: 5 | AC12: 24 | AD12: =IF(AC12=24,15,IF(AC12=12,10,0)) -> 15 | AE12: 0.1 | AF12: =AE12*1.1 -> 0.11 | AG12: =AF12*AC12 -> 2.64 | AI12: 9
A13: WEPP | B13: C | C13: 2 | D13: =IF(C13=1,"Motor y Transmisión",IF(C13=2,"Refrigeración",IF(C13=3,"Climatización",IF(C13=4,"Sistema de Combustión",IF(C13=5,"Frenos",IF(C13=6,"Mantenimiento y Cuidado",IF(C13=7,"Carrocería",""))))))) -> Refrigeración | E13: 1 | F13: 2020 | G13: =AE13*1000 -> 300 | H13: Kühler System Schutz | I13: Protector del Sistema de Refrigeración | J13: =F13 -> 2020 | K13: =G13 -> 300 | L13: 3.3 | M13: 0.3 | N13: 0 | O13: 0.3 | P13: 0.3 | Q13: =+L13+M13+N13+O13+P13 -> 4.2 | R13: 7.7 | S13: =R13*1.1 -> 8.47 | T13: 14.65 | U13: =R13-Q13 -> 3.5 | V13: =U13*0.6 -> 2.1 | W13: =U13*0.4 -> 1.4 | Z13: 1 | AA13: =INT(AC13/3) -> 8 | AB13: 5 | AC13: 24 | AD13: =IF(AC13=24,15,IF(AC13=12,10,0)) -> 15 | AE13: 0.3 | AF13: =AE13*1.1 -> 0.33 | AG13: =AF13*AC13 -> 7.92 | AK13: 2
A14: WEPP | B14: C | C14: 2 | D14: =IF(C14=1,"Motor y Transmisión",IF(C14=2,"Refrigeración",IF(C14=3,"Climatización",IF(C14=4,"Sistema de Combustión",IF(C14=5,"Frenos",IF(C14=6,"Mantenimiento y Cuidado",IF(C14=7,"Carrocería",""))))))) -> Refrigeración | E14: 1 | F14: 2021 | G14: =AE14*1000 -> 400 | H14: Kühlerdicht | I14: Tapafugas | J14: =F14 -> 2021 | K14: =G14 -> 400 | L14: 3 | M14: 0.3 | N14: 0 | O14: 0.3 | P14: 0.3 | Q14: =+L14+M14+N14+O14+P14 -> 3.9 | R14: 7.25 | S14: =R14*1.1 -> 7.975 | T14: 13.15 | U14: =R14-Q14 -> 3.35 | V14: =U14*0.6 -> 2.01 | W14: =U14*0.4 -> 1.34 | Z14: 1 | AA14: =INT(AC14/3) -> 8 | AB14: 5 | AC14: 24 | AD14: =IF(AC14=24,15,IF(AC14=12,10,0)) -> 15 | AE14: 0.4 | AF14: =AE14*1.1 -> 0.44 | AG14: =AF14*AC14 -> 10.56 | AK14: 2
A15: WEPP | B15: C | C15: 2 | D15: =IF(C15=1,"Motor y Transmisión",IF(C15=2,"Refrigeración",IF(C15=3,"Climatización",IF(C15=4,"Sistema de Combustión",IF(C15=5,"Frenos",IF(C15=6,"Mantenimiento y Cuidado",IF(C15=7,"Carrocería",""))))))) -> Refrigeración | E15: 1 | F15: 2023 | G15: =AE15*1000 -> 400 | H15: Kühlerreinigung | I15: Limpia Radiadores | J15: =F15 -> 2023 | K15: =G15 -> 400 | L15: 2.75 | M15: 0.3 | N15: 0 | O15: 0.3 | P15: 0.3 | Q15: =+L15+M15+N15+O15+P15 -> 3.65 | R15: 7.45 | S15: =R15*1.1 -> 8.195 | T15: 14.15 | U15: =R15-Q15 -> 3.8 | V15: =U15*0.6 -> 2.28 | W15: =U15*0.4 -> 1.52 | Z15: 1 | AA15: =INT(AC15/3) -> 8 | AB15: 5 | AC15: 24 | AD15: =IF(AC15=24,15,IF(AC15=12,10,0)) -> 15 | AE15: 0.4 | AF15: =AE15*1.1 -> 0.44 | AG15: =AF15*AC15 -> 10.56 | AK15: 2
A16: WEPP | B16: C | C16: 2 | D16: =IF(C16=1,"Motor y Transmisión",IF(C16=2,"Refrigeración",IF(C16=3,"Climatización",IF(C16=4,"Sistema de Combustión",IF(C16=5,"Frenos",IF(C16=6,"Mantenimiento y Cuidado",IF(C16=7,"Carrocería",""))))))) -> Refrigeración | E16: 1 | F16: 2123 | G16: =AE16*1000 -> 500 | H16: Thermoschutz | I16: Protector Térmico | J16: =F16 -> 2123 | K16: =G16 -> 500 | L16: 4.9 | M16: 0.3 | N16: 0 | O16: 0.3 | P16: 0.3 | Q16: =+L16+M16+N16+O16+P16 -> 5.8 | R16: 12 | S16: =R16*1.1 -> 13.2 | U16: =R16-Q16 -> 6.2 | V16: =U16*0.6 -> 3.72 | W16: =U16*0.4 -> 2.48 | Z16: 1 | AA16: =INT(AC16/3) -> 4 | AB16: 5 | AC16: 12 | AD16: =IF(AC16=24,15,IF(AC16=12,10,0)) -> 10 | AE16: 0.5 | AF16: =AE16*1.1 -> 0.55 | AG16: =AF16*AC16 -> 6.6
A17: WEPP | B17: C | C17: 3 | D17: =IF(C17=1,"Motor y Transmisión",IF(C17=2,"Refrigeración",IF(C17=3,"Climatización",IF(C17=4,"Sistema de Combustión",IF(C17=5,"Frenos",IF(C17=6,"Mantenimiento y Cuidado",IF(C17=7,"Carrocería",""))))))) -> Climatización | E17: 0 | F17: 2024-1000 | G17: =AE17*1000 -> 1000 | H17: Klimafresh | I17: Climafresh | J17: =F17 -> 2024-1000 | K17: =G17 -> 1000 | L17: 5.5 | M17: 0.3 | N17: 0 | O17: 0.3 | P17: 0.3 | Q17: =+L17+M17+N17+O17+P17 -> 6.4 | R17: 13.7 | S17: =R17*1.1 -> 15.07 | U17: =R17-Q17 -> 7.3 | V17: =U17*0.6 -> 4.38 | W17: =U17*0.4 -> 2.92 | Z17: 1 | AA17: =INT(AC17/3) -> 4 | AB17: 5 | AC17: 12 | AD17: =IF(AC17=24,15,IF(AC17=12,10,0)) -> 10 | AE17: 1 | AF17: =AE17*1.1 -> 1.1 | AG17: =AF17*AC17 -> 13.2 | AK17: ?
A18: WEPP | B18: C | C18: 3 | D18: =IF(C18=1,"Motor y Transmisión",IF(C18=2,"Refrigeración",IF(C18=3,"Climatización",IF(C18=4,"Sistema de Combustión",IF(C18=5,"Frenos",IF(C18=6,"Mantenimiento y Cuidado",IF(C18=7,"Carrocería",""))))))) -> Climatización | E18: 1 | F18: 2025 | G18: =AE18*1000 -> 100 | H18: Airfresh | I18: Airfresh | J18: =F18 -> 2025 | K18: =G18 -> 100 | L18: 3.35 | M18: 0.3 | N18: 0 | O18: 0.3 | P18: 0.3 | Q18: =+L18+M18+N18+O18+P18 -> 4.25 | R18: 9.25 | S18: =R18*1.1 -> 10.175 | T18: 15.2 | U18: =R18-Q18 -> 5 | V18: =U18*0.6 -> 3 | W18: =U18*0.4 -> 2 | Z18: 1 | AA18: =INT(AC18/3) -> 8 | AB18: 5 | AC18: 24 | AD18: =IF(AC18=24,15,IF(AC18=12,10,0)) -> 15 | AE18: 0.1 | AF18: =AE18*1.1 -> 0.11 | AG18: =AF18*AC18 -> 2.64 | AK18: 1
A19: WEPP | B19: C | C19: 3 | D19: =IF(C19=1,"Motor y Transmisión",IF(C19=2,"Refrigeración",IF(C19=3,"Climatización",IF(C19=4,"Sistema de Combustión",IF(C19=5,"Frenos",IF(C19=6,"Mantenimiento y Cuidado",IF(C19=7,"Carrocería",""))))))) -> Climatización | E19: 0 | F19: 2125 | G19: =AE19*1000 -> 100 | H19: Airfresh Mint | I19: Airfresh Menta | J19: =F19 -> 2125 | K19: =G19 -> 100 | L19: 3.35 | M19: 0.3 | N19: 0 | O19: 0.3 | P19: 0.3 | Q19: =+L19+M19+N19+O19+P19 -> 4.25 | R19: 9.25 | S19: =R19*1.1 -> 10.175 | T19: 15.2 | U19: =R19-Q19 -> 5 | V19: =U19*0.6 -> 3 | W19: =U19*0.4 -> 2 | Z19: 1 | AA19: =INT(AC19/3) -> 8 | AB19: 5 | AC19: 24 | AD19: =IF(AC19=24,15,IF(AC19=12,10,0)) -> 15 | AE19: 0.1 | AF19: =AE19*1.1 -> 0.11 | AG19: =AF19*AC19 -> 2.64 | AK19: 1
A20: WEPP | B20: C | C20: 3 | D20: =IF(C20=1,"Motor y Transmisión",IF(C20=2,"Refrigeración",IF(C20=3,"Climatización",IF(C20=4,"Sistema de Combustión",IF(C20=5,"Frenos",IF(C20=6,"Mantenimiento y Cuidado",IF(C20=7,"Carrocería",""))))))) -> Climatización | E20: 0 | F20: 2127 | G20: 75 | H20: Airclean | I20: Airclean Limpiador de Conductos de Aire | J20: =F20 -> 2127 | K20: =G20 -> 75 | L20: 3.35 | M20: 0.3 | N20: 0 | O20: 0.3 | P20: 0.3 | Q20: =+L20+M20+N20+O20+P20 -> 4.25 | R20: 9.25 | S20: =R20*1.1 -> 10.175 | T20: 15.2 | U20: =R20-Q20 -> 5 | V20: =U20*0.6 -> 3 | W20: =U20*0.4 -> 2 | Z20: 1 | AA20: =INT(AC20/3) -> 8 | AB20: 5 | AC20: 24 | AD20: =IF(AC20=24,15,IF(AC20=12,10,0)) -> 15 | AE20: 0.1 | AF20: =AE20*1.1 -> 0.11 | AG20: =AF20*AC20 -> 2.64 | AK20: 1
A21: WEPP | B21: C | C21: 3 | D21: =IF(C21=1,"Motor y Transmisión",IF(C21=2,"Refrigeración",IF(C21=3,"Climatización",IF(C21=4,"Sistema de Combustión",IF(C21=5,"Frenos",IF(C21=6,"Mantenimiento y Cuidado",IF(C21=7,"Carrocería",""))))))) -> Climatización | E21: 1 | F21: 7020100 | G21: =AE21*1000 -> 100 | H21: Leckstopp und Indikator | I21: Tapafugas A/C con Indicador de Fugas | J21: =F21 -> 7020100 | K21: =G21 -> 100 | L21: 6.8 | M21: 0.3 | N21: 0 | O21: 0.3 | P21: 0.3 | Q21: =+L21+M21+N21+O21+P21 -> 7.7 | R21: 21.2 | S21: =R21*1.1 -> 23.32 | T21: 33.7 | U21: =R21-Q21 -> 13.5 | V21: =U21*0.6 -> 8.1 | W21: =U21*0.4 -> 5.4 | Z21: 1 | AA21: =INT(AC21/3) -> 8 | AB21: 5 | AC21: 24 | AD21: =IF(AC21=24,15,IF(AC21=12,10,0)) -> 15 | AE21: 0.1 | AF21: =AE21*1.1 -> 0.11 | AG21: =AF21*AC21 -> 2.64 | AJ21: 1
A22: WEPP | B22: C | C22: 3 | D22: =IF(C22=1,"Motor y Transmisión",IF(C22=2,"Refrigeración",IF(C22=3,"Climatización",IF(C22=4,"Sistema de Combustión",IF(C22=5,"Frenos",IF(C22=6,"Mantenimiento y Cuidado",IF(C22=7,"Carrocería",""))))))) -> Climatización | E22: 1 | F22: 1711 | G22: =AE22*1000 -> 100 | H22: AC Aerosol Adapter | I22: Adaptador tapafugas | J22: =F22 -> 1711 | K22: =G22 -> 100 | L22: 2.5 | M22: 0.3 | N22: 0 | O22: 0.3 | P22: 0.3 | Q22: =+L22+M22+N22+O22+P22 -> 3.4 | R22: 7 | S22: =R22*1.1 -> 7.7 | U22: =R22-Q22 -> 3.6 | V22: =U22*0.6 -> 2.16 | W22: =U22*0.4 -> 1.44 | Z22: 1 | AA22: =INT(AC22/3) -> 0 | AB22: 5 | AC22: 1 | AD22: =IF(AC22=24,15,IF(AC22=12,10,0)) -> 0 | AE22: 0.1 | AF22: =AE22*1.1 -> 0.11 | AG22: =AF22*AC22 -> 0.11 | AK22: 1
A23: WEPP | B23: C | C23: 3 | D23: =IF(C23=1,"Motor y Transmisión",IF(C23=2,"Refrigeración",IF(C23=3,"Climatización",IF(C23=4,"Sistema de Combustión",IF(C23=5,"Frenos",IF(C23=6,"Mantenimiento y Cuidado",IF(C23=7,"Carrocería",""))))))) -> Climatización | E23: 1 | F23: 7021100 | G23: =AE23*1000 -> 100 | H23: Leckstopp komplett | I23: Tapafugas A/C sin Indicador de Fugas 100 | J23: =F23 -> 7021100 | K23: =G23 -> 100 | L23: 15.5 | M23: 0.3 | N23: 0 | O23: 0.3 | P23: 0.3 | Q23: =+L23+M23+N23+O23+P23 -> 16.4 | R23: 44.7 | S23: =R23*1.1 -> 49.17 | T23: 71.7 | U23: =R23-Q23 -> 28.3 | V23: =U23*0.6 -> 16.98 | W23: =U23*0.4 -> 11.32 | Z23: 1 | AA23: =INT(AC23/3) -> 8 | AB23: 5 | AC23: 24 | AD23: =IF(AC23=24,15,IF(AC23=12,10,0)) -> 15 | AE23: 0.1 | AF23: =AE23*1.1 -> 0.11 | AG23: =AF23*AC23 -> 2.64 | AJ23: 6
A24: WEPP | B24: C | C24: 3 | D24: =IF(C24=1,"Motor y Transmisión",IF(C24=2,"Refrigeración",IF(C24=3,"Climatización",IF(C24=4,"Sistema de Combustión",IF(C24=5,"Frenos",IF(C24=6,"Mantenimiento y Cuidado",IF(C24=7,"Carrocería",""))))))) -> Climatización | E24: 1 | F24: 7050250 | G24: =AE24*1000 -> 250 | H24: AC Leckindikator | I24: Indicador de Fuga de A/C 250 | J24: =F24 -> 7050250 | K24: =G24 -> 250 | L24: 12.9 | M24: 0.3 | N24: 0 | O24: 0.3 | P24: 0.3 | Q24: =+L24+M24+N24+O24+P24 -> 13.8 | R24: 30.7 | S24: =R24*1.1 -> 33.77 | T24: 47.1 | U24: =R24-Q24 -> 16.9 | V24: =U24*0.6 -> 10.14 | W24: =U24*0.4 -> 6.76 | Z24: 1 | AA24: =INT(AC24/3) -> 8 | AB24: 5 | AC24: 24 | AD24: =IF(AC24=24,15,IF(AC24=12,10,0)) -> 15 | AE24: 0.25 | AF24: =AE24*1.1 -> 0.275 | AG24: =AF24*AC24 -> 6.6 | AJ24: 6
A25: WEPP | B25: C | C25: 3 | D25: =IF(C25=1,"Motor y Transmisión",IF(C25=2,"Refrigeración",IF(C25=3,"Climatización",IF(C25=4,"Sistema de Combustión",IF(C25=5,"Frenos",IF(C25=6,"Mantenimiento y Cuidado",IF(C25=7,"Carrocería",""))))))) -> Climatización | E25: 1 | F25: 7050001 | G25: =AE25*1000 -> 1000 | H25: AC Leckindikator | I25: Indicador de Fuga de A/C 1000 | J25: =F25 -> 7050001 | K25: =G25 -> 1000 | L25: 49 | M25: 0.3 | N25: 0 | O25: 0.3 | P25: 0.3 | Q25: =+L25+M25+N25+O25+P25 -> 49.9 | R25: 130.1 | S25: =R25*1.1 -> 143.11 | U25: =R25-Q25 -> 80.2 | V25: =U25*0.6 -> 48.12 | W25: =U25*0.4 -> 32.08 | Z25: 1 | AA25: =INT(AC25/3) -> 4 | AB25: 5 | AC25: 12 | AD25: =IF(AC25=24,15,IF(AC25=12,10,0)) -> 10 | AE25: 1 | AF25: =AE25*1.1 -> 1.1 | AG25: =AF25*AC25 -> 13.2 | AJ25: 6
A26: WEPP | B26: C | C26: 3 | D26: =IF(C26=1,"Motor y Transmisión",IF(C26=2,"Refrigeración",IF(C26=3,"Climatización",IF(C26=4,"Sistema de Combustión",IF(C26=5,"Frenos",IF(C26=6,"Mantenimiento y Cuidado",IF(C26=7,"Carrocería",""))))))) -> Climatización | E26: 1 | F26: 7034001 | G26: =AE26*1000 -> 1000 | H26: POE 68 | I26: Lubricante Universal POE 68 | J26: =F26 -> 7034001 | K26: =G26 -> 1000 | L26: 13.25 | M26: 0.3 | N26: 0 | O26: 0.3 | P26: 0.3 | Q26: =+L26+M26+N26+O26+P26 -> 14.15 | R26: 32 | S26: =R26*1.1 -> 35.2 | U26: =R26-Q26 -> 17.85 | V26: =U26*0.6 -> 10.71 | W26: =U26*0.4 -> 7.14 | Z26: 1 | AA26: =INT(AC26/3) -> 4 | AB26: 5 | AC26: 12 | AD26: =IF(AC26=24,15,IF(AC26=12,10,0)) -> 10 | AE26: 1 | AF26: =AE26*1.1 -> 1.1 | AG26: =AF26*AC26 -> 13.2
A27: WEPP | B27: C | C27: 3 | D27: =IF(C27=1,"Motor y Transmisión",IF(C27=2,"Refrigeración",IF(C27=3,"Climatización",IF(C27=4,"Sistema de Combustión",IF(C27=5,"Frenos",IF(C27=6,"Mantenimiento y Cuidado",IF(C27=7,"Carrocería",""))))))) -> Climatización | E27: 1 | F27: 7035001 | G27: =AE27*1000 -> 1000 | H27: POE 68 + UV | I27: Lubricante Universal POE 68 con Indicador UV | J27: =F27 -> 7035001 | K27: =G27 -> 1000 | L27: 13.85 | M27: 0.3 | N27: 0 | O27: 0.3 | P27: 0.3 | Q27: =+L27+M27+N27+O27+P27 -> 14.75 | R27: 32 | S27: =R27*1.1 -> 35.2 | U27: =R27-Q27 -> 17.25 | V27: =U27*0.6 -> 10.35 | W27: =U27*0.4 -> 6.9 | Z27: 1 | AA27: =INT(AC27/3) -> 4 | AB27: 5 | AC27: 12 | AD27: =IF(AC27=24,15,IF(AC27=12,10,0)) -> 10 | AE27: 1 | AF27: =AE27*1.1 -> 1.1 | AG27: =AF27*AC27 -> 13.2 | AJ27: 6
A28: WEPP | B28: C | C28: 3 | D28: =IF(C28=1,"Motor y Transmisión",IF(C28=2,"Refrigeración",IF(C28=3,"Climatización",IF(C28=4,"Sistema de Combustión",IF(C28=5,"Frenos",IF(C28=6,"Mantenimiento y Cuidado",IF(C28=7,"Carrocería",""))))))) -> Climatización | E28: 1 | F28: 2127 | G28: =AE28*1000 -> 100 | H28: Pollenfilterkanal Reiniger | I28: Airclean Limpiador de Conductos de Aire | J28: =F28 -> 2127 | K28: =G28 -> 100 | L28: 3.95 | M28: 0.3 | N28: 0 | O28: 0.3 | P28: 0.3 | Q28: =+L28+M28+N28+O28+P28 -> 4.85 | R28: 7.8 | S28: =R28*1.1 -> 8.58 | T28: 12.65 | U28: =R28-Q28 -> 2.95 | V28: =U28*0.6 -> 1.77 | W28: =U28*0.4 -> 1.18 | Z28: 1 | AA28: =INT(AC28/3) -> 8 | AB28: 5 | AC28: 24 | AD28: =IF(AC28=24,15,IF(AC28=12,10,0)) -> 15 | AE28: 0.1 | AF28: =AE28*1.1 -> 0.11 | AG28: =AF28*AC28 -> 2.64 | AK28: 1
A29: WEPP | B29: C | C29: 4 | D29: =IF(C29=1,"Motor y Transmisión",IF(C29=2,"Refrigeración",IF(C29=3,"Climatización",IF(C29=4,"Sistema de Combustión",IF(C29=5,"Frenos",IF(C29=6,"Mantenimiento y Cuidado",IF(C29=7,"Carrocería",""))))))) -> Sistema de Combustión | E29: 1 | F29: 2030 | G29: =AE29*1000 -> 500 | H29: Diesel Intensiv Reiniger | I29: Limpiador Intensivo Diésel | J29: =F29 -> 2030 | K29: =G29 -> 500 | L29: 3.65 | M29: 0.3 | N29: 0 | O29: 0.3 | P29: 0.3 | Q29: =+L29+M29+N29+O29+P29 -> 4.55 | R29: 9.05 | S29: =R29*1.1 -> 9.955 | T29: 17.5 | U29: =R29-Q29 -> 4.5 | V29: =U29*0.6 -> 2.7 | W29: =U29*0.4 -> 1.8 | Z29: 1 | AA29: =INT(AC29/3) -> 8 | AB29: 5 | AC29: 24 | AD29: =IF(AC29=24,15,IF(AC29=12,10,0)) -> 15 | AE29: 0.5 | AF29: =AE29*1.1 -> 0.55 | AG29: =AF29*AC29 -> 13.2 | AK29: 4
A30: WEPP | B30: C | C30: 4 | D30: =IF(C30=1,"Motor y Transmisión",IF(C30=2,"Refrigeración",IF(C30=3,"Climatización",IF(C30=4,"Sistema de Combustión",IF(C30=5,"Frenos",IF(C30=6,"Mantenimiento y Cuidado",IF(C30=7,"Carrocería",""))))))) -> Sistema de Combustión | E30: 1 | F30: 2130 | G30: =AE30*1000 -> 400 | H30: Diesel Einlass Reiniger Spray | I30: Limpiador de Admisión de Aire Diésel | J30: =F30 -> 2130 | K30: =G30 -> 400 | L30: 3.95 | M30: 0.3 | N30: 0 | O30: 0.3 | P30: 0.3 | Q30: =+L30+M30+N30+O30+P30 -> 4.85 | R30: 12.2 | S30: =R30*1.1 -> 13.42 | T30: 20.3 | U30: =R30-Q30 -> 7.35 | V30: =U30*0.6 -> 4.41 | W30: =U30*0.4 -> 2.94 | Z30: 1 | AA30: =INT(AC30/3) -> 8 | AB30: 5 | AC30: 24 | AD30: =IF(AC30=24,15,IF(AC30=12,10,0)) -> 15 | AE30: 0.4 | AF30: =AE30*1.1 -> 0.44 | AG30: =AF30*AC30 -> 10.56 | AJ30: 2
A31: WEPP | B31: C | C31: 4 | D31: =IF(C31=1,"Motor y Transmisión",IF(C31=2,"Refrigeración",IF(C31=3,"Climatización",IF(C31=4,"Sistema de Combustión",IF(C31=5,"Frenos",IF(C31=6,"Mantenimiento y Cuidado",IF(C31=7,"Carrocería",""))))))) -> Sistema de Combustión | E31: 1 | F31: 2230 | G31: =AE31*1000 -> 400 | H31: Turbo AGR Ansaugreiniger | I31: Limpiador Turbo EGR Aspiración | J31: =F31 -> 2230 | K31: =G31 -> 400 | L31: 6.5 | M31: 0.3 | N31: 0 | O31: 0.3 | P31: 0.3 | Q31: =+L31+M31+N31+O31+P31 -> 7.4 | R31: 17.9 | S31: =R31*1.1 -> 19.69 | T31: 29.6 | U31: =R31-Q31 -> 10.5 | V31: =U31*0.6 -> 6.3 | W31: =U31*0.4 -> 4.2 | Z31: 1 | AA31: =INT(AC31/3) -> 8 | AB31: 5 | AC31: 24 | AD31: =IF(AC31=24,15,IF(AC31=12,10,0)) -> 15 | AE31: 0.4 | AF31: =AE31*1.1 -> 0.44 | AG31: =AF31*AC31 -> 10.56 | AJ31: 2
A32: WEPP | B32: C | C32: 4 | D32: =IF(C32=1,"Motor y Transmisión",IF(C32=2,"Refrigeración",IF(C32=3,"Climatización",IF(C32=4,"Sistema de Combustión",IF(C32=5,"Frenos",IF(C32=6,"Mantenimiento y Cuidado",IF(C32=7,"Carrocería",""))))))) -> Sistema de Combustión | E32: 1 | F32: 2031 | G32: =AE32*1000 -> 400 | H32: Drosselklappen + Vergaserreiniger | I32: Limpiador de Válvulas de Mariposa y Carburadores | J32: =F32 -> 2031 | K32: =G32 -> 400 | L32: 3.5 | M32: 0.3 | N32: 0 | O32: 0.3 | P32: 0.3 | Q32: =+L32+M32+N32+O32+P32 -> 4.4 | R32: 9.05 | S32: =R32*1.1 -> 9.955 | T32: 15.45 | U32: =R32-Q32 -> 4.65 | V32: =U32*0.6 -> 2.79 | W32: =U32*0.4 -> 1.86 | Z32: 1 | AA32: =INT(AC32/3) -> 8 | AB32: 5 | AC32: 24 | AD32: =IF(AC32=24,15,IF(AC32=12,10,0)) -> 15 | AE32: 0.4 | AF32: =AE32*1.1 -> 0.44 | AG32: =AF32*AC32 -> 10.56 | AJ32: 12
A33: WEPP | B33: C | C33: 4 | D33: =IF(C33=1,"Motor y Transmisión",IF(C33=2,"Refrigeración",IF(C33=3,"Climatización",IF(C33=4,"Sistema de Combustión",IF(C33=5,"Frenos",IF(C33=6,"Mantenimiento y Cuidado",IF(C33=7,"Carrocería",""))))))) -> Sistema de Combustión | E33: 1 | F33: 2032-300 | G33: =AE33*1000 -> 300 | H33: Diesel System Schutz | I33: Protector Diésel 300 | J33: =F33 -> 2032-300 | K33: =G33 -> 300 | L33: 2.55 | M33: 0.3 | N33: 0 | O33: 0.3 | P33: 0.3 | Q33: =+L33+M33+N33+O33+P33 -> 3.45 | R33: 6.45 | S33: =R33*1.1 -> 7.095 | T33: 11.4 | U33: =R33-Q33 -> 3 | V33: =U33*0.6 -> 1.8 | W33: =U33*0.4 -> 1.2 | Z33: 1 | AA33: =INT(AC33/3) -> 8 | AB33: 5 | AC33: 24 | AD33: =IF(AC33=24,15,IF(AC33=12,10,0)) -> 15 | AE33: 0.3 | AF33: =AE33*1.1 -> 0.33 | AG33: =AF33*AC33 -> 7.92 | AK33: 1
A34: WEPP | B34: C | C34: 4 | D34: =IF(C34=1,"Motor y Transmisión",IF(C34=2,"Refrigeración",IF(C34=3,"Climatización",IF(C34=4,"Sistema de Combustión",IF(C34=5,"Frenos",IF(C34=6,"Mantenimiento y Cuidado",IF(C34=7,"Carrocería",""))))))) -> Sistema de Combustión | E34: 1 | F34: 2032 | G34: =AE34*1000 -> 400 | H34: Diesel System Schutz | I34: Protector Diésel 400 | J34: =F34 -> 2032 | K34: =G34 -> 400 | L34: 2.75 | M34: 0.3 | N34: 0 | O34: 0.3 | P34: 0.3 | Q34: =+L34+M34+N34+O34+P34 -> 3.65 | R34: 7.5 | S34: =R34*1.1 -> 8.25 | T34: 13.8 | U34: =R34-Q34 -> 3.85 | V34: =U34*0.6 -> 2.31 | W34: =U34*0.4 -> 1.54 | Z34: 1 | AA34: =INT(AC34/3) -> 8 | AB34: 5 | AC34: 24 | AD34: =IF(AC34=24,15,IF(AC34=12,10,0)) -> 15 | AE34: 0.4 | AF34: =AE34*1.1 -> 0.44 | AG34: =AF34*AC34 -> 10.56 | AK34: 1
A35: WEPP | B35: C | C35: 4 | D35: =IF(C35=1,"Motor y Transmisión",IF(C35=2,"Refrigeración",IF(C35=3,"Climatización",IF(C35=4,"Sistema de Combustión",IF(C35=5,"Frenos",IF(C35=6,"Mantenimiento y Cuidado",IF(C35=7,"Carrocería",""))))))) -> Sistema de Combustión | E35: 1 | F35: 2032+ | G35: =AE35*1000 -> 250 | H35: Diesel Complete Clean | I35: Diésel Limpieza Completa | J35: =F35 -> 2032+ | K35: =G35 -> 250 | L35: 3.6 | M35: 0.3 | N35: 0 | O35: 0.3 | P35: 0.3 | Q35: =+L35+M35+N35+O35+P35 -> 4.5 | R35: 8.9 | S35: =R35*1.1 -> 9.79 | T35: 17.3 | U35: =R35-Q35 -> 4.4 | V35: =U35*0.6 -> 2.64 | W35: =U35*0.4 -> 1.76 | Z35: 1 | AA35: =INT(AC35/3) -> 8 | AB35: 5 | AC35: 24 | AD35: =IF(AC35=24,15,IF(AC35=12,10,0)) -> 15 | AE35: 0.25 | AF35: =AE35*1.1 -> 0.275 | AG35: =AF35*AC35 -> 6.6 | AK35: 5
A36: WEPP | B36: C | C36: 4 | D36: =IF(C36=1,"Motor y Transmisión",IF(C36=2,"Refrigeración",IF(C36=3,"Climatización",IF(C36=4,"Sistema de Combustión",IF(C36=5,"Frenos",IF(C36=6,"Mantenimiento y Cuidado",IF(C36=7,"Carrocería",""))))))) -> Sistema de Combustión | E36: 1 | F36: 732 | G36: =AE36*1000 -> 50 | H36: SCR Schutz | I36: Protector SCR 50 | J36: =F36 -> 732 | K36: =G36 -> 50 | L36: 1.2 | M36: 0.3 | N36: 0 | O36: 0.3 | P36: 0.3 | Q36: =+L36+M36+N36+O36+P36 -> 2.1 | R36: 2.45 | S36: =R36*1.1 -> 2.695 | U36: =R36-Q36 -> 0.35 | V36: =U36*0.6 -> 0.21 | W36: =U36*0.4 -> 0.14 | Z36: 1 | AA36: =INT(AC36/3) -> 33 | AB36: 5 | AC36: 100 | AD36: =IF(AC36=24,15,IF(AC36=12,10,0)) -> 0 | AE36: 0.05 | AF36: =AE36*1.1 -> 0.055 | AG36: =AF36*AC36 -> 5.5 | AK36: 1
A37: WEPP | B37: C | C37: 4 | D37: =IF(C37=1,"Motor y Transmisión",IF(C37=2,"Refrigeración",IF(C37=3,"Climatización",IF(C37=4,"Sistema de Combustión",IF(C37=5,"Frenos",IF(C37=6,"Mantenimiento y Cuidado",IF(C37=7,"Carrocería",""))))))) -> Sistema de Combustión | E37: 1 | F37: 732-400 | G37: =AE37*1000 -> 400 | H37: SCR Schutz | I37: Protector SCR 400 | J37: =F37 -> 732-400 | K37: =G37 -> 400 | L37: 4.7 | M37: 0.3 | N37: 0 | O37: 0.3 | P37: 0.3 | Q37: =+L37+M37+N37+O37+P37 -> 5.6 | R37: 10.5 | S37: =R37*1.1 -> 11.55 | U37: =R37-Q37 -> 4.9 | V37: =U37*0.6 -> 2.94 | W37: =U37*0.4 -> 1.96 | Z37: 1 | AA37: =INT(AC37/3) -> 4 | AB37: 5 | AC37: 12 | AD37: =IF(AC37=24,15,IF(AC37=12,10,0)) -> 10 | AE37: 0.4 | AF37: =AE37*1.1 -> 0.44 | AG37: =AF37*AC37 -> 5.28 | AK37: 1
A38: WEPP | B38: C | C38: 4 | D38: =IF(C38=1,"Motor y Transmisión",IF(C38=2,"Refrigeración",IF(C38=3,"Climatización",IF(C38=4,"Sistema de Combustión",IF(C38=5,"Frenos",IF(C38=6,"Mantenimiento y Cuidado",IF(C38=7,"Carrocería",""))))))) -> Sistema de Combustión | E38: 1 | F38: 2132 | G38: =AE38*1000 -> 500 | H38: DPF/ Turbo Cleaner | I38: Limpiador DPF Turbo 500 | J38: =F38 -> 2132 | K38: =G38 -> 500 | L38: 5.5 | M38: 0.3 | N38: 0 | O38: 0.3 | P38: 0.3 | Q38: =+L38+M38+N38+O38+P38 -> 6.4 | R38: 16.4 | S38: =R38*1.1 -> 18.04 | T38: 26.1 | U38: =R38-Q38 -> 10 | V38: =U38*0.6 -> 6 | W38: =U38*0.4 -> 4 | Z38: 1 | AA38: =INT(AC38/3) -> 8 | AB38: 5 | AC38: 24 | AD38: =IF(AC38=24,15,IF(AC38=12,10,0)) -> 15 | AE38: 0.5 | AF38: =AE38*1.1 -> 0.55 | AG38: =AF38*AC38 -> 13.2 | AK38: 10
A39: WEPP | B39: C | C39: 4 | D39: =IF(C39=1,"Motor y Transmisión",IF(C39=2,"Refrigeración",IF(C39=3,"Climatización",IF(C39=4,"Sistema de Combustión",IF(C39=5,"Frenos",IF(C39=6,"Mantenimiento y Cuidado",IF(C39=7,"Carrocería",""))))))) -> Sistema de Combustión | F39: 2132-300 | G39: =AE39*1000 -> 300 | H39: DPF/ Turbo Cleaner | I39: Limpiador DPF Turbo 300 | J39: =F39 -> 2132-300 | K39: =G39 -> 300 | L39: 3.9 | M39: 0.3 | N39: 0 | O39: 0.3 | P39: 0.3 | Q39: =+L39+M39+N39+O39+P39 -> 4.8 | R39: 9.8 | S39: =R39*1.1 -> 10.78 | T39: 18.3 | U39: =R39-Q39 -> 5 | V39: =U39*0.6 -> 3 | W39: =U39*0.4 -> 2 | Z39: 1 | AA39: =INT(AC39/3) -> 8 | AB39: 5 | AC39: 24 | AD39: =IF(AC39=24,15,IF(AC39=12,10,0)) -> 15 | AE39: 0.3 | AF39: =AE39*1.1 -> 0.33 | AG39: =AF39*AC39 -> 7.92
A40: WEPP | B40: C | C40: 4 | D40: =IF(C40=1,"Motor y Transmisión",IF(C40=2,"Refrigeración",IF(C40=3,"Climatización",IF(C40=4,"Sistema de Combustión",IF(C40=5,"Frenos",IF(C40=6,"Mantenimiento y Cuidado",IF(C40=7,"Carrocería",""))))))) -> Sistema de Combustión | E40: 1 | F40: 2232 | G40: =AE40*1000 -> 500 | H40: DPF Direct Cleaner | I40: Limpiador Directo DPF | J40: =F40 -> 2232 | K40: =G40 -> 500 | L40: 6.85 | M40: 0.3 | N40: 0 | O40: 0.3 | P40: 0.3 | Q40: =+L40+M40+N40+O40+P40 -> 7.75 | R40: 18.3 | S40: =R40*1.1 -> 20.13 | T40: 30 | U40: =R40-Q40 -> 10.55 | V40: =U40*0.6 -> 6.33 | W40: =U40*0.4 -> 4.22 | Z40: 1 | AA40: =INT(AC40/3) -> 4 | AB40: 5 | AC40: 12 | AD40: =IF(AC40=24,15,IF(AC40=12,10,0)) -> 10 | AE40: 0.5 | AF40: =AE40*1.1 -> 0.55 | AG40: =AF40*AC40 -> 6.6 | AJ40: 6
A41: WEPP | B41: C | C41: 4 | D41: =IF(C41=1,"Motor y Transmisión",IF(C41=2,"Refrigeración",IF(C41=3,"Climatización",IF(C41=4,"Sistema de Combustión",IF(C41=5,"Frenos",IF(C41=6,"Mantenimiento y Cuidado",IF(C41=7,"Carrocería",""))))))) -> Sistema de Combustión | E41: 1 | F41: 39000 | G41: =AE41*1000 -> 2000 | H41: Druckbecherpistole | I41: Pistola de Apliación para WEPP 2232 | J41: =F41 -> 39000 | K41: - | L41: 135 | M41: 0.3 | N41: 0 | O41: 0.3 | P41: 0.3 | Q41: =+L41+M41+N41+O41+P41 -> 135.9 | R41: 170 | S41: =R41*1.1 -> 187 | U41: =R41-Q41 -> 34.1 | V41: =U41*0.6 -> 20.46 | W41: =U41*0.4 -> 13.64 | Z41: 1 | AA41: =INT(AC41/3) -> 0 | AB41: 5 | AC41: 1 | AD41: =IF(AC41=24,15,IF(AC41=12,10,0)) -> 0 | AE41: 2 | AF41: =AE41*1.1 -> 2.2 | AG41: =AF41*AC41 -> 2.2 | AJ41: 1
A42: WEPP | B42: C | C42: 4 | D42: =IF(C42=1,"Motor y Transmisión",IF(C42=2,"Refrigeración",IF(C42=3,"Climatización",IF(C42=4,"Sistema de Combustión",IF(C42=5,"Frenos",IF(C42=6,"Mantenimiento y Cuidado",IF(C42=7,"Carrocería",""))))))) -> Sistema de Combustión | E42: 1 | F42: 39001 | G42: =AE42*1000 -> 100 | H42: Hohlraumschlauch | I42: Sonda para pistola 39000 | J42: =F42 -> 39001 | K42: - | L42: 20 | M42: 0.3 | N42: 0 | O42: 0.3 | P42: 0.3 | Q42: =+L42+M42+N42+O42+P42 -> 20.9 | R42: 30.95 | S42: =R42*1.1 -> 34.045 | U42: =R42-Q42 -> 10.05 | V42: =U42*0.6 -> 6.03 | W42: =U42*0.4 -> 4.02 | Z42: 1 | AA42: =INT(AC42/3) -> 0 | AB42: 5 | AC42: 1 | AD42: =IF(AC42=24,15,IF(AC42=12,10,0)) -> 0 | AE42: 0.1 | AF42: =AE42*1.1 -> 0.11 | AG42: =AF42*AC42 -> 0.11 | AJ42: 2
A43: WEPP | B43: C | C43: 4 | D43: =IF(C43=1,"Motor y Transmisión",IF(C43=2,"Refrigeración",IF(C43=3,"Climatización",IF(C43=4,"Sistema de Combustión",IF(C43=5,"Frenos",IF(C43=6,"Mantenimiento y Cuidado",IF(C43=7,"Carrocería",""))))))) -> Sistema de Combustión | E43: 1 | F43: 2033 | G43: =AE43*1000 -> 400 | H43: Ventil Reiniger | I43: Limpiador Intensivo de Válvulas | J43: =F43 -> 2033 | K43: =G43 -> 400 | L43: 4.9 | M43: 0.3 | N43: 0 | O43: 0.3 | P43: 0.3 | Q43: =+L43+M43+N43+O43+P43 -> 5.8 | R43: 9.2 | S43: =R43*1.1 -> 10.12 | T43: 16.95 | U43: =R43-Q43 -> 3.4 | V43: =U43*0.6 -> 2.04 | W43: =U43*0.4 -> 1.36 | Z43: 1 | AA43: =INT(AC43/3) -> 8 | AB43: 5 | AC43: 24 | AD43: =IF(AC43=24,15,IF(AC43=12,10,0)) -> 15 | AE43: 0.4 | AF43: =AE43*1.1 -> 0.44 | AG43: =AF43*AC43 -> 10.56 | AJ43: 4
A44: WEPP | B44: C | C44: 4 | D44: =IF(C44=1,"Motor y Transmisión",IF(C44=2,"Refrigeración",IF(C44=3,"Climatización",IF(C44=4,"Sistema de Combustión",IF(C44=5,"Frenos",IF(C44=6,"Mantenimiento y Cuidado",IF(C44=7,"Carrocería",""))))))) -> Sistema de Combustión | E44: 0 | F44: 2034 | G44: =AE44*1000 -> 500 | H44: Injection Cleaner | I44: Limpiador de Inyección Gasolina 500 | J44: =F44 -> 2034 | K44: =G44 -> 500 | L44: 4.75 | M44: 0.3 | N44: 0 | O44: 0.3 | P44: 0.3 | Q44: =+L44+M44+N44+O44+P44 -> 5.65 | R44: 14.6 | S44: =R44*1.1 -> 16.06 | T44: 25.6 | U44: =R44-Q44 -> 8.95 | V44: =U44*0.6 -> 5.37 | W44: =U44*0.4 -> 3.58 | Z44: 1 | AA44: =INT(AC44/3) -> 8 | AB44: 5 | AC44: 24 | AD44: =IF(AC44=24,15,IF(AC44=12,10,0)) -> 15 | AE44: 0.5 | AF44: =AE44*1.1 -> 0.55 | AG44: =AF44*AC44 -> 13.2 | AK44: 2
A45: WEPP | B45: C | C45: 4 | D45: =IF(C45=1,"Motor y Transmisión",IF(C45=2,"Refrigeración",IF(C45=3,"Climatización",IF(C45=4,"Sistema de Combustión",IF(C45=5,"Frenos",IF(C45=6,"Mantenimiento y Cuidado",IF(C45=7,"Carrocería",""))))))) -> Sistema de Combustión | E45: 0 | F45: 2034-300 | G45: =AE45*1000 -> 300 | H45: Injection Cleaner | I45: Limpiador de Inyección Gasolina 300 | J45: =F45 -> 2034-300 | K45: =G45 -> 300 | L45: 3.5 | M45: 0.3 | N45: 0 | O45: 0.3 | P45: 0.3 | Q45: =+L45+M45+N45+O45+P45 -> 4.4 | R45: 8.75 | S45: =R45*1.1 -> 9.625 | T45: 15.4 | U45: =R45-Q45 -> 4.35 | V45: =U45*0.6 -> 2.61 | W45: =U45*0.4 -> 1.74 | Z45: 1 | AA45: =INT(AC45/3) -> 8 | AB45: 5 | AC45: 24 | AD45: =IF(AC45=24,15,IF(AC45=12,10,0)) -> 15 | AE45: 0.3 | AF45: =AE45*1.1 -> 0.33 | AG45: =AF45*AC45 -> 7.92 | AK45: 2
A46: WEPP | B46: C | C46: 4 | D46: =IF(C46=1,"Motor y Transmisión",IF(C46=2,"Refrigeración",IF(C46=3,"Climatización",IF(C46=4,"Sistema de Combustión",IF(C46=5,"Frenos",IF(C46=6,"Mantenimiento y Cuidado",IF(C46=7,"Carrocería",""))))))) -> Sistema de Combustión | F46: 2036 | G46: =AE46*1000 -> 400 | H46: Einspritz System Schutz | I46: Protector del Sistema de Inyección 400 | J46: =F46 -> 2036 | K46: =G46 -> 400 | L46: 2.8 | M46: 0.3 | N46: 0 | O46: 0.3 | P46: 0.3 | Q46: =+L46+M46+N46+O46+P46 -> 3.7 | R46: 7.3 | S46: =R46*1.1 -> 8.03 | T46: 14 | U46: =R46-Q46 -> 3.6 | V46: =U46*0.6 -> 2.16 | W46: =U46*0.4 -> 1.44 | Z46: 1 | AA46: =INT(AC46/3) -> 8 | AB46: 5 | AC46: 24 | AD46: =IF(AC46=24,15,IF(AC46=12,10,0)) -> 15 | AE46: 0.4 | AF46: =AE46*1.1 -> 0.44 | AG46: =AF46*AC46 -> 10.56
A47: WEPP | B47: C | C47: 4 | D47: =IF(C47=1,"Motor y Transmisión",IF(C47=2,"Refrigeración",IF(C47=3,"Climatización",IF(C47=4,"Sistema de Combustión",IF(C47=5,"Frenos",IF(C47=6,"Mantenimiento y Cuidado",IF(C47=7,"Carrocería",""))))))) -> Sistema de Combustión | F47: 2036-300 | G47: =AE47*1000 -> 300 | H47: Einspritz System Schutz | I47: Protector del Sistema de Inyección 300 | J47: =F47 -> 2036-300 | K47: =G47 -> 300 | L47: 2.6 | M47: 0.3 | N47: 0 | O47: 0.3 | P47: 0.3 | Q47: =+L47+M47+N47+O47+P47 -> 3.5 | R47: 5.7 | S47: =R47*1.1 -> 6.27 | T47: 11 | U47: =R47-Q47 -> 2.2 | V47: =U47*0.6 -> 1.32 | W47: =U47*0.4 -> 0.88 | Z47: 1 | AA47: =INT(AC47/3) -> 8 | AB47: 5 | AC47: 24 | AD47: =IF(AC47=24,15,IF(AC47=12,10,0)) -> 15 | AE47: 0.3 | AF47: =AE47*1.1 -> 0.33 | AG47: =AF47*AC47 -> 7.92
A48: WEPP | B48: C | C48: 4 | D48: =IF(C48=1,"Motor y Transmisión",IF(C48=2,"Refrigeración",IF(C48=3,"Climatización",IF(C48=4,"Sistema de Combustión",IF(C48=5,"Frenos",IF(C48=6,"Mantenimiento y Cuidado",IF(C48=7,"Carrocería",""))))))) -> Sistema de Combustión | F48: 2036+ | G48: =AE48*1000 -> 250 | H48: GDI Protection Bezin | I48: Protector GDI | J48: =F48 -> 2036+ | K48: =G48 -> 250 | L48: 3.75 | M48: 0.3 | N48: 0 | O48: 0.3 | P48: 0.3 | Q48: =+L48+M48+N48+O48+P48 -> 4.65 | R48: 9.1 | S48: =R48*1.1 -> 10.01 | T48: 17.9 | U48: =R48-Q48 -> 4.45 | V48: =U48*0.6 -> 2.67 | W48: =U48*0.4 -> 1.78 | Z48: 1 | AA48: =INT(AC48/3) -> 8 | AB48: 5 | AC48: 24 | AD48: =IF(AC48=24,15,IF(AC48=12,10,0)) -> 15 | AE48: 0.25 | AF48: =AE48*1.1 -> 0.275 | AG48: =AF48*AC48 -> 6.6
A49: WEPP | B49: C | C49: 4 | D49: =IF(C49=1,"Motor y Transmisión",IF(C49=2,"Refrigeración",IF(C49=3,"Climatización",IF(C49=4,"Sistema de Combustión",IF(C49=5,"Frenos",IF(C49=6,"Mantenimiento y Cuidado",IF(C49=7,"Carrocería",""))))))) -> Sistema de Combustión | F49: 2536 | G49: =AE49*1000 -> 250 | H49: Hybrid Benzin Additiv | I49: Aditivo para Motores Híbridos | J49: =F49 -> 2536 | K49: =G49 -> 250 | L49: 2.95 | M49: 0.3 | N49: 0 | O49: 0.3 | P49: 0.3 | Q49: =+L49+M49+N49+O49+P49 -> 3.85 | R49: 9.95 | S49: =R49*1.1 -> 10.945 | T49: 18.4 | U49: =R49-Q49 -> 6.1 | V49: =U49*0.6 -> 3.66 | W49: =U49*0.4 -> 2.44 | Z49: 1 | AA49: =INT(AC49/3) -> 8 | AB49: 5 | AC49: 24 | AD49: =IF(AC49=24,15,IF(AC49=12,10,0)) -> 15 | AE49: 0.25 | AF49: =AE49*1.1 -> 0.275 | AG49: =AF49*AC49 -> 6.6
A50: WEPP | B50: C | C50: 4 | D50: =IF(C50=1,"Motor y Transmisión",IF(C50=2,"Refrigeración",IF(C50=3,"Climatización",IF(C50=4,"Sistema de Combustión",IF(C50=5,"Frenos",IF(C50=6,"Mantenimiento y Cuidado",IF(C50=7,"Carrocería",""))))))) -> Sistema de Combustión | F50: 2038 | G50: =AE50*1000 -> 400 | H50: Active Solvent | I50: Disolvente Activo | J50: =F50 -> 2038 | K50: =G50 -> 400 | L50: 4.5 | M50: 0.3 | N50: 0 | O50: 0.3 | P50: 0.3 | Q50: =+L50+M50+N50+O50+P50 -> 5.4 | R50: 12.85 | S50: =R50*1.1 -> 14.135 | U50: =R50-Q50 -> 7.45 | V50: =U50*0.6 -> 4.47 | W50: =U50*0.4 -> 2.98 | Z50: 1 | AA50: =INT(AC50/3) -> 8 | AB50: 5 | AC50: 24 | AD50: =IF(AC50=24,15,IF(AC50=12,10,0)) -> 15 | AE50: 0.4 | AF50: =AE50*1.1 -> 0.44 | AG50: =AF50*AC50 -> 10.56
A51: WEPP | B51: C | C51: 5 | D51: =IF(C51=1,"Motor y Transmisión",IF(C51=2,"Refrigeración",IF(C51=3,"Climatización",IF(C51=4,"Sistema de Combustión",IF(C51=5,"Frenos",IF(C51=6,"Mantenimiento y Cuidado",IF(C51=7,"Carrocería",""))))))) -> Frenos | F51: 2055 | G51: =AE51*1000 -> 400 | H51: Bremsen System Schuz Spray | I51: Protector del Sistema de Frenos 400 | J51: =F51 -> 2055 | K51: =G51 -> 400 | L51: 4.9 | M51: 0.3 | N51: 0 | O51: 0.3 | P51: 0.3 | Q51: =+L51+M51+N51+O51+P51 -> 5.8 | R51: 11.8 | S51: =R51*1.1 -> 12.98 | U51: =R51-Q51 -> 6 | V51: =U51*0.6 -> 3.6 | W51: =U51*0.4 -> 2.4 | Z51: 1 | AA51: =INT(AC51/3) -> 8 | AB51: 5 | AC51: 24 | AD51: =IF(AC51=24,15,IF(AC51=12,10,0)) -> 15 | AE51: 0.4 | AF51: =AE51*1.1 -> 0.44 | AG51: =AF51*AC51 -> 10.56
A52: WEPP | B52: C | C52: 5 | D52: =IF(C52=1,"Motor y Transmisión",IF(C52=2,"Refrigeración",IF(C52=3,"Climatización",IF(C52=4,"Sistema de Combustión",IF(C52=5,"Frenos",IF(C52=6,"Mantenimiento y Cuidado",IF(C52=7,"Carrocería",""))))))) -> Frenos | F52: 2057 | G52: =AE52*1000 -> 50 | H52: Bremsen System Schuz Spray | I52: Protector del Sistema de Frenos 50 | J52: =F52 -> 2057 | K52: =G52 -> 50 | L52: 2.45 | M52: 0.3 | N52: 0 | O52: 0.3 | P52: 0.3 | Q52: =+L52+M52+N52+O52+P52 -> 3.35 | R52: 4.25 | S52: =R52*1.1 -> 4.675 | U52: =R52-Q52 -> 0.9 | V52: =U52*0.6 -> 0.54 | W52: =U52*0.4 -> 0.36 | Z52: 1 | AA52: =INT(AC52/3) -> 16 | AB52: 5 | AC52: 48 | AD52: =IF(AC52=24,15,IF(AC52=12,10,0)) -> 0 | AE52: 0.05 | AF52: =AE52*1.1 -> 0.055 | AG52: =AF52*AC52 -> 2.64
A53: WEPP | B53: C | C53: 5 | D53: =IF(C53=1,"Motor y Transmisión",IF(C53=2,"Refrigeración",IF(C53=3,"Climatización",IF(C53=4,"Sistema de Combustión",IF(C53=5,"Frenos",IF(C53=6,"Mantenimiento y Cuidado",IF(C53=7,"Carrocería",""))))))) -> Frenos | F53: 255 | G53: =AE53*1000 -> 400 | H53: Bremsen Hi Tec | I53: Frenos Hi Tec | J53: =F53 -> 255 | K53: =G53 -> 400 | L53: 3.75 | M53: 0.3 | N53: 0 | O53: 0.3 | P53: 0.3 | Q53: =+L53+M53+N53+O53+P53 -> 4.65 | R53: 10.6 | S53: =R53*1.1 -> 11.66 | U53: =R53-Q53 -> 5.95 | V53: =U53*0.6 -> 3.57 | W53: =U53*0.4 -> 2.38 | Z53: 1 | AA53: =INT(AC53/3) -> 8 | AB53: 5 | AC53: 24 | AD53: =IF(AC53=24,15,IF(AC53=12,10,0)) -> 15 | AE53: 0.4 | AF53: =AE53*1.1 -> 0.44 | AG53: =AF53*AC53 -> 10.56
A54: WEPP | B54: C | C54: 5 | D54: =IF(C54=1,"Motor y Transmisión",IF(C54=2,"Refrigeración",IF(C54=3,"Climatización",IF(C54=4,"Sistema de Combustión",IF(C54=5,"Frenos",IF(C54=6,"Mantenimiento y Cuidado",IF(C54=7,"Carrocería",""))))))) -> Frenos | F54: 2255 | G54: =AE54*1000 -> 200 | H54: Bremsenpaste mit Keramik | I54: Pasta de Frenos con Cerámica | J54: =F54 -> 2255 | K54: =G54 -> 200 | M54: 0.3 | N54: 0 | O54: 0.3 | P54: 0.3 | Q54: =+L54+M54+N54+O54+P54 -> 0.9 | S54: =R54*1.1 -> 0 | U54: =R54-Q54 -> -0.9 | V54: =U54*0.6 -> -0.54 | W54: =U54*0.4 -> -0.36 | AA54: =INT(AC54/3) -> 0 | AB54: 5 | AD54: =IF(AC54=24,15,IF(AC54=12,10,0)) -> 0 | AE54: 0.2 | AF54: =AE54*1.1 -> 0.22 | AG54: =AF54*AC54 -> 0
A55: WEPP | B55: C | C55: 5 | D55: =IF(C55=1,"Motor y Transmisión",IF(C55=2,"Refrigeración",IF(C55=3,"Climatización",IF(C55=4,"Sistema de Combustión",IF(C55=5,"Frenos",IF(C55=6,"Mantenimiento y Cuidado",IF(C55=7,"Carrocería",""))))))) -> Frenos | F55: 2455 | G55: =AE55*1000 -> 200 | H55: Bremsen Paste | I55: Pasta de Frenos | J55: =F55 -> 2455 | K55: =G55 -> 200 | L55: 7.55 | M55: 0.3 | N55: 0 | O55: 0.3 | P55: 0.3 | Q55: =+L55+M55+N55+O55+P55 -> 8.45 | R55: 18.25 | S55: =R55*1.1 -> 20.075 | U55: =R55-Q55 -> 9.8 | V55: =U55*0.6 -> 5.88 | W55: =U55*0.4 -> 3.92 | Z55: 1 | AA55: =INT(AC55/3) -> 4 | AB55: 5 | AC55: 12 | AD55: =IF(AC55=24,15,IF(AC55=12,10,0)) -> 10 | AE55: 0.2 | AF55: =AE55*1.1 -> 0.22 | AG55: =AF55*AC55 -> 2.64
A56: WEPP | B56: C | C56: 6 | D56: =IF(C56=1,"Motor y Transmisión",IF(C56=2,"Refrigeración",IF(C56=3,"Climatización",IF(C56=4,"Sistema de Combustión",IF(C56=5,"Frenos",IF(C56=6,"Mantenimiento y Cuidado",IF(C56=7,"Carrocería",""))))))) -> Mantenimiento y Cuidado | E56: 0 | F56: 2022 | G56: =AE56*1000 -> 1000 | H56: Scheibenfrostschutz | I56: Anticongelante para Parabrisas | J56: =F56 -> 2022 | K56: =G56 -> 1000 | L56: 1.85 | M56: 0.3 | N56: 0 | O56: 0.3 | P56: 0.3 | Q56: =+L56+M56+N56+O56+P56 -> 2.75 | R56: 1.95 | S56: =R56*1.1 -> 2.145 | U56: =R56-Q56 -> -0.8 | V56: =U56*0.6 -> -0.48 | W56: =U56*0.4 -> -0.32 | Z56: 1 | AA56: =INT(AC56/3) -> 4 | AB56: 5 | AC56: 12 | AD56: =IF(AC56=24,15,IF(AC56=12,10,0)) -> 10 | AE56: 1 | AF56: =AE56*1.1 -> 1.1 | AG56: =AF56*AC56 -> 13.2
A57: WEPP | B57: C | C57: 6 | D57: =IF(C57=1,"Motor y Transmisión",IF(C57=2,"Refrigeración",IF(C57=3,"Climatización",IF(C57=4,"Sistema de Combustión",IF(C57=5,"Frenos",IF(C57=6,"Mantenimiento y Cuidado",IF(C57=7,"Carrocería",""))))))) -> Mantenimiento y Cuidado | F57: 2026 | G57: =AE57*1000 -> 50 | H57: Scheibenwischer Konzentrat | I57: Limpiador de Parabrisas Concentrado | J57: =F57 -> 2026 | K57: =G57 -> 50 | L57: 0.55 | M57: 0.3 | N57: 0 | O57: 0.3 | P57: 0.3 | Q57: =+L57+M57+N57+O57+P57 -> 1.45 | R57: 0.65 | S57: =R57*1.1 -> 0.715 | U57: =R57-Q57 -> -0.8 | V57: =U57*0.6 -> -0.48 | W57: =U57*0.4 -> -0.32 | Z57: 1 | AA57: =INT(AC57/3) -> 42 | AB57: 5 | AC57: 126 | AD57: =IF(AC57=24,15,IF(AC57=12,10,0)) -> 0 | AE57: 0.05 | AF57: =AE57*1.1 -> 0.055 | AG57: =AF57*AC57 -> 6.93
A58: WEPP | B58: C | C58: 6 | D58: =IF(C58=1,"Motor y Transmisión",IF(C58=2,"Refrigeración",IF(C58=3,"Climatización",IF(C58=4,"Sistema de Combustión",IF(C58=5,"Frenos",IF(C58=6,"Mantenimiento y Cuidado",IF(C58=7,"Carrocería",""))))))) -> Mantenimiento y Cuidado | F58: 2040 | G58: =AE58*1000 -> 400 | H58: Haftsynthese | I58: Lubricante Sintético Adhesivo 400 | J58: =F58 -> 2040 | K58: =G58 -> 400 | M58: 0.3 | N58: 0 | O58: 0.3 | P58: 0.3 | Q58: =+L58+M58+N58+O58+P58 -> 0.9 | R58: 6.35 | S58: =R58*1.1 -> 6.985 | U58: =R58-Q58 -> 5.45 | V58: =U58*0.6 -> 3.27 | W58: =U58*0.4 -> 2.18 | AA58: =INT(AC58/3) -> 0 | AB58: 5 | AD58: =IF(AC58=24,15,IF(AC58=12,10,0)) -> 0 | AE58: 0.4 | AF58: =AE58*1.1 -> 0.44 | AG58: =AF58*AC58 -> 0
A59: WEPP | B59: C | C59: 6 | D59: =IF(C59=1,"Motor y Transmisión",IF(C59=2,"Refrigeración",IF(C59=3,"Climatización",IF(C59=4,"Sistema de Combustión",IF(C59=5,"Frenos",IF(C59=6,"Mantenimiento y Cuidado",IF(C59=7,"Carrocería",""))))))) -> Mantenimiento y Cuidado | F59: 2041 | G59: =AE59*1000 -> 400 | H59: Haftschmier | I59: Lubricación Adhesiva | J59: =F59 -> 2041 | K59: =G59 -> 400 | L59: 3.7 | M59: 0.3 | N59: 0 | O59: 0.3 | P59: 0.3 | Q59: =+L59+M59+N59+O59+P59 -> 4.6 | R59: 10.2 | S59: =R59*1.1 -> 11.22 | U59: =R59-Q59 -> 5.6 | V59: =U59*0.6 -> 3.36 | W59: =U59*0.4 -> 2.24 | Z59: 1 | AA59: =INT(AC59/3) -> 8 | AB59: 5 | AC59: 24 | AD59: =IF(AC59=24,15,IF(AC59=12,10,0)) -> 15 | AE59: 0.4 | AF59: =AE59*1.1 -> 0.44 | AG59: =AF59*AC59 -> 10.56
A60: WEPP | B60: C | C60: 6 | D60: =IF(C60=1,"Motor y Transmisión",IF(C60=2,"Refrigeración",IF(C60=3,"Climatización",IF(C60=4,"Sistema de Combustión",IF(C60=5,"Frenos",IF(C60=6,"Mantenimiento y Cuidado",IF(C60=7,"Carrocería",""))))))) -> Mantenimiento y Cuidado | F60: 2042 | G60: =AE60*1000 -> 400 | H60: Fliessfett transparent | I60: Grasa semilíquida Transparente | J60: =F60 -> 2042 | K60: =G60 -> 400 | L60: 3.85 | M60: 0.3 | N60: 0 | O60: 0.3 | P60: 0.3 | Q60: =+L60+M60+N60+O60+P60 -> 4.75 | R60: 7.95 | S60: =R60*1.1 -> 8.745 | U60: =R60-Q60 -> 3.2 | V60: =U60*0.6 -> 1.92 | W60: =U60*0.4 -> 1.28 | Z60: 1 | AA60: =INT(AC60/3) -> 8 | AB60: 5 | AC60: 24 | AD60: =IF(AC60=24,15,IF(AC60=12,10,0)) -> 15 | AE60: 0.4 | AF60: =AE60*1.1 -> 0.44 | AG60: =AF60*AC60 -> 10.56
A61: WEPP | B61: C | C61: 6 | D61: =IF(C61=1,"Motor y Transmisión",IF(C61=2,"Refrigeración",IF(C61=3,"Climatización",IF(C61=4,"Sistema de Combustión",IF(C61=5,"Frenos",IF(C61=6,"Mantenimiento y Cuidado",IF(C61=7,"Carrocería",""))))))) -> Mantenimiento y Cuidado | F61: 2043 | G61: =AE61*1000 -> 400 | H61: Wartungs Haftöl | I61: Aceite Adhesivo de Mantenimiento | J61: =F61 -> 2043 | K61: =G61 -> 400 | L61: 3.15 | M61: 0.3 | N61: 0 | O61: 0.3 | P61: 0.3 | Q61: =+L61+M61+N61+O61+P61 -> 4.05 | R61: 7.8 | S61: =R61*1.1 -> 8.58 | U61: =R61-Q61 -> 3.75 | V61: =U61*0.6 -> 2.25 | W61: =U61*0.4 -> 1.5 | Z61: 1 | AA61: =INT(AC61/3) -> 8 | AB61: 5 | AC61: 24 | AD61: =IF(AC61=24,15,IF(AC61=12,10,0)) -> 15 | AE61: 0.4 | AF61: =AE61*1.1 -> 0.44 | AG61: =AF61*AC61 -> 10.56
A62: WEPP | B62: C | C62: 6 | D62: =IF(C62=1,"Motor y Transmisión",IF(C62=2,"Refrigeración",IF(C62=3,"Climatización",IF(C62=4,"Sistema de Combustión",IF(C62=5,"Frenos",IF(C62=6,"Mantenimiento y Cuidado",IF(C62=7,"Carrocería",""))))))) -> Mantenimiento y Cuidado | F62: 2045 | G62: =AE62*1000 -> 400 | H62: Silikon Gleitfett | I62: Grasa de Silicona | J62: =F62 -> 2045 | K62: =G62 -> 400 | L62: 3.9 | M62: 0.3 | N62: 0 | O62: 0.3 | P62: 0.3 | Q62: =+L62+M62+N62+O62+P62 -> 4.8 | R62: 9.5 | S62: =R62*1.1 -> 10.45 | U62: =R62-Q62 -> 4.7 | V62: =U62*0.6 -> 2.82 | W62: =U62*0.4 -> 1.88 | Z62: 1 | AA62: =INT(AC62/3) -> 8 | AB62: 5 | AC62: 24 | AD62: =IF(AC62=24,15,IF(AC62=12,10,0)) -> 15 | AE62: 0.4 | AF62: =AE62*1.1 -> 0.44 | AG62: =AF62*AC62 -> 10.56
A63: WEPP | B63: C | C63: 6 | D63: =IF(C63=1,"Motor y Transmisión",IF(C63=2,"Refrigeración",IF(C63=3,"Climatización",IF(C63=4,"Sistema de Combustión",IF(C63=5,"Frenos",IF(C63=6,"Mantenimiento y Cuidado",IF(C63=7,"Carrocería",""))))))) -> Mantenimiento y Cuidado | F63: 2246 | G63: =AE63*1000 -> 400 | H63: Super Rostlöser Active | I63: Desbloqueante Activo | J63: =F63 -> 2246 | K63: =G63 -> 400 | L63: 3.75 | M63: 0.3 | N63: 0 | O63: 0.3 | P63: 0.3 | Q63: =+L63+M63+N63+O63+P63 -> 4.65 | R63: 7.9 | S63: =R63*1.1 -> 8.69 | U63: =R63-Q63 -> 3.25 | V63: =U63*0.6 -> 1.95 | W63: =U63*0.4 -> 1.3 | Z63: 1 | AA63: =INT(AC63/3) -> 8 | AB63: 5 | AC63: 24 | AD63: =IF(AC63=24,15,IF(AC63=12,10,0)) -> 15 | AE63: 0.4 | AF63: =AE63*1.1 -> 0.44 | AG63: =AF63*AC63 -> 10.56
A64: WEPP | B64: C | C64: 6 | D64: =IF(C64=1,"Motor y Transmisión",IF(C64=2,"Refrigeración",IF(C64=3,"Climatización",IF(C64=4,"Sistema de Combustión",IF(C64=5,"Frenos",IF(C64=6,"Mantenimiento y Cuidado",IF(C64=7,"Carrocería",""))))))) -> Mantenimiento y Cuidado | F64: 2048 | G64: =AE64*1000 -> 400 | H64: Rostlöser MOS2 | I64: Desbloqueante MOS2 | J64: =F64 -> 2048 | K64: =G64 -> 400 | L64: 2.35 | M64: 0.3 | N64: 0 | O64: 0.3 | P64: 0.3 | Q64: =+L64+M64+N64+O64+P64 -> 3.25 | R64: 4.55 | S64: =R64*1.1 -> 5.005 | U64: =R64-Q64 -> 1.3 | V64: =U64*0.6 -> 0.78 | W64: =U64*0.4 -> 0.52 | Z64: 1 | AA64: =INT(AC64/3) -> 8 | AB64: 5 | AC64: 24 | AD64: =IF(AC64=24,15,IF(AC64=12,10,0)) -> 15 | AE64: 0.4 | AF64: =AE64*1.1 -> 0.44 | AG64: =AF64*AC64 -> 10.56
A65: WEPP | B65: C | C65: 6 | D65: =IF(C65=1,"Motor y Transmisión",IF(C65=2,"Refrigeración",IF(C65=3,"Climatización",IF(C65=4,"Sistema de Combustión",IF(C65=5,"Frenos",IF(C65=6,"Mantenimiento y Cuidado",IF(C65=7,"Carrocería",""))))))) -> Mantenimiento y Cuidado | F65: 2047 | G65: =AE65*1000 -> 400 | H65: Silikonspray | I65: Aerosol de Silicona | J65: =F65 -> 2047 | K65: =G65 -> 400 | L65: 2.5 | M65: 0.3 | N65: 0 | O65: 0.3 | P65: 0.3 | Q65: =+L65+M65+N65+O65+P65 -> 3.4 | R65: 4.85 | S65: =R65*1.1 -> 5.335 | U65: =R65-Q65 -> 1.45 | V65: =U65*0.6 -> 0.87 | W65: =U65*0.4 -> 0.58 | Z65: 1 | AA65: =INT(AC65/3) -> 8 | AB65: 5 | AC65: 24 | AD65: =IF(AC65=24,15,IF(AC65=12,10,0)) -> 15 | AE65: 0.4 | AF65: =AE65*1.1 -> 0.44 | AG65: =AF65*AC65 -> 10.56
A66: WEPP | B66: C | C66: 6 | D66: =IF(C66=1,"Motor y Transmisión",IF(C66=2,"Refrigeración",IF(C66=3,"Climatización",IF(C66=4,"Sistema de Combustión",IF(C66=5,"Frenos",IF(C66=6,"Mantenimiento y Cuidado",IF(C66=7,"Carrocería",""))))))) -> Mantenimiento y Cuidado | F66: 2053 | G66: =AE66*1000 -> 400 | H66: Innenraumspray | I66: Aerosol para Interiores | J66: =F66 -> 2053 | K66: =G66 -> 400 | L66: 3.5 | M66: 0.3 | N66: 0 | O66: 0.3 | P66: 0.3 | Q66: =+L66+M66+N66+O66+P66 -> 4.4 | R66: 8.55 | S66: =R66*1.1 -> 9.405 | U66: =R66-Q66 -> 4.15 | V66: =U66*0.6 -> 2.49 | W66: =U66*0.4 -> 1.66 | Z66: 1 | AA66: =INT(AC66/3) -> 8 | AB66: 5 | AC66: 24 | AD66: =IF(AC66=24,15,IF(AC66=12,10,0)) -> 15 | AE66: 0.4 | AF66: =AE66*1.1 -> 0.44 | AG66: =AF66*AC66 -> 10.56
A67: WEPP | B67: C | C67: 6 | D67: =IF(C67=1,"Motor y Transmisión",IF(C67=2,"Refrigeración",IF(C67=3,"Climatización",IF(C67=4,"Sistema de Combustión",IF(C67=5,"Frenos",IF(C67=6,"Mantenimiento y Cuidado",IF(C67=7,"Carrocería",""))))))) -> Mantenimiento y Cuidado | F67: 2054 | G67: =AE67*1000 -> 400 | H67: Ölspray Mit PTFE | I67: Aerosol de Aceite con PTFE | J67: =F67 -> 2054 | K67: =G67 -> 400 | L67: 4.8 | M67: 0.3 | N67: 0 | O67: 0.3 | P67: 0.3 | Q67: =+L67+M67+N67+O67+P67 -> 5.7 | R67: 11.2 | S67: =R67*1.1 -> 12.32 | U67: =R67-Q67 -> 5.5 | V67: =U67*0.6 -> 3.3 | W67: =U67*0.4 -> 2.2 | Z67: 1 | AA67: =INT(AC67/3) -> 8 | AB67: 5 | AC67: 24 | AD67: =IF(AC67=24,15,IF(AC67=12,10,0)) -> 15 | AE67: 0.4 | AF67: =AE67*1.1 -> 0.44 | AG67: =AF67*AC67 -> 10.56
A68: WEPP | B68: C | C68: 6 | D68: =IF(C68=1,"Motor y Transmisión",IF(C68=2,"Refrigeración",IF(C68=3,"Climatización",IF(C68=4,"Sistema de Combustión",IF(C68=5,"Frenos",IF(C68=6,"Mantenimiento y Cuidado",IF(C68=7,"Carrocería",""))))))) -> Mantenimiento y Cuidado | F68: 2056 | G68: =AE68*1000 -> 400 | H68: Fettspray Mit PTFE | I68: Aerosol de Grasa con PTFE | J68: =F68 -> 2056 | K68: =G68 -> 400 | L68: 4.8 | M68: 0.3 | N68: 0 | O68: 0.3 | P68: 0.3 | Q68: =+L68+M68+N68+O68+P68 -> 5.7 | R68: 11 | S68: =R68*1.1 -> 12.1 | U68: =R68-Q68 -> 5.3 | V68: =U68*0.6 -> 3.18 | W68: =U68*0.4 -> 2.12 | Z68: 1 | AA68: =INT(AC68/3) -> 8 | AB68: 5 | AC68: 24 | AD68: =IF(AC68=24,15,IF(AC68=12,10,0)) -> 15 | AE68: 0.4 | AF68: =AE68*1.1 -> 0.44 | AG68: =AF68*AC68 -> 10.56
A69: WEPP | B69: C | C69: 6 | D69: =IF(C69=1,"Motor y Transmisión",IF(C69=2,"Refrigeración",IF(C69=3,"Climatización",IF(C69=4,"Sistema de Combustión",IF(C69=5,"Frenos",IF(C69=6,"Mantenimiento y Cuidado",IF(C69=7,"Carrocería",""))))))) -> Mantenimiento y Cuidado | F69: 2059 | G69: =AE69*1000 -> 400 | H69: Kupferspray | I69: Aerosol de Cobre | J69: =F69 -> 2059 | K69: =G69 -> 400 | L69: 3.9 | M69: 0.3 | N69: 0 | O69: 0.3 | P69: 0.3 | Q69: =+L69+M69+N69+O69+P69 -> 4.8 | R69: 6.35 | S69: =R69*1.1 -> 6.985 | U69: =R69-Q69 -> 1.55 | V69: =U69*0.6 -> 0.93 | W69: =U69*0.4 -> 0.62 | Z69: 1 | AA69: =INT(AC69/3) -> 8 | AB69: 5 | AC69: 24 | AD69: =IF(AC69=24,15,IF(AC69=12,10,0)) -> 15 | AE69: 0.4 | AF69: =AE69*1.1 -> 0.44 | AG69: =AF69*AC69 -> 10.56
A70: WEPP | B70: C | C70: 6 | D70: =IF(C70=1,"Motor y Transmisión",IF(C70=2,"Refrigeración",IF(C70=3,"Climatización",IF(C70=4,"Sistema de Combustión",IF(C70=5,"Frenos",IF(C70=6,"Mantenimiento y Cuidado",IF(C70=7,"Carrocería",""))))))) -> Mantenimiento y Cuidado | F70: 2060 | G70: 400 | H70: Bremsenreiniger Acetonfrei | I70: Limpiador de Frenos sin Acetona 400 | J70: =F70 -> 2060 | K70: =G70 -> 400 | L70: 1.9 | M70: 0.3 | N70: 0 | O70: 0.3 | P70: 0.3 | Q70: =+L70+M70+N70+O70+P70 -> 2.8 | R70: 3.85 | S70: =R70*1.1 -> 4.235 | U70: =R70-Q70 -> 1.05 | V70: =U70*0.6 -> 0.63 | W70: =U70*0.4 -> 0.42 | Z70: 1 | AA70: =INT(AC70/3) -> 4 | AB70: 5 | AC70: 12 | AD70: =IF(AC70=24,15,IF(AC70=12,10,0)) -> 10 | AE70: 0.6 | AF70: =AE70*1.1 -> 0.66 | AG70: =AF70*AC70 -> 7.92
A71: WEPP | B71: C | C71: 6 | D71: =IF(C71=1,"Motor y Transmisión",IF(C71=2,"Refrigeración",IF(C71=3,"Climatización",IF(C71=4,"Sistema de Combustión",IF(C71=5,"Frenos",IF(C71=6,"Mantenimiento y Cuidado",IF(C71=7,"Carrocería",""))))))) -> Mantenimiento y Cuidado | F71: 2063 | G71: =AE71*1000 -> 30000 | H71: Bremsenreiniger Acetonfrei | I71: Limpiador de Frenos sin Acetona 30000 | J71: =F71 -> 2063 | K71: =G71 -> 30000 | L71: 70.5 | M71: 0.3 | N71: 0 | O71: 0.3 | P71: 0.3 | Q71: =+L71+M71+N71+O71+P71 -> 71.4 | R71: 75 | S71: =R71*1.1 -> 82.5 | U71: =R71-Q71 -> 3.6 | V71: =U71*0.6 -> 2.16 | W71: =U71*0.4 -> 1.44 | Z71: 1 | AA71: =INT(AC71/3) -> 0 | AB71: 5 | AC71: 1 | AD71: =IF(AC71=24,15,IF(AC71=12,10,0)) -> 0 | AE71: 30 | AF71: =AE71*1.1 -> 33 | AG71: =AF71*AC71 -> 33
A72: WEPP | B72: C | C72: 6 | D72: =IF(C72=1,"Motor y Transmisión",IF(C72=2,"Refrigeración",IF(C72=3,"Climatización",IF(C72=4,"Sistema de Combustión",IF(C72=5,"Frenos",IF(C72=6,"Mantenimiento y Cuidado",IF(C72=7,"Carrocería",""))))))) -> Mantenimiento y Cuidado | F72: 2117 | G72: =AE72*1000 -> 500 | H72: Sicherheitsreiniger | I72: Limpiador Universal | J72: =F72 -> 2117 | K72: =G72 -> 500 | M72: 0.3 | N72: 0 | O72: 0.3 | P72: 0.3 | Q72: =+L72+M72+N72+O72+P72 -> 0.9 | R72: 3.5 | S72: =R72*1.1 -> 3.85 | U72: =R72-Q72 -> 2.6 | V72: =U72*0.6 -> 1.56 | W72: =U72*0.4 -> 1.04 | AA72: =INT(AC72/3) -> 0 | AB72: 5 | AD72: =IF(AC72=24,15,IF(AC72=12,10,0)) -> 0 | AE72: 0.5 | AF72: =AE72*1.1 -> 0.55 | AG72: =AF72*AC72 -> 0
A73: WEPP | B73: C | C73: 6 | D73: =IF(C73=1,"Motor y Transmisión",IF(C73=2,"Refrigeración",IF(C73=3,"Climatización",IF(C73=4,"Sistema de Combustión",IF(C73=5,"Frenos",IF(C73=6,"Mantenimiento y Cuidado",IF(C73=7,"Carrocería",""))))))) -> Mantenimiento y Cuidado | F73: 2061 | G73: =AE73*1000 -> 500 | H73: Multi Komplex Reiniger (Scheiben) | I73: Limpiacristales | J73: =F73 -> 2061 | K73: =G73 -> 500 | L73: 3.2 | M73: 0.3 | N73: 0 | O73: 0.3 | P73: 0.3 | Q73: =+L73+M73+N73+O73+P73 -> 4.1 | R73: 6.15 | S73: =R73*1.1 -> 6.765 | U73: =R73-Q73 -> 2.05 | V73: =U73*0.6 -> 1.23 | W73: =U73*0.4 -> 0.82 | Z73: 1 | AA73: =INT(AC73/3) -> 8 | AB73: 5 | AC73: 24 | AD73: =IF(AC73=24,15,IF(AC73=12,10,0)) -> 15 | AE73: 0.5 | AF73: =AE73*1.1 -> 0.55 | AG73: =AF73*AC73 -> 13.2
A74: WEPP | B74: C | C74: 6 | D74: =IF(C74=1,"Motor y Transmisión",IF(C74=2,"Refrigeración",IF(C74=3,"Climatización",IF(C74=4,"Sistema de Combustión",IF(C74=5,"Frenos",IF(C74=6,"Mantenimiento y Cuidado",IF(C74=7,"Carrocería",""))))))) -> Mantenimiento y Cuidado | F74: 2070 | G74: =AE74*1000 -> 400 | H74: Elektronik Reiniger Spray | I74: Limpiacontactos | J74: =F74 -> 2070 | K74: =G74 -> 400 | L74: 3.45 | M74: 0.3 | N74: 0 | O74: 0.3 | P74: 0.3 | Q74: =+L74+M74+N74+O74+P74 -> 4.35 | R74: 8.1 | S74: =R74*1.1 -> 8.91 | U74: =R74-Q74 -> 3.75 | V74: =U74*0.6 -> 2.25 | W74: =U74*0.4 -> 1.5 | Z74: 1 | AA74: =INT(AC74/3) -> 8 | AB74: 5 | AC74: 24 | AD74: =IF(AC74=24,15,IF(AC74=12,10,0)) -> 15 | AE74: 0.4 | AF74: =AE74*1.1 -> 0.44 | AG74: =AF74*AC74 -> 10.56
A75: WEPP | B75: C | C75: 6 | D75: =IF(C75=1,"Motor y Transmisión",IF(C75=2,"Refrigeración",IF(C75=3,"Climatización",IF(C75=4,"Sistema de Combustión",IF(C75=5,"Frenos",IF(C75=6,"Mantenimiento y Cuidado",IF(C75=7,"Carrocería",""))))))) -> Mantenimiento y Cuidado | F75: 2071 | G75: =AE75*1000 -> 400 | H75: Elektronik Spray | I75: Limpiador de Electrónica | J75: =F75 -> 2071 | K75: =G75 -> 400 | L75: 3.2 | M75: 0.3 | N75: 0 | O75: 0.3 | P75: 0.3 | Q75: =+L75+M75+N75+O75+P75 -> 4.1 | R75: 8.6 | S75: =R75*1.1 -> 9.46 | U75: =R75-Q75 -> 4.5 | V75: =U75*0.6 -> 2.7 | W75: =U75*0.4 -> 1.8 | Z75: 1 | AA75: =INT(AC75/3) -> 8 | AB75: 5 | AC75: 24 | AD75: =IF(AC75=24,15,IF(AC75=12,10,0)) -> 15 | AE75: 0.4 | AF75: =AE75*1.1 -> 0.44 | AG75: =AF75*AC75 -> 10.56
A76: WEPP | B76: C | C76: 6 | D76: =IF(C76=1,"Motor y Transmisión",IF(C76=2,"Refrigeración",IF(C76=3,"Climatización",IF(C76=4,"Sistema de Combustión",IF(C76=5,"Frenos",IF(C76=6,"Mantenimiento y Cuidado",IF(C76=7,"Carrocería",""))))))) -> Mantenimiento y Cuidado | F76: 2075 | G76: =AE76*1000 -> 400 | H76: Motorstarter Spray | I76: Autoarranque | J76: =F76 -> 2075 | K76: =G76 -> 400 | L76: 3.1 | M76: 0.3 | N76: 0 | O76: 0.3 | P76: 0.3 | Q76: =+L76+M76+N76+O76+P76 -> 4 | R76: 6.35 | S76: =R76*1.1 -> 6.985 | U76: =R76-Q76 -> 2.35 | V76: =U76*0.6 -> 1.41 | W76: =U76*0.4 -> 0.94 | Z76: 1 | AA76: =INT(AC76/3) -> 8 | AB76: 5 | AC76: 24 | AD76: =IF(AC76=24,15,IF(AC76=12,10,0)) -> 15 | AE76: 0.4 | AF76: =AE76*1.1 -> 0.44 | AG76: =AF76*AC76 -> 10.56
A77: WEPP | B77: C | C77: 6 | D77: =IF(C77=1,"Motor y Transmisión",IF(C77=2,"Refrigeración",IF(C77=3,"Climatización",IF(C77=4,"Sistema de Combustión",IF(C77=5,"Frenos",IF(C77=6,"Mantenimiento y Cuidado",IF(C77=7,"Carrocería",""))))))) -> Mantenimiento y Cuidado | F77: 2076 | G77: =AE77*1000 -> 400 | H77: Batterieschutz Spray | I77: Protecttor Bornes | J77: =F77 -> 2076 | K77: =G77 -> 400 | L77: 3.2 | M77: 0.3 | N77: 0 | O77: 0.3 | P77: 0.3 | Q77: =+L77+M77+N77+O77+P77 -> 4.1 | R77: 8.55 | S77: =R77*1.1 -> 9.405 | U77: =R77-Q77 -> 4.45 | V77: =U77*0.6 -> 2.67 | W77: =U77*0.4 -> 1.78 | Z77: 1 | AA77: =INT(AC77/3) -> 8 | AB77: 5 | AC77: 24 | AD77: =IF(AC77=24,15,IF(AC77=12,10,0)) -> 15 | AE77: 0.4 | AF77: =AE77*1.1 -> 0.44 | AG77: =AF77*AC77 -> 10.56
A78: WEPP | B78: C | C78: 6 | D78: =IF(C78=1,"Motor y Transmisión",IF(C78=2,"Refrigeración",IF(C78=3,"Climatización",IF(C78=4,"Sistema de Combustión",IF(C78=5,"Frenos",IF(C78=6,"Mantenimiento y Cuidado",IF(C78=7,"Carrocería",""))))))) -> Mantenimiento y Cuidado | F78: 2094 | G78: =AE78*1000 -> 400 | H78: Reifenglanz | I78: Brillo de Neumáticos | J78: =F78 -> 2094 | K78: =G78 -> 400 | L78: 3.5 | M78: 0.3 | N78: 0 | O78: 0.3 | P78: 0.3 | Q78: =+L78+M78+N78+O78+P78 -> 4.4 | R78: 6.6 | S78: =R78*1.1 -> 7.26 | U78: =R78-Q78 -> 2.2 | V78: =U78*0.6 -> 1.32 | W78: =U78*0.4 -> 0.88 | Z78: 1 | AA78: =INT(AC78/3) -> 8 | AB78: 5 | AC78: 24 | AD78: =IF(AC78=24,15,IF(AC78=12,10,0)) -> 15 | AE78: 0.4 | AF78: =AE78*1.1 -> 0.44 | AG78: =AF78*AC78 -> 10.56
A79: WEPP | B79: C | C79: 6 | D79: =IF(C79=1,"Motor y Transmisión",IF(C79=2,"Refrigeración",IF(C79=3,"Climatización",IF(C79=4,"Sistema de Combustión",IF(C79=5,"Frenos",IF(C79=6,"Mantenimiento y Cuidado",IF(C79=7,"Carrocería",""))))))) -> Mantenimiento y Cuidado | F79: 2194 | G79: =AE79*1000 -> 500 | H79: Reifenmontage Spray | I79: Montaje de Neumáticos | J79: =F79 -> 2194 | K79: =G79 -> 500 | M79: 0.3 | N79: 0 | O79: 0.3 | P79: 0.3 | Q79: =+L79+M79+N79+O79+P79 -> 0.9 | R79: 9.65 | S79: =R79*1.1 -> 10.615 | U79: =R79-Q79 -> 8.75 | V79: =U79*0.6 -> 5.25 | W79: =U79*0.4 -> 3.5 | AA79: =INT(AC79/3) -> 0 | AB79: 5 | AD79: =IF(AC79=24,15,IF(AC79=12,10,0)) -> 0 | AE79: 0.5 | AF79: =AE79*1.1 -> 0.55 | AG79: =AF79*AC79 -> 0
A80: WEPP | B80: C | C80: 6 | D80: =IF(C80=1,"Motor y Transmisión",IF(C80=2,"Refrigeración",IF(C80=3,"Climatización",IF(C80=4,"Sistema de Combustión",IF(C80=5,"Frenos",IF(C80=6,"Mantenimiento y Cuidado",IF(C80=7,"Carrocería",""))))))) -> Mantenimiento y Cuidado | F80: 2095 | G80: =AE80*1000 -> 200 | H80: Schnell Dichtung (schwarz) | I80: Sustituto de Juntas (negro) | J80: =F80 -> 2095 | K80: =G80 -> 200 | L80: 7.5 | M80: 0.3 | N80: 0 | O80: 0.3 | P80: 0.3 | Q80: =+L80+M80+N80+O80+P80 -> 8.4 | R80: 15.7 | S80: =R80*1.1 -> 17.27 | U80: =R80-Q80 -> 7.3 | V80: =U80*0.6 -> 4.38 | W80: =U80*0.4 -> 2.92 | Z80: 1 | AA80: =INT(AC80/3) -> 8 | AB80: 5 | AC80: 24 | AD80: =IF(AC80=24,15,IF(AC80=12,10,0)) -> 15 | AE80: 0.2 | AF80: =AE80*1.1 -> 0.22 | AG80: =AF80*AC80 -> 5.28
A81: WEPP | B81: C | C81: 6 | D81: =IF(C81=1,"Motor y Transmisión",IF(C81=2,"Refrigeración",IF(C81=3,"Climatización",IF(C81=4,"Sistema de Combustión",IF(C81=5,"Frenos",IF(C81=6,"Mantenimiento y Cuidado",IF(C81=7,"Carrocería",""))))))) -> Mantenimiento y Cuidado | F81: 2195 | G81: =AE81*1000 -> 200 | H81: Schnell Dichtung (grau) | I81: Sustituto de Juntas (gris) | J81: =F81 -> 2195 | K81: =G81 -> 200 | M81: 0.3 | N81: 0 | O81: 0.3 | P81: 0.3 | Q81: =+L81+M81+N81+O81+P81 -> 0.9 | S81: =R81*1.1 -> 0 | U81: =R81-Q81 -> -0.9 | V81: =U81*0.6 -> -0.54 | W81: =U81*0.4 -> -0.36 | AA81: =INT(AC81/3) -> 0 | AB81: 5 | AD81: =IF(AC81=24,15,IF(AC81=12,10,0)) -> 0 | AE81: 0.2 | AF81: =AE81*1.1 -> 0.22 | AG81: =AF81*AC81 -> 0
A82: WEPP | B82: C | C82: 6 | D82: =IF(C82=1,"Motor y Transmisión",IF(C82=2,"Refrigeración",IF(C82=3,"Climatización",IF(C82=4,"Sistema de Combustión",IF(C82=5,"Frenos",IF(C82=6,"Mantenimiento y Cuidado",IF(C82=7,"Carrocería",""))))))) -> Mantenimiento y Cuidado | F82: 2096 | G82: =AE82*1000 -> 400 | H82: Lecksuch Spray (Luft) | I82: Spray Detector de Fugas (aire) | J82: =F82 -> 2096 | K82: =G82 -> 400 | L82: 3.5 | M82: 0.3 | N82: 0 | O82: 0.3 | P82: 0.3 | Q82: =+L82+M82+N82+O82+P82 -> 4.4 | R82: 4.8 | S82: =R82*1.1 -> 5.28 | U82: =R82-Q82 -> 0.4 | V82: =U82*0.6 -> 0.24 | W82: =U82*0.4 -> 0.16 | Z82: 1 | AA82: =INT(AC82/3) -> 8 | AB82: 5 | AC82: 24 | AD82: =IF(AC82=24,15,IF(AC82=12,10,0)) -> 15 | AE82: 0.4 | AF82: =AE82*1.1 -> 0.44 | AG82: =AF82*AC82 -> 10.56
A83: WEPP | B83: C | C83: 7 | D83: =IF(C83=1,"Motor y Transmisión",IF(C83=2,"Refrigeración",IF(C83=3,"Climatización",IF(C83=4,"Sistema de Combustión",IF(C83=5,"Frenos",IF(C83=6,"Mantenimiento y Cuidado",IF(C83=7,"Carrocería",""))))))) -> Carrocería | F83: 2083 | G83: =AE83*1000 -> 1000 | H83: Glas und Lack Reiniger | I83: Limpiador de Vidrios y Pintura | J83: =F83 -> 2083 | K83: =G83 -> 1000 | L83: 5.4 | M83: 0.3 | N83: 0 | O83: 0.3 | P83: 0.3 | Q83: =+L83+M83+N83+O83+P83 -> 6.3 | R83: 7.85 | S83: =R83*1.1 -> 8.635 | T83: 12.7 | U83: =R83-Q83 -> 1.55 | V83: =U83*0.6 -> 0.93 | W83: =U83*0.4 -> 0.62 | Z83: 1 | AA83: =INT(AC83/3) -> 4 | AB83: 5 | AC83: 12 | AD83: =IF(AC83=24,15,IF(AC83=12,10,0)) -> 10 | AE83: 1 | AF83: =AE83*1.1 -> 1.1 | AG83: =AF83*AC83 -> 13.2
A84: WEPP | B84: C | C84: 7 | D84: =IF(C84=1,"Motor y Transmisión",IF(C84=2,"Refrigeración",IF(C84=3,"Climatización",IF(C84=4,"Sistema de Combustión",IF(C84=5,"Frenos",IF(C84=6,"Mantenimiento y Cuidado",IF(C84=7,"Carrocería",""))))))) -> Carrocería | F84: 2090 | G84: =AE84*1000 -> 400 | H84: Metallschutz Spray | I84: Pintura de Zinc | J84: =F84 -> 2090 | K84: =G84 -> 400 | L84: 3.5 | M84: 0.3 | N84: 0 | O84: 0.3 | P84: 0.3 | Q84: =+L84+M84+N84+O84+P84 -> 4.4 | R84: 7.8 | S84: =R84*1.1 -> 8.58 | U84: =R84-Q84 -> 3.4 | V84: =U84*0.6 -> 2.04 | W84: =U84*0.4 -> 1.36 | Z84: 1 | AA84: =INT(AC84/3) -> 8 | AB84: 5 | AC84: 24 | AD84: =IF(AC84=24,15,IF(AC84=12,10,0)) -> 15 | AE84: 0.4 | AF84: =AE84*1.1 -> 0.44 | AG84: =AF84*AC84 -> 10.56
A85: WEPP | B85: C | C85: 7 | D85: =IF(C85=1,"Motor y Transmisión",IF(C85=2,"Refrigeración",IF(C85=3,"Climatización",IF(C85=4,"Sistema de Combustión",IF(C85=5,"Frenos",IF(C85=6,"Mantenimiento y Cuidado",IF(C85=7,"Carrocería",""))))))) -> Carrocería | F85: 2091 | G85: =AE85*1000 -> 500 | H85: Unterbodenschutz (schwarz matt) | I85: Protector de Bajos (negro mate) | J85: =F85 -> 2091 | K85: =G85 -> 500 | L85: 3.9 | M85: 0.3 | N85: 0 | O85: 0.3 | P85: 0.3 | Q85: =+L85+M85+N85+O85+P85 -> 4.8 | R85: 5.9 | S85: =R85*1.1 -> 6.49 | U85: =R85-Q85 -> 1.1 | V85: =U85*0.6 -> 0.66 | W85: =U85*0.4 -> 0.44 | Z85: 1 | AA85: =INT(AC85/3) -> 4 | AB85: 5 | AC85: 12 | AD85: =IF(AC85=24,15,IF(AC85=12,10,0)) -> 10 | AE85: 0.5 | AF85: =AE85*1.1 -> 0.55 | AG85: =AF85*AC85 -> 6.6
A86: WEPP | B86: C | C86: 7 | D86: =IF(C86=1,"Motor y Transmisión",IF(C86=2,"Refrigeración",IF(C86=3,"Climatización",IF(C86=4,"Sistema de Combustión",IF(C86=5,"Frenos",IF(C86=6,"Mantenimiento y Cuidado",IF(C86=7,"Carrocería",""))))))) -> Carrocería | F86: 2092 | G86: =AE86*1000 -> 500 | H86: Hohlraumversiegelung | I86: Sellador de Cavidades (transparente) | J86: =F86 -> 2092 | K86: =G86 -> 500 | M86: 0.3 | N86: 0 | O86: 0.3 | P86: 0.3 | Q86: =+L86+M86+N86+O86+P86 -> 0.9 | R86: 6.2 | S86: =R86*1.1 -> 6.82 | U86: =R86-Q86 -> 5.3 | V86: =U86*0.6 -> 3.18 | W86: =U86*0.4 -> 2.12 | AA86: =INT(AC86/3) -> 0 | AB86: 5 | AD86: =IF(AC86=24,15,IF(AC86=12,10,0)) -> 0 | AE86: 0.5 | AF86: =AE86*1.1 -> 0.55 | AG86: =AF86*AC86 -> 0
A87: WEPP | B87: C | C87: 7 | D87: =IF(C87=1,"Motor y Transmisión",IF(C87=2,"Refrigeración",IF(C87=3,"Climatización",IF(C87=4,"Sistema de Combustión",IF(C87=5,"Frenos",IF(C87=6,"Mantenimiento y Cuidado",IF(C87=7,"Carrocería",""))))))) -> Carrocería | F87: 2199 | G87: =AE87*1000 -> 50 | H87: 2 Komponenten Polyurethan Kleber | I87: Adhesivo de Poluretano 2 componentes 90 | J87: =F87 -> 2199 | K87: =G87 -> 50 | L87: 7.75 | M87: 0.3 | N87: 0 | O87: 0.3 | P87: 0.3 | Q87: =+L87+M87+N87+O87+P87 -> 8.65 | R87: 15.6 | S87: =R87*1.1 -> 17.16 | U87: =R87-Q87 -> 6.95 | V87: =U87*0.6 -> 4.17 | W87: =U87*0.4 -> 2.78 | Z87: 1 | AA87: =INT(AC87/3) -> 4 | AB87: 5 | AC87: 12 | AD87: =IF(AC87=24,15,IF(AC87=12,10,0)) -> 10 | AE87: 0.05 | AF87: =AE87*1.1 -> 0.055 | AG87: =AF87*AC87 -> 0.66
A88: WEPP | B88: C | C88: 7 | D88: =IF(C88=1,"Motor y Transmisión",IF(C88=2,"Refrigeración",IF(C88=3,"Climatización",IF(C88=4,"Sistema de Combustión",IF(C88=5,"Frenos",IF(C88=6,"Mantenimiento y Cuidado",IF(C88=7,"Carrocería",""))))))) -> Carrocería | F88: 2399 | G88: =AE88*1000 -> 50 | H88: 2 Komponenten Polyurethan Kleber | I88: Adhesivo de Poluretano 2 componentes 210 | J88: =F88 -> 2399 | K88: =G88 -> 50 | L88: 7.75 | M88: 0.3 | N88: 0 | O88: 0.3 | P88: 0.3 | Q88: =+L88+M88+N88+O88+P88 -> 8.65 | R88: 15.6 | S88: =R88*1.1 -> 17.16 | U88: =R88-Q88 -> 6.95 | V88: =U88*0.6 -> 4.17 | W88: =U88*0.4 -> 2.78 | Z88: 1 | AA88: =INT(AC88/3) -> 4 | AB88: 5 | AC88: 12 | AD88: =IF(AC88=24,15,IF(AC88=12,10,0)) -> 10 | AE88: 0.05 | AF88: =AE88*1.1 -> 0.055 | AG88: =AF88*AC88 -> 0.66
A89: WEPP | B89: LE | D89: =IF(C89=1,"Motor y Transmisión",IF(C89=2,"Refrigeración",IF(C89=3,"Climatización",IF(C89=4,"Sistema de Combustión",IF(C89=5,"Frenos",IF(C89=6,"Mantenimiento y Cuidado",IF(C89=7,"Carrocería",""))))))) | E89: 1 | F89: 2010 | G89: =AE89*1000 -> 400 | H89: Motor System Reiniger | I89: Limpiador de Motor 400 | J89: =F89 -> 2010 | K89: =G89 -> 400 | L89: 2.95 | M89: 0.3 | N89: 0 | O89: 0.3 | P89: 0.3 | Q89: =+L89+M89+N89+O89+P89 -> 3.85 | R89: 9.35 | S89: =R89*1.1 -> 10.285 | T89: 16.85 | U89: =R89-Q89 -> 5.5 | V89: =U89*0.6 -> 3.3 | W89: =U89*0.4 -> 2.2 | Z89: 1 | AA89: =INT(AC89/3) -> 8 | AB89: 5 | AC89: 24 | AD89: =IF(AC89=24,15,IF(AC89=12,10,0)) -> 15 | AE89: 0.4 | AF89: =AE89*1.1 -> 0.44 | AG89: =AF89*AC89 -> 10.56 | AI89: 1 | AK89: 2
A90: WEPP | B90: LE | D90: =IF(C90=1,"Motor y Transmisión",IF(C90=2,"Refrigeración",IF(C90=3,"Climatización",IF(C90=4,"Sistema de Combustión",IF(C90=5,"Frenos",IF(C90=6,"Mantenimiento y Cuidado",IF(C90=7,"Carrocería",""))))))) | E90: 1 | F90: 2010-300 | G90: =AE90*1000 -> 300 | H90: Motor System Reiniger | I90: Limpiador de Motor 300 | J90: =F90 -> 2010-300 | K90: =G90 -> 300 | L90: 2.45 | M90: 0.3 | N90: 0 | O90: 0.3 | P90: 0.3 | Q90: =+L90+M90+N90+O90+P90 -> 3.35 | R90: 7.4 | S90: =R90*1.1 -> 8.14 | T90: 12.65 | U90: =R90-Q90 -> 4.05 | V90: =U90*0.6 -> 2.43 | W90: =U90*0.4 -> 1.62 | Z90: 1 | AA90: =INT(AC90/3) -> 8 | AB90: 5 | AC90: 24 | AD90: =IF(AC90=24,15,IF(AC90=12,10,0)) -> 15 | AE90: 0.3 | AF90: =AE90*1.1 -> 0.33 | AG90: =AF90*AC90 -> 7.92 | AI90: 1 | AK90: 2
A91: WEPP | B91: LE | D91: =IF(C91=1,"Motor y Transmisión",IF(C91=2,"Refrigeración",IF(C91=3,"Climatización",IF(C91=4,"Sistema de Combustión",IF(C91=5,"Frenos",IF(C91=6,"Mantenimiento y Cuidado",IF(C91=7,"Carrocería",""))))))) | E91: 1 | F91: 2017 | G91: =AE91*1000 -> 400 | H91: Leak detector spray liquids | I91: Detector de Pérdida de Líquidos | J91: =F91 -> 2017 | K91: =G91 -> 400 | L91: 3.65 | M91: 0.3 | N91: 0 | O91: 0.3 | P91: 0.3 | Q91: =+L91+M91+N91+O91+P91 -> 4.55 | S91: =R91*1.1 -> 0 | U91: =R91-Q91 -> -4.55 | V91: =U91*0.6 -> -2.73 | W91: =U91*0.4 -> -1.82 | Z91: 1 | AA91: =INT(AC91/3) -> 8 | AB91: 5 | AC91: 24 | AD91: =IF(AC91=24,15,IF(AC91=12,10,0)) -> 15 | AE91: 0.4 | AF91: =AE91*1.1 -> 0.44 | AG91: =AF91*AC91 -> 10.56 | AK91: 1
A92: WEPP | B92: LE | D92: =IF(C92=1,"Motor y Transmisión",IF(C92=2,"Refrigeración",IF(C92=3,"Climatización",IF(C92=4,"Sistema de Combustión",IF(C92=5,"Frenos",IF(C92=6,"Mantenimiento y Cuidado",IF(C92=7,"Carrocería",""))))))) | E92: 0 | F92: 2028 | G92: =AE92*1000 -> 1000 | H92: Intercooler Cleaner | I92: Limpiador de Intercooler | J92: =F92 -> 2028 | K92: =G92 -> 1000 | L92: 5.65 | M92: 0.3 | N92: 0 | O92: 0.3 | P92: 0.3 | Q92: =+L92+M92+N92+O92+P92 -> 6.55 | R92: 9.2 | S92: =R92*1.1 -> 10.12 | T92: 12.85 | U92: =R92-Q92 -> 2.65 | V92: =U92*0.6 -> 1.59 | W92: =U92*0.4 -> 1.06 | Z92: 1 | AA92: =INT(AC92/3) -> 4 | AB92: 5 | AC92: 12 | AD92: =IF(AC92=24,15,IF(AC92=12,10,0)) -> 10 | AE92: 1 | AF92: =AE92*1.1 -> 1.1 | AG92: =AF92*AC92 -> 13.2 | AK92: 0
A93: WEPP | B93: LE | D93: =IF(C93=1,"Motor y Transmisión",IF(C93=2,"Refrigeración",IF(C93=3,"Climatización",IF(C93=4,"Sistema de Combustión",IF(C93=5,"Frenos",IF(C93=6,"Mantenimiento y Cuidado",IF(C93=7,"Carrocería",""))))))) | E93: 1 | F93: 1996-45 | G93: =AE93*1000 -> 100 | H93: 40 cm Rohr für Desinfektionspistole | I93: Tubo de 40 cm para Pistola de Desinfección | J93: =F93 -> 1996-45 | K93: =G93 -> 100 | L93: 20 | M93: 0.3 | N93: 0 | O93: 0.3 | P93: 0.3 | Q93: =+L93+M93+N93+O93+P93 -> 20.9 | S93: =R93*1.1 -> 0 | U93: =R93-Q93 -> -20.9 | V93: =U93*0.6 -> -12.54 | W93: =U93*0.4 -> -8.36 | Z93: 1 | AA93: =INT(AC93/3) -> 0 | AB93: 5 | AC93: 1 | AD93: =IF(AC93=24,15,IF(AC93=12,10,0)) -> 0 | AE93: 0.1 | AF93: =AE93*1.1 -> 0.11 | AG93: =AF93*AC93 -> 0.11 | AK93: 1
A94: WEPP | B94: LE | D94: =IF(C94=1,"Motor y Transmisión",IF(C94=2,"Refrigeración",IF(C94=3,"Climatización",IF(C94=4,"Sistema de Combustión",IF(C94=5,"Frenos",IF(C94=6,"Mantenimiento y Cuidado",IF(C94=7,"Carrocería",""))))))) | E94: 1 | F94: 1996-60 | G94: =AE94*1000 -> 100 | H94: 60 cm Rohr für Desinfektionspistole | I94: Tubo de 60 cm para Pistola de Desinfección | J94: =F94 -> 1996-60 | K94: =G94 -> 100 | L94: 25 | M94: 0.3 | N94: 0 | O94: 0.3 | P94: 0.3 | Q94: =+L94+M94+N94+O94+P94 -> 25.9 | S94: =R94*1.1 -> 0 | U94: =R94-Q94 -> -25.9 | V94: =U94*0.6 -> -15.54 | W94: =U94*0.4 -> -10.36 | Z94: 1 | AA94: =INT(AC94/3) -> 0 | AB94: 5 | AC94: 1 | AD94: =IF(AC94=24,15,IF(AC94=12,10,0)) -> 0 | AE94: 0.1 | AF94: =AE94*1.1 -> 0.11 | AG94: =AF94*AC94 -> 0.11 | AK94: 1
A95: WEPP | B95: LE | D95: =IF(C95=1,"Motor y Transmisión",IF(C95=2,"Refrigeración",IF(C95=3,"Climatización",IF(C95=4,"Sistema de Combustión",IF(C95=5,"Frenos",IF(C95=6,"Mantenimiento y Cuidado",IF(C95=7,"Carrocería",""))))))) | E95: 1 | F95: 2006 | G95: =AE95*1000 -> 1000 | H95: Desinfektions Pistole | I95: Pistola de Desinfección | J95: =F95 -> 2006 | K95: - | L95: 87.45 | M95: 0.3 | N95: 0 | O95: 0.3 | P95: 0.3 | Q95: =+L95+M95+N95+O95+P95 -> 88.35 | R95: 135 | S95: =R95*1.1 -> 148.5 | U95: =R95-Q95 -> 46.65 | V95: =U95*0.6 -> 27.99 | W95: =U95*0.4 -> 18.66 | Z95: 1 | AA95: =INT(AC95/3) -> 0 | AB95: 5 | AC95: 1 | AD95: =IF(AC95=24,15,IF(AC95=12,10,0)) -> 0 | AE95: 1 | AF95: =AE95*1.1 -> 1.1 | AG95: =AF95*AC95 -> 1.1 | AK95: 1
A96: WEPP | B96: LE | D96: =IF(C96=1,"Motor y Transmisión",IF(C96=2,"Refrigeración",IF(C96=3,"Climatización",IF(C96=4,"Sistema de Combustión",IF(C96=5,"Frenos",IF(C96=6,"Mantenimiento y Cuidado",IF(C96=7,"Carrocería",""))))))) | F96: 7030001 | G96: =AE96*1000 -> 1000 | H96: PAG 100 | I96: PAG 100 | J96: =F96 -> 7030001 | K96: =G96 -> 1000 | L96: 13.5 | M96: 0.3 | N96: 0 | O96: 0.3 | P96: 0.3 | Q96: =+L96+M96+N96+O96+P96 -> 14.4 | R96: 19.75 | S96: =R96*1.1 -> 21.725 | T96: 32.9 | U96: =R96-Q96 -> 5.35 | V96: =U96*0.6 -> 3.21 | W96: =U96*0.4 -> 2.14 | Z96: 1 | AA96: =INT(AC96/3) -> 4 | AB96: 5 | AC96: 12 | AD96: =IF(AC96=24,15,IF(AC96=12,10,0)) -> 10 | AE96: 1 | AF96: =AE96*1.1 -> 1.1 | AG96: =AF96*AC96 -> 13.2
A97: WEPP | B97: LE | D97: =IF(C97=1,"Motor y Transmisión",IF(C97=2,"Refrigeración",IF(C97=3,"Climatización",IF(C97=4,"Sistema de Combustión",IF(C97=5,"Frenos",IF(C97=6,"Mantenimiento y Cuidado",IF(C97=7,"Carrocería",""))))))) | F97: 7031001 | G97: =AE97*1000 -> 1000 | H97: AC Kompressor ÖL | I97: Aceite para Compresor A/C | J97: =F97 -> 7031001 | K97: =G97 -> 1000 | L97: 14.5 | M97: 0.3 | N97: 0 | O97: 0.3 | P97: 0.3 | Q97: =+L97+M97+N97+O97+P97 -> 15.4 | R97: 20 | S97: =R97*1.1 -> 22 | T97: 32.6 | U97: =R97-Q97 -> 4.6 | V97: =U97*0.6 -> 2.76 | W97: =U97*0.4 -> 1.84 | Z97: 1 | AA97: =INT(AC97/3) -> 4 | AB97: 5 | AC97: 12 | AD97: =IF(AC97=24,15,IF(AC97=12,10,0)) -> 10 | AE97: 1 | AF97: =AE97*1.1 -> 1.1 | AG97: =AF97*AC97 -> 13.2
A98: WEPP | B98: LE | D98: =IF(C98=1,"Motor y Transmisión",IF(C98=2,"Refrigeración",IF(C98=3,"Climatización",IF(C98=4,"Sistema de Combustión",IF(C98=5,"Frenos",IF(C98=6,"Mantenimiento y Cuidado",IF(C98=7,"Carrocería",""))))))) | F98: 7032001 | G98: =AE98*1000 -> 1000 | H98: Kompressor ÖL R1234YF | I98: Aceite para Compresor R123YF | J98: =F98 -> 7032001 | K98: =G98 -> 1000 | L98: 12.5 | M98: 0.3 | N98: 0 | O98: 0.3 | P98: 0.3 | Q98: =+L98+M98+N98+O98+P98 -> 13.4 | S98: =R98*1.1 -> 0 | U98: =R98-Q98 -> -13.4 | V98: =U98*0.6 -> -8.04 | W98: =U98*0.4 -> -5.36 | Z98: 1 | AA98: =INT(AC98/3) -> 4 | AB98: 5 | AC98: 12 | AD98: =IF(AC98=24,15,IF(AC98=12,10,0)) -> 10 | AE98: 1 | AF98: =AE98*1.1 -> 1.1 | AG98: =AF98*AC98 -> 13.2
A99: WEPP | B99: LE | D99: =IF(C99=1,"Motor y Transmisión",IF(C99=2,"Refrigeración",IF(C99=3,"Climatización",IF(C99=4,"Sistema de Combustión",IF(C99=5,"Frenos",IF(C99=6,"Mantenimiento y Cuidado",IF(C99=7,"Carrocería",""))))))) | F99: 7034001 | G99: =AE99*1000 -> 1000 | H99: Kompressor Universal ÖL | I99: Aceite Universal para Compresor | J99: =F99 -> 7034001 | K99: =G99 -> 1000 | L99: 13.25 | M99: 0.3 | N99: 0 | O99: 0.3 | P99: 0.3 | Q99: =+L99+M99+N99+O99+P99 -> 14.15 | S99: =R99*1.1 -> 0 | U99: =R99-Q99 -> -14.15 | V99: =U99*0.6 -> -8.49 | W99: =U99*0.4 -> -5.66 | Z99: 1 | AA99: =INT(AC99/3) -> 4 | AB99: 5 | AC99: 12 | AD99: =IF(AC99=24,15,IF(AC99=12,10,0)) -> 10 | AE99: 1 | AF99: =AE99*1.1 -> 1.1 | AG99: =AF99*AC99 -> 13.2
A100: WEPP | B100: LE | D100: =IF(C100=1,"Motor y Transmisión",IF(C100=2,"Refrigeración",IF(C100=3,"Climatización",IF(C100=4,"Sistema de Combustión",IF(C100=5,"Frenos",IF(C100=6,"Mantenimiento y Cuidado",IF(C100=7,"Carrocería",""))))))) | F100: 7035001 | G100: =AE100*1000 -> 1000 | H100: POE 68 ÖL Universal mit UV Indikator | I100: POE 68 Aceite Universal con Indicador UV | J100: =F100 -> 7035001 | K100: =G100 -> 1000 | L100: 13.85 | M100: 0.3 | N100: 0 | O100: 0.3 | P100: 0.3 | Q100: =+L100+M100+N100+O100+P100 -> 14.75 | S100: =R100*1.1 -> 0 | U100: =R100-Q100 -> -14.75 | V100: =U100*0.6 -> -8.85 | W100: =U100*0.4 -> -5.9 | Z100: 1 | AA100: =INT(AC100/3) -> 4 | AB100: 5 | AC100: 12 | AD100: =IF(AC100=24,15,IF(AC100=12,10,0)) -> 10 | AE100: 1 | AF100: =AE100*1.1 -> 1.1 | AG100: =AF100*AC100 -> 13.2
...

Sheet familias
D1: -
A2: 1 | B2: =IF(A2=1,"Motor y Transmisión",IF(A2=2,"Refrigeración",IF(A2=3,"Climatización",IF(A2=4,"Sistema de Combustión",IF(A2=5,"Frenos",IF(A2=6,"Mantenimiento y Cuidado",IF(A2=7,"Carrocería",""))))))) -> Motor y Transmisión | C2: motorytransmision | D2: Limpiador de Motor SF (sin disolventes) | G2: motor
A3: 1 | B3: =IF(A3=1,"Motor y Transmisión",IF(A3=2,"Refrigeración",IF(A3=3,"Climatización",IF(A3=4,"Sistema de Combustión",IF(A3=5,"Frenos",IF(A3=6,"Mantenimiento y Cuidado",IF(A3=7,"Carrocería",""))))))) -> Motor y Transmisión | C3: motorytransmision | D3: Limpiador Intensivo de Motor | G3: refrigeracion
A4: 1 | B4: =IF(A4=1,"Motor y Transmisión",IF(A4=2,"Refrigeración",IF(A4=3,"Climatización",IF(A4=4,"Sistema de Combustión",IF(A4=5,"Frenos",IF(A4=6,"Mantenimiento y Cuidado",IF(A4=7,"Carrocería",""))))))) -> Motor y Transmisión | C4: motorytransmision | D4: Tapafugas de Aceite 400 | G4: climatizacion
A5: 1 | B5: =IF(A5=1,"Motor y Transmisión",IF(A5=2,"Refrigeración",IF(A5=3,"Climatización",IF(A5=4,"Sistema de Combustión",IF(A5=5,"Frenos",IF(A5=6,"Mantenimiento y Cuidado",IF(A5=7,"Carrocería",""))))))) -> Motor y Transmisión | C5: motorytransmision | D5: Tapafugas de Aceite 300 | G5: combustion
A6: 1 | B6: =IF(A6=1,"Motor y Transmisión",IF(A6=2,"Refrigeración",IF(A6=3,"Climatización",IF(A6=4,"Sistema de Combustión",IF(A6=5,"Frenos",IF(A6=6,"Mantenimiento y Cuidado",IF(A6=7,"Carrocería",""))))))) -> Motor y Transmisión | C6: motorytransmision | D6: Protector Contra el Desgaste del Motor | G6: frenos
A7: 1 | B7: =IF(A7=1,"Motor y Transmisión",IF(A7=2,"Refrigeración",IF(A7=3,"Climatización",IF(A7=4,"Sistema de Combustión",IF(A7=5,"Frenos",IF(A7=6,"Mantenimiento y Cuidado",IF(A7=7,"Carrocería",""))))))) -> Motor y Transmisión | C7: motorytransmision | D7: Aditivos para Aceites de Transmisión | G7: mantenimiento
A8: 1 | B8: =IF(A8=1,"Motor y Transmisión",IF(A8=2,"Refrigeración",IF(A8=3,"Climatización",IF(A8=4,"Sistema de Combustión",IF(A8=5,"Frenos",IF(A8=6,"Mantenimiento y Cuidado",IF(A8=7,"Carrocería",""))))))) -> Motor y Transmisión | C8: motorytransmision | D8: Limpiador de ATF | G8: carroceria
A9: 1 | B9: =IF(A9=1,"Motor y Transmisión",IF(A9=2,"Refrigeración",IF(A9=3,"Climatización",IF(A9=4,"Sistema de Combustión",IF(A9=5,"Frenos",IF(A9=6,"Mantenimiento y Cuidado",IF(A9=7,"Carrocería",""))))))) -> Motor y Transmisión | C9: motorytransmision | D9: Protector ATF | G9: -
A10: 1 | B10: =IF(A10=1,"Motor y Transmisión",IF(A10=2,"Refrigeración",IF(A10=3,"Climatización",IF(A10=4,"Sistema de Combustión",IF(A10=5,"Frenos",IF(A10=6,"Mantenimiento y Cuidado",IF(A10=7,"Carrocería",""))))))) -> Motor y Transmisión | C10: motorytransmision | D10: Limpiador de Dirección Asistida
A11: 1 | B11: =IF(A11=1,"Motor y Transmisión",IF(A11=2,"Refrigeración",IF(A11=3,"Climatización",IF(A11=4,"Sistema de Combustión",IF(A11=5,"Frenos",IF(A11=6,"Mantenimiento y Cuidado",IF(A11=7,"Carrocería",""))))))) -> Motor y Transmisión | C11: motorytransmision | D11: Protector de la Dirección Asistida
D12: -
A13: 2 | B13: =IF(A13=1,"Motor y Transmisión",IF(A13=2,"Refrigeración",IF(A13=3,"Climatización",IF(A13=4,"Sistema de Combustión",IF(A13=5,"Frenos",IF(A13=6,"Mantenimiento y Cuidado",IF(A13=7,"Carrocería",""))))))) -> Refrigeración | C13: refrigeracion | D13: Protector del Sistema de Refrigeración
A14: 2 | B14: =IF(A14=1,"Motor y Transmisión",IF(A14=2,"Refrigeración",IF(A14=3,"Climatización",IF(A14=4,"Sistema de Combustión",IF(A14=5,"Frenos",IF(A14=6,"Mantenimiento y Cuidado",IF(A14=7,"Carrocería",""))))))) -> Refrigeración | C14: refrigeracion | D14: Tapafugas
A15: 2 | B15: =IF(A15=1,"Motor y Transmisión",IF(A15=2,"Refrigeración",IF(A15=3,"Climatización",IF(A15=4,"Sistema de Combustión",IF(A15=5,"Frenos",IF(A15=6,"Mantenimiento y Cuidado",IF(A15=7,"Carrocería",""))))))) -> Refrigeración | C15: refrigeracion | D15: Limpia Radiadores
A16: 2 | B16: =IF(A16=1,"Motor y Transmisión",IF(A16=2,"Refrigeración",IF(A16=3,"Climatización",IF(A16=4,"Sistema de Combustión",IF(A16=5,"Frenos",IF(A16=6,"Mantenimiento y Cuidado",IF(A16=7,"Carrocería",""))))))) -> Refrigeración | C16: refrigeracion | D16: Protector Térmico
D17: -
A18: 3 | B18: =IF(A18=1,"Motor y Transmisión",IF(A18=2,"Refrigeración",IF(A18=3,"Climatización",IF(A18=4,"Sistema de Combustión",IF(A18=5,"Frenos",IF(A18=6,"Mantenimiento y Cuidado",IF(A18=7,"Carrocería",""))))))) -> Climatización | C18: climatizacion | D18: Climafresh
A19: 3 | B19: =IF(A19=1,"Motor y Transmisión",IF(A19=2,"Refrigeración",IF(A19=3,"Climatización",IF(A19=4,"Sistema de Combustión",IF(A19=5,"Frenos",IF(A19=6,"Mantenimiento y Cuidado",IF(A19=7,"Carrocería",""))))))) -> Climatización | C19: climatizacion | D19: Airfresh
A20: 3 | B20: =IF(A20=1,"Motor y Transmisión",IF(A20=2,"Refrigeración",IF(A20=3,"Climatización",IF(A20=4,"Sistema de Combustión",IF(A20=5,"Frenos",IF(A20=6,"Mantenimiento y Cuidado",IF(A20=7,"Carrocería",""))))))) -> Climatización | C20: climatizacion | D20: Airfresh Menta
A21: 3 | B21: =IF(A21=1,"Motor y Transmisión",IF(A21=2,"Refrigeración",IF(A21=3,"Climatización",IF(A21=4,"Sistema de Combustión",IF(A21=5,"Frenos",IF(A21=6,"Mantenimiento y Cuidado",IF(A21=7,"Carrocería",""))))))) -> Climatización | C21: climatizacion | D21: Airclean Limpiador de Conductos de Aire
A22: 3 | B22: =IF(A22=1,"Motor y Transmisión",IF(A22=2,"Refrigeración",IF(A22=3,"Climatización",IF(A22=4,"Sistema de Combustión",IF(A22=5,"Frenos",IF(A22=6,"Mantenimiento y Cuidado",IF(A22=7,"Carrocería",""))))))) -> Climatización | C22: climatizacion | D22: Tapafugas A/C con Indicador de Fugas
A23: 3 | B23: =IF(A23=1,"Motor y Transmisión",IF(A23=2,"Refrigeración",IF(A23=3,"Climatización",IF(A23=4,"Sistema de Combustión",IF(A23=5,"Frenos",IF(A23=6,"Mantenimiento y Cuidado",IF(A23=7,"Carrocería",""))))))) -> Climatización | C23: climatizacion | D23: Adaptador tapafugas
A24: 3 | B24: =IF(A24=1,"Motor y Transmisión",IF(A24=2,"Refrigeración",IF(A24=3,"Climatización",IF(A24=4,"Sistema de Combustión",IF(A24=5,"Frenos",IF(A24=6,"Mantenimiento y Cuidado",IF(A24=7,"Carrocería",""))))))) -> Climatización | C24: climatizacion | D24: Tapafugas A/C sin Indicador de Fugas 100
A25: 3 | B25: =IF(A25=1,"Motor y Transmisión",IF(A25=2,"Refrigeración",IF(A25=3,"Climatización",IF(A25=4,"Sistema de Combustión",IF(A25=5,"Frenos",IF(A25=6,"Mantenimiento y Cuidado",IF(A25=7,"Carrocería",""))))))) -> Climatización | C25: climatizacion | D25: Tapafugas A/C sin Indicador de Fugas 60
A26: 3 | B26: =IF(A26=1,"Motor y Transmisión",IF(A26=2,"Refrigeración",IF(A26=3,"Climatización",IF(A26=4,"Sistema de Combustión",IF(A26=5,"Frenos",IF(A26=6,"Mantenimiento y Cuidado",IF(A26=7,"Carrocería",""))))))) -> Climatización | C26: climatizacion | D26: Indicador de Fuga de A/C 250
A27: 3 | B27: =IF(A27=1,"Motor y Transmisión",IF(A27=2,"Refrigeración",IF(A27=3,"Climatización",IF(A27=4,"Sistema de Combustión",IF(A27=5,"Frenos",IF(A27=6,"Mantenimiento y Cuidado",IF(A27=7,"Carrocería",""))))))) -> Climatización | C27: climatizacion | D27: Indicador de Fuga de A/C 1000
A28: 3 | B28: =IF(A28=1,"Motor y Transmisión",IF(A28=2,"Refrigeración",IF(A28=3,"Climatización",IF(A28=4,"Sistema de Combustión",IF(A28=5,"Frenos",IF(A28=6,"Mantenimiento y Cuidado",IF(A28=7,"Carrocería",""))))))) -> Climatización | C28: climatizacion | D28: Lubricante Universal POE 68
A29: 3 | B29: =IF(A29=1,"Motor y Transmisión",IF(A29=2,"Refrigeración",IF(A29=3,"Climatización",IF(A29=4,"Sistema de Combustión",IF(A29=5,"Frenos",IF(A29=6,"Mantenimiento y Cuidado",IF(A29=7,"Carrocería",""))))))) -> Climatización | C29: climatizacion | D29: Lubricante Universal POE 68 con Indicador UV
A30: 3 | B30: =IF(A30=1,"Motor y Transmisión",IF(A30=2,"Refrigeración",IF(A30=3,"Climatización",IF(A30=4,"Sistema de Combustión",IF(A30=5,"Frenos",IF(A30=6,"Mantenimiento y Cuidado",IF(A30=7,"Carrocería",""))))))) -> Climatización | C30: climatizacion | D30: Airclean Limpiador de Conductos de Aire
D31: -
A32: 4 | B32: =IF(A32=1,"Motor y Transmisión",IF(A32=2,"Refrigeración",IF(A32=3,"Climatización",IF(A32=4,"Sistema de Combustión",IF(A32=5,"Frenos",IF(A32=6,"Mantenimiento y Cuidado",IF(A32=7,"Carrocería",""))))))) -> Sistema de Combustión | C32: sistemadecombustion | D32: Limpiador Intensivo Diésel
A33: 4 | B33: =IF(A33=1,"Motor y Transmisión",IF(A33=2,"Refrigeración",IF(A33=3,"Climatización",IF(A33=4,"Sistema de Combustión",IF(A33=5,"Frenos",IF(A33=6,"Mantenimiento y Cuidado",IF(A33=7,"Carrocería",""))))))) -> Sistema de Combustión | C33: sistemadecombustion | D33: Limpiador de Admisión de Aire Diésel
A34: 4 | B34: =IF(A34=1,"Motor y Transmisión",IF(A34=2,"Refrigeración",IF(A34=3,"Climatización",IF(A34=4,"Sistema de Combustión",IF(A34=5,"Frenos",IF(A34=6,"Mantenimiento y Cuidado",IF(A34=7,"Carrocería",""))))))) -> Sistema de Combustión | C34: sistemadecombustion | D34: Limpiador Turbo EGR Aspiración
A35: 4 | B35: =IF(A35=1,"Motor y Transmisión",IF(A35=2,"Refrigeración",IF(A35=3,"Climatización",IF(A35=4,"Sistema de Combustión",IF(A35=5,"Frenos",IF(A35=6,"Mantenimiento y Cuidado",IF(A35=7,"Carrocería",""))))))) -> Sistema de Combustión | C35: sistemadecombustion | D35: Limpiador de Válvulas de Mariposa y Carburadores
A36: 4 | B36: =IF(A36=1,"Motor y Transmisión",IF(A36=2,"Refrigeración",IF(A36=3,"Climatización",IF(A36=4,"Sistema de Combustión",IF(A36=5,"Frenos",IF(A36=6,"Mantenimiento y Cuidado",IF(A36=7,"Carrocería",""))))))) -> Sistema de Combustión | C36: sistemadecombustion | D36: Protector Diésel 300
A37: 4 | B37: =IF(A37=1,"Motor y Transmisión",IF(A37=2,"Refrigeración",IF(A37=3,"Climatización",IF(A37=4,"Sistema de Combustión",IF(A37=5,"Frenos",IF(A37=6,"Mantenimiento y Cuidado",IF(A37=7,"Carrocería",""))))))) -> Sistema de Combustión | C37: sistemadecombustion | D37: Protector Diésel 400
A38: 4 | B38: =IF(A38=1,"Motor y Transmisión",IF(A38=2,"Refrigeración",IF(A38=3,"Climatización",IF(A38=4,"Sistema de Combustión",IF(A38=5,"Frenos",IF(A38=6,"Mantenimiento y Cuidado",IF(A38=7,"Carrocería",""))))))) -> Sistema de Combustión | C38: sistemadecombustion | D38: Diésel Limpieza Completa
A39: 4 | B39: =IF(A39=1,"Motor y Transmisión",IF(A39=2,"Refrigeración",IF(A39=3,"Climatización",IF(A39=4,"Sistema de Combustión",IF(A39=5,"Frenos",IF(A39=6,"Mantenimiento y Cuidado",IF(A39=7,"Carrocería",""))))))) -> Sistema de Combustión | C39: sistemadecombustion | D39: Protector SCR 50
A40: 4 | B40: =IF(A40=1,"Motor y Transmisión",IF(A40=2,"Refrigeración",IF(A40=3,"Climatización",IF(A40=4,"Sistema de Combustión",IF(A40=5,"Frenos",IF(A40=6,"Mantenimiento y Cuidado",IF(A40=7,"Carrocería",""))))))) -> Sistema de Combustión | C40: sistemadecombustion | D40: Protector SCR 400
A41: 4 | B41: =IF(A41=1,"Motor y Transmisión",IF(A41=2,"Refrigeración",IF(A41=3,"Climatización",IF(A41=4,"Sistema de Combustión",IF(A41=5,"Frenos",IF(A41=6,"Mantenimiento y Cuidado",IF(A41=7,"Carrocería",""))))))) -> Sistema de Combustión | C41: sistemadecombustion | D41: Limpiador DPF Turbo 500
A42: 4 | B42: =IF(A42=1,"Motor y Transmisión",IF(A42=2,"Refrigeración",IF(A42=3,"Climatización",IF(A42=4,"Sistema de Combustión",IF(A42=5,"Frenos",IF(A42=6,"Mantenimiento y Cuidado",IF(A42=7,"Carrocería",""))))))) -> Sistema de Combustión | C42: sistemadecombustion | D42: Limpiador DPF Turbo 300
A43: 4 | B43: =IF(A43=1,"Motor y Transmisión",IF(A43=2,"Refrigeración",IF(A43=3,"Climatización",IF(A43=4,"Sistema de Combustión",IF(A43=5,"Frenos",IF(A43=6,"Mantenimiento y Cuidado",IF(A43=7,"Carrocería",""))))))) -> Sistema de Combustión | C43: sistemadecombustion | D43: Juego Limpiador DPF Turbo
... A54: 4 | B54: =IF(A54=1,"Motor y Transmisión",IF(A54=2,"Refrigeración",IF(A54=3,"Climatización",IF(A54=4,"Sistema de Combustión",IF(A54=5,"Frenos",IF(A54=6,"Mantenimiento y Cuidado",IF(A54=7,"Carrocería",""))))))) -> Sistema de Combustión | C54: sistemadecombustion | D54: Disolvente Activo
D55: -
A56: 5 | B56: =IF(A56=1,"Motor y Transmisión",IF(A56=2,"Refrigeración",IF(A56=3,"Climatización",IF(A56=4,"Sistema de Combustión",IF(A56=5,"Frenos",IF(A56=6,"Mantenimiento y Cuidado",IF(A56=7,"Carrocería",""))))))) -> Frenos | C56: frenos | D56: Protector del Sistema de Frenos 400
A57: 5 | B57: =IF(A57=1,"Motor y Transmisión",IF(A57=2,"Refrigeración",IF(A57=3,"Climatización",IF(A57=4,"Sistema de Combustión",IF(A57=5,"Frenos",IF(A57=6,"Mantenimiento y Cuidado",IF(A57=7,"Carrocería",""))))))) -> Frenos | C57: frenos | D57: Protector del Sistema de Frenos 50
A58: 5 | B58: =IF(A58=1,"Motor y Transmisión",IF(A58=2,"Refrigeración",IF(A58=3,"Climatización",IF(A58=4,"Sistema de Combustión",IF(A58=5,"Frenos",IF(A58=6,"Mantenimiento y Cuidado",IF(A58=7,"Carrocería",""))))))) -> Frenos | C58: frenos | D58: Frenos Hi Tec
A59: 5 | B59: =IF(A59=1,"Motor y Transmisión",IF(A59=2,"Refrigeración",IF(A59=3,"Climatización",IF(A59=4,"Sistema de Combustión",IF(A59=5,"Frenos",IF(A59=6,"Mantenimiento y Cuidado",IF(A59=7,"Carrocería",""))))))) -> Frenos | C59: frenos | D59: Pasta de Frenos con Cerámica
A60: 5 | B60: =IF(A60=1,"Motor y Transmisión",IF(A60=2,"Refrigeración",IF(A60=3,"Climatización",IF(A60=4,"Sistema de Combustión",IF(A60=5,"Frenos",IF(A60=6,"Mantenimiento y Cuidado",IF(A60=7,"Carrocería",""))))))) -> Frenos | C60: frenos | D60: Pasta de Frenos
D61: -
A62: 6 | B62: =IF(A62=1,"Motor y Transmisión",IF(A62=2,"Refrigeración",IF(A62=3,"Climatización",IF(A62=4,"Sistema de Combustión",IF(A62=5,"Frenos",IF(A62=6,"Mantenimiento y Cuidado",IF(A62=7,"Carrocería",""))))))) -> Mantenimiento y Cuidado | C62: mantenimientoycuidado | D62: Anticongelante para Parabrisas
A63: 6 | B63: =IF(A63=1,"Motor y Transmisión",IF(A63=2,"Refrigeración",IF(A63=3,"Climatización",IF(A63=4,"Sistema de Combustión",IF(A63=5,"Frenos",IF(A63=6,"Mantenimiento y Cuidado",IF(A63=7,"Carrocería",""))))))) -> Mantenimiento y Cuidado | C63: mantenimientoycuidado | D63: Limpiador de Parabrisas Concentrado
A64: 6 | B64: =IF(A64=1,"Motor y Transmisión",IF(A64=2,"Refrigeración",IF(A64=3,"Climatización",IF(A64=4,"Sistema de Combustión",IF(A64=5,"Frenos",IF(A64=6,"Mantenimiento y Cuidado",IF(A64=7,"Carrocería",""))))))) -> Mantenimiento y Cuidado | C64: mantenimientoycuidado | D64: Lubricante Sintético Adhesivo 400
A65: 6 | B65: =IF(A65=1,"Motor y Transmisión",IF(A65=2,"Refrigeración",IF(A65=3,"Climatización",IF(A65=4,"Sistema de Combustión",IF(A65=5,"Frenos",IF(A65=6,"Mantenimiento y Cuidado",IF(A65=7,"Carrocería",""))))))) -> Mantenimiento y Cuidado | C65: mantenimientoycuidado | D65: Lubricación Adhesiva
A66: 6 | B66: =IF(A66=1,"Motor y Transmisión",IF(A66=2,"Refrigeración",IF(A66=3,"Climatización",IF(A66=4,"Sistema de Combustión",IF(A66=5,"Frenos",IF(A66=6,"Mantenimiento y Cuidado",IF(A66=7,"Carrocería",""))))))) -> Mantenimiento y Cuidado | C66: mantenimientoycuidado | D66: Grasa semilíquida Transparente
A67: 6 | B67: =IF(A67=1,"Motor y Transmisión",IF(A67=2,"Refrigeración",IF(A67=3,"Climatización",IF(A67=4,"Sistema de Combustión",IF(A67=5,"Frenos",IF(A67=6,"Mantenimiento y Cuidado",IF(A67=7,"Carrocería",""))))))) -> Mantenimiento y Cuidado | C67: mantenimientoycuidado | D67: Aceite Adhesivo de Mantenimiento
A68: 6 | B68: =IF(A68=1,"Motor y Transmisión",IF(A68=2,"Refrigeración",IF(A68=3,"Climatización",IF(A68=4,"Sistema de Combustión",IF(A68=5,"Frenos",IF(A68=6,"Mantenimiento y Cuidado",IF(A68=7,"Carrocería",""))))))) -> Mantenimiento y Cuidado | C68: mantenimientoycuidado | D68: Grasa de Silicona
A69: 6 | B69: =IF(A69=1,"Motor y Transmisión",IF(A69=2,"Refrigeración",IF(A69=3,"Climatización",IF(A69=4,"Sistema de Combustión",IF(A69=5,"Frenos",IF(A69=6,"Mantenimiento y Cuidado",IF(A69=7,"Carrocería",""))))))) -> Mantenimiento y Cuidado | C69: mantenimientoycuidado | D69: Desbloqueante Activo
A70: 6 | B70: =IF(A70=1,"Motor y Transmisión",IF(A70=2,"Refrigeración",IF(A70=3,"Climatización",IF(A70=4,"Sistema de Combustión",IF(A70=5,"Frenos",IF(A70=6,"Mantenimiento y Cuidado",IF(A70=7,"Carrocería",""))))))) -> Mantenimiento y Cuidado | C70: mantenimientoycuidado | D70: Desbloqueante MOS2
A71: 6 | B71: =IF(A71=1,"Motor y Transmisión",IF(A71=2,"Refrigeración",IF(A71=3,"Climatización",IF(A71=4,"Sistema de Combustión",IF(A71=5,"Frenos",IF(A71=6,"Mantenimiento y Cuidado",IF(A71=7,"Carrocería",""))))))) -> Mantenimiento y Cuidado | C71: mantenimientoycuidado | D71: Aerosol de Silicona
A72: 6 | B72: =IF(A72=1,"Motor y Transmisión",IF(A72=2,"Refrigeración",IF(A72=3,"Climatización",IF(A72=4,"Sistema de Combustión",IF(A72=5,"Frenos",IF(A72=6,"Mantenimiento y Cuidado",IF(A72=7,"Carrocería",""))))))) -> Mantenimiento y Cuidado | C72: mantenimientoycuidado | D72: Aerosol para Interiores
A73: 6 | B73: =IF(A73=1,"Motor y Transmisión",IF(A73=2,"Refrigeración",IF(A73=3,"Climatización",IF(A73=4,"Sistema de Combustión",IF(A73=5,"Frenos",IF(A73=6,"Mantenimiento y Cuidado",IF(A73=7,"Carrocería",""))))))) -> Mantenimiento y Cuidado | C73: mantenimientoycuidado | D73: Aerosol de Aceite con PTFE
... A88: 6 | B88: =IF(A88=1,"Motor y Transmisión",IF(A88=2,"Refrigeración",IF(A88=3,"Climatización",IF(A88=4,"Sistema de Combustión",IF(A88=5,"Frenos",IF(A88=6,"Mantenimiento y Cuidado",IF(A88=7,"Carrocería",""))))))) -> Mantenimiento y Cuidado | C88: mantenimientoycuidado | D88: Spray Detector de Fugas (aire)
D89: -
A90: 7 | B90: =IF(A90=1,"Motor y Transmisión",IF(A90=2,"Refrigeración",IF(A90=3,"Climatización",IF(A90=4,"Sistema de Combustión",IF(A90=5,"Frenos",IF(A90=6,"Mantenimiento y Cuidado",IF(A90=7,"Carrocería",""))))))) -> Carrocería | C90: carroceria | D90: Limpiador de Vidrios y Pintura
A91: 7 | B91: =IF(A91=1,"Motor y Transmisión",IF(A91=2,"Refrigeración",IF(A91=3,"Climatización",IF(A91=4,"Sistema de Combustión",IF(A91=5,"Frenos",IF(A91=6,"Mantenimiento y Cuidado",IF(A91=7,"Carrocería",""))))))) -> Carrocería | C91: carroceria | D91: Pintura de Zinc
A92: 7 | B92: =IF(A92=1,"Motor y Transmisión",IF(A92=2,"Refrigeración",IF(A92=3,"Climatización",IF(A92=4,"Sistema de Combustión",IF(A92=5,"Frenos",IF(A92=6,"Mantenimiento y Cuidado",IF(A92=7,"Carrocería",""))))))) -> Carrocería | C92: carroceria | D92: Protector de Bajos (negro mate)
A93: 7 | B93: =IF(A93=1,"Motor y Transmisión",IF(A93=2,"Refrigeración",IF(A93=3,"Climatización",IF(A93=4,"Sistema de Combustión",IF(A93=5,"Frenos",IF(A93=6,"Mantenimiento y Cuidado",IF(A93=7,"Carrocería",""))))))) -> Carrocería | C93: carroceria | D93: Sellador de Cavidades (transparente)
A94: 7 | B94: =IF(A94=1,"Motor y Transmisión",IF(A94=2,"Refrigeración",IF(A94=3,"Climatización",IF(A94=4,"Sistema de Combustión",IF(A94=5,"Frenos",IF(A94=6,"Mantenimiento y Cuidado",IF(A94=7,"Carrocería",""))))))) -> Carrocería | C94: carroceria | D94: Adhesivo de Poluretano 2 componentes 90
A95: 7 | B95: =IF(A95=1,"Motor y Transmisión",IF(A95=2,"Refrigeración",IF(A95=3,"Climatización",IF(A95=4,"Sistema de Combustión",IF(A95=5,"Frenos",IF(A95=6,"Mantenimiento y Cuidado",IF(A95=7,"Carrocería",""))))))) -> Carrocería | C95: carroceria | D95: Adhesivo de Poluretano 2 componentes 210

Sheet DATOS (2)
A1: 1 | B1: 2 | E1: 3 | F1: 4 | G1: 5 | H1: 6 | I1: 7 | J1: 8 | K1: 9 | L1: 10 | M1: 11 | N1: 12 | O1: 13 | P1: 14 | Q1: 15 | R1: 16 | S1: 17 | T1: 18 | U1: 19 | V1: 20 | W1: 21 | X1: 22 | Y1: 23 | Z1: 24 | AB1: 25 | AC1: 26 | AD1: 27 | AE1: 28 | AF1: 29 | AG1: 30 | AH1: 31 | AI1: 32 | AJ1: 33 | AK1: 34 | AL1: 35 | AM1: 36
A2: proveedor | B2: documento | C2: clase | E2: relevancia | F2: referencia | H2: Aleman | I2: Español | J2: =F2 -> referencia | K2: =G2 -> 0 | L2: COSTO | M2: PORTE UD | N2: ADUANA | O2: EMBALAJE | P2: MANIPULACIÓN | Q2: COSTO REAL | R2: PRECIO TALLER | S2: PVP | T2: PRECIO CLIENTE | U2: BENEFICIO TOTAL | V2: BENEFICIO MIO | W2: BENEFICIO COMERCIAL | X2: BENEFICIO % | Z2: unidad | AA2: cantidad minima | AB2: dto unidad | AC2: unidades caja | AD2: dto caja | AE2: Volumen (L) | AF2: PESO (Kg) | AG2: PESO CAJA (Kg) | AH2: AUXILIAR COSTO+TRANSPORTE | AI2: TRANSPORTE | AJ2: Pedido unidad | AK2: Pedido caja | AL2: Palet | AM2: Precio Pedido | AS2: PVP (IVA INCLUIDO)
A3: WEPP | B3: C | C3: 1 | D3: =IF(C3=1,"Motor y Transmisión",IF(C3=2,"Refrigeración",IF(C3=3,"Climatización",IF(C3=4,"Sistema de Combustión",IF(C3=5,"Frenos",IF(C3=6,"Mantenimiento y Cuidado",IF(C3=7,"Carrocería",""))))))) -> Motor y Transmisión | E3: 1 | F3: 2010 SF | G3: =AE3*1000 -> 300 | H3: Motor System Reiniger (Lösungsmittelfrei) | I3: Limpiador de Motor SF (sin disolventes) | J3: =F3 -> 2010 SF | K3: =G3 -> 300 | L3: 2.95 | M3: 0.3 | N3: 0 | O3: 0.3 | P3: 0.3 | Q3: =+L3+M3+N3+O3+P3 -> 3.85 | R3: 9.35 | S3: =ROUND(R3*1.1,2) -> 10.29 | T3: 16.85 | U3: =R3-Q3 -> 5.5 | V3: =U3*0.6 -> 3.3 | W3: =U3*0.4 -> 2.2 | Z3: 1 | AA3: =INT(AC3/3) -> 8 | AB3: 5 | AC3: 24 | AD3: =IF(AC3=24,15,IF(AC3=12,10,0)) -> 15 | AE3: 0.3 | AF3: =AE3*1.1 -> 0.33 | AG3: =AF3*AC3 -> 7.92 | AI3: 1 | AK3: 2 | AS3: =ROUND(S3*1.21,2) -> 12.45
A4: WEPP | B4: C | C4: 1 | D4: =IF(C4=1,"Motor y Transmisión",IF(C4=2,"Refrigeración",IF(C4=3,"Climatización",IF(C4=4,"Sistema de Combustión",IF(C4=5,"Frenos",IF(C4=6,"Mantenimiento y Cuidado",IF(C4=7,"Carrocería",""))))))) -> Motor y Transmisión | E4: 1 | F4: 2110 | G4: =AE4*1000 -> 300 | H4: Motor Intensiv Reiniger | I4: Limpiador Intensivo de Motor | J4: =F4 -> 2110 | K4: =G4 -> 300 | L4: 4.78 | M4: 0.3 | N4: 0 | O4: 0.3 | P4: 0.3 | Q4: =+L4+M4+N4+O4+P4 -> 5.68 | R4: 12.85 | S4: =ROUND(R4*1.1,2) -> 14.14 | T4: 21.35 | U4: =R4-Q4 -> 7.17 | V4: =U4*0.6 -> 4.302 | W4: =U4*0.4 -> 2.868 | Z4: 1 | AA4: =INT(AC4/3) -> 8 | AB4: 5 | AC4: 24 | AD4: =IF(AC4=24,15,IF(AC4=12,10,0)) -> 15 | AE4: 0.3 | AF4: =AE4*1.1 -> 0.33 | AG4: =AF4*AC4 -> 7.92 | AI4: 2 | AK4: 2 | AS4: =ROUND(S4*1.21,2) -> 17.11
A5: WEPP | B5: C | C5: 1 | D5: =IF(C5=1,"Motor y Transmisión",IF(C5=2,"Refrigeración",IF(C5=3,"Climatización",IF(C5=4,"Sistema de Combustión",IF(C5=5,"Frenos",IF(C5=6,"Mantenimiento y Cuidado",IF(C5=7,"Carrocería",""))))))) -> Motor y Transmisión | E5: 1 | F5: 2011 | G5: =AE5*1000 -> 400 | H5: Ölstopp Additiv | I5: Tapafugas de Aceite 400 | J5: =F5 -> 2011 | K5: =G5 -> 400 | L5: 3.3 | M5: 0.3 | N5: 0 | O5: 0.3 | P5: 0.3 | Q5: =+L5+M5+N5+O5+P5 -> 4.2 | R5: 9.7 | S5: =ROUND(R5*1.1,2) -> 10.67 | T5: 14.4 | U5: =R5-Q5 -> 5.5 | V5: =U5*0.6 -> 3.3 | W5: =U5*0.4 -> 2.2 | Z5: 1 | AA5: =INT(AC5/3) -> 8 | AB5: 5 | AC5: 24 | AD5: =IF(AC5=24,15,IF(AC5=12,10,0)) -> 15 | AE5: 0.4 | AF5: =AE5*1.1 -> 0.44 | AG5: =AF5*AC5 -> 10.56 | AI5: 3 | AK5: 2 | AS5: =ROUND(S5*1.21,2) -> 12.91
A6: WEPP | B6: C | C6: 1 | D6: =IF(C6=1,"Motor y Transmisión",IF(C6=2,"Refrigeración",IF(C6=3,"Climatización",IF(C6=4,"Sistema de Combustión",IF(C6=5,"Frenos",IF(C6=6,"Mantenimiento y Cuidado",IF(C6=7,"Carrocería",""))))))) -> Motor y Transmisión | E6: 1 | F6: 2011-300 | G6: =AE6*1000 -> 300 | H6: Ölstopp Additiv | I6: Tapafugas de Aceite 300 | J6: =F6 -> 2011-300 | K6: =G6 -> 300 | L6: 2.8 | M6: 0.3 | N6: 0 | O6: 0.3 | P6: 0.3 | Q6: =+L6+M6+N6+O6+P6 -> 3.7 | R6: 7.5 | S6: =ROUND(R6*1.1,2) -> 8.25 | T6: 13.45 | U6: =R6-Q6 -> 3.8 | V6: =U6*0.6 -> 2.28 | W6: =U6*0.4 -> 1.52 | Z6: 1 | AA6: =INT(AC6/3) -> 8 | AB6: 5 | AC6: 24 | AD6: =IF(AC6=24,15,IF(AC6=12,10,0)) -> 15 | AE6: 0.3 | AF6: =AE6*1.1 -> 0.33 | AG6: =AF6*AC6 -> 7.92 | AS6: =ROUND(S6*1.21,2) -> 9.98
A7: WEPP | B7: C | C7: 1 | D7: =IF(C7=1,"Motor y Transmisión",IF(C7=2,"Refrigeración",IF(C7=3,"Climatización",IF(C7=4,"Sistema de Combustión",IF(C7=5,"Frenos",IF(C7=6,"Mantenimiento y Cuidado",IF(C7=7,"Carrocería",""))))))) -> Motor y Transmisión | E7: 1 | F7: 2111 | G7: =AE7*1000 -> 300 | H7: Motor Verschleiss Schutz | I7: Protector Contra el Desgaste del Motor | J7: =F7 -> 2111 | K7: =G7 -> 300 | L7: 3.95 | M7: 0.3 | N7: 0 | O7: 0.3 | P7: 0.3 | Q7: =+L7+M7+N7+O7+P7 -> 4.85 | R7: 10.05 | S7: =ROUND(R7*1.1,2) -> 11.06 | T7: 18.1 | U7: =R7-Q7 -> 5.2 | V7: =U7*0.6 -> 3.12 | W7: =U7*0.4 -> 2.08 | Z7: 1 | AA7: =INT(AC7/3) -> 8 | AB7: 5 | AC7: 24 | AD7: =IF(AC7=24,15,IF(AC7=12,10,0)) -> 15 | AE7: 0.3 | AF7: =AE7*1.1 -> 0.33 | AG7: =AF7*AC7 -> 7.92 | AI7: 4 | AK7: 2 | AS7: =ROUND(S7*1.21,2) -> 13.38
A8: WEPP | B8: C | C8: 1 | D8: =IF(C8=1,"Motor y Transmisión",IF(C8=2,"Refrigeración",IF(C8=3,"Climatización",IF(C8=4,"Sistema de Combustión",IF(C8=5,"Frenos",IF(C8=6,"Mantenimiento y Cuidado",IF(C8=7,"Carrocería",""))))))) -> Motor y Transmisión | E8: 1 | F8: 2012 | G8: =AE8*1000 -> 100 | H8: Getriebeöladditiv | I8: Aditivos para Aceites de Transmisión | J8: =F8 -> 2012 | K8: =G8 -> 100 | L8: 3.85 | M8: 0.3 | N8: 0 | O8: 0.3 | P8: 0.3 | Q8: =+L8+M8+N8+O8+P8 -> 4.75 | R8: 8.95 | S8: =ROUND(R8*1.1,2) -> 9.85 | T8: 14.8 | U8: =R8-Q8 -> 4.2 | V8: =U8*0.6 -> 2.52 | W8: =U8*0.4 -> 1.68 | Z8: 1 | AA8: =INT(AC8/3) -> 8 | AB8: 5 | AC8: 24 | AD8: =IF(AC8=24,15,IF(AC8=12,10,0)) -> 15 | AE8: 0.1 | AF8: =AE8*1.1 -> 0.11 | AG8: =AF8*AC8 -> 2.64 | AI8: 5 | AS8: =ROUND(S8*1.21,2) -> 11.92
A9: WEPP | B9: C | C9: 1 | D9: =IF(C9=1,"Motor y Transmisión",IF(C9=2,"Refrigeración",IF(C9=3,"Climatización",IF(C9=4,"Sistema de Combustión",IF(C9=5,"Frenos",IF(C9=6,"Mantenimiento y Cuidado",IF(C9=7,"Carrocería",""))))))) -> Motor y Transmisión | E9: 1 | F9: 2013 | G9: =AE9*1000 -> 300 | H9: ATF Cleaner | I9: Limpiador de ATF | J9: =F9 -> 2013 | K9: =G9 -> 300 | L9: 3.9 | M9: 0.3 | N9: 0 | O9: 0.3 | P9: 0.3 | Q9: =+L9+M9+N9+O9+P9 -> 4.8 | R9: 11.3 | S9: =ROUND(R9*1.1,2) -> 12.43 | T9: 18.1 | U9: =R9-Q9 -> 6.5 | V9: =U9*0.6 -> 3.9 | W9: =U9*0.4 -> 2.6 | Z9: 1 | AA9: =INT(AC9/3) -> 8 | AB9: 5 | AC9: 24 | AD9: =IF(AC9=24,15,IF(AC9=12,10,0)) -> 15 | AE9: 0.3 | AF9: =AE9*1.1 -> 0.33 | AG9: =AF9*AC9 -> 7.92 | AI9: 6 | AS9: =ROUND(S9*1.21,2) -> 15.04
A10: WEPP | B10: C | C10: 1 | D10: =IF(C10=1,"Motor y Transmisión",IF(C10=2,"Refrigeración",IF(C10=3,"Climatización",IF(C10=4,"Sistema de Combustión",IF(C10=5,"Frenos",IF(C10=6,"Mantenimiento y Cuidado",IF(C10=7,"Carrocería",""))))))) -> Motor y Transmisión | E10: 1 | F10: 2014 | G10: =AE10*1000 -> 300 | H10: ATF Protection | I10: Protector ATF | J10: =F10 -> 2014 | K10: =G10 -> 300 | L10: 4.3 | M10: 0.3 | N10: 0 | O10: 0.3 | P10: 0.3 | Q10: =+L10+M10+N10+O10+P10 -> 5.2 | R10: 14.5 | S10: =ROUND(R10*1.1,2) -> 15.95 | T10: 23 | U10: =R10-Q10 -> 9.3 | V10: =U10*0.6 -> 5.58 | W10: =U10*0.4 -> 3.72 | Z10: 1 | AA10: =INT(AC10/3) -> 8 | AB10: 5 | AC10: 24 | AD10: =IF(AC10=24,15,IF(AC10=12,10,0)) -> 15 | AE10: 0.3 | AF10: =AE10*1.1 -> 0.33 | AG10: =AF10*AC10 -> 7.92 | AI10: 7 | AS10: =ROUND(S10*1.21,2) -> 19.3
A11: WEPP | B11: C | C11: 1 | D11: =IF(C11=1,"Motor y Transmisión",IF(C11=2,"Refrigeración",IF(C11=3,"Climatización",IF(C11=4,"Sistema de Combustión",IF(C11=5,"Frenos",IF(C11=6,"Mantenimiento y Cuidado",IF(C11=7,"Carrocería",""))))))) -> Motor y Transmisión | E11: 0 | F11: 2015 | G11: =AE11*1000 -> 300 | H11: Power Steering Cleaner | I11: Limpiador de Dirección Asistida | J11: =F11 -> 2015 | K11: =G11 -> 300 | L11: 3.7 | M11: 0.3 | N11: 0 | O11: 0.3 | P11: 0.3 | Q11: =+L11+M11+N11+O11+P11 -> 4.6 | R11: 11 | S11: =ROUND(R11*1.1,2) -> 12.1 | T11: 17.7 | U11: =R11-Q11 -> 6.4 | V11: =U11*0.6 -> 3.84 | W11: =U11*0.4 -> 2.56 | Z11: 1 | AA11: =INT(AC11/3) -> 8 | AB11: 5 | AC11: 24 | AD11: =IF(AC11=24,15,IF(AC11=12,10,0)) -> 15 | AE11: 0.3 | AF11: =AE11*1.1 -> 0.33 | AG11: =AF11*AC11 -> 7.92 | AI11: 8 | AS11: =ROUND(S11*1.21,2) -> 14.64
A12: WEPP | B12: C | C12: 1 | D12: =IF(C12=1,"Motor y Transmisión",IF(C12=2,"Refrigeración",IF(C12=3,"Climatización",IF(C12=4,"Sistema de Combustión",IF(C12=5,"Frenos",IF(C12=6,"Mantenimiento y Cuidado",IF(C12=7,"Carrocería",""))))))) -> Motor y Transmisión | E12: 0 | F12: 2016 | G12: =AE12*1000 -> 100 | H12: Power Steering Protection | I12: Protector de la Dirección Asistida | J12: =F12 -> 2016 | K12: =G12 -> 100 | L12: 2.85 | M12: 0.3 | N12: 0 | O12: 0.3 | P12: 0.3 | Q12: =+L12+M12+N12+O12+P12 -> 3.75 | R12: 8.9 | S12: =ROUND(R12*1.1,2) -> 9.79 | T12: 14.25 | U12: =R12-Q12 -> 5.15 | V12: =U12*0.6 -> 3.09 | W12: =U12*0.4 -> 2.06 | Z12: 1 | AA12: =INT(AC12/3) -> 8 | AB12: 5 | AC12: 24 | AD12: =IF(AC12=24,15,IF(AC12=12,10,0)) -> 15 | AE12: 0.1 | AF12: =AE12*1.1 -> 0.11 | AG12: =AF12*AC12 -> 2.64 | AI12: 9 | AS12: =ROUND(S12*1.21,2) -> 11.85
A13: WEPP | B13: C | C13: 2 | D13: =IF(C13=1,"Motor y Transmisión",IF(C13=2,"Refrigeración",IF(C13=3,"Climatización",IF(C13=4,"Sistema de Combustión",IF(C13=5,"Frenos",IF(C13=6,"Mantenimiento y Cuidado",IF(C13=7,"Carrocería",""))))))) -> Refrigeración | E13: 1 | F13: 2020 | G13: =AE13*1000 -> 300 | H13: Kühler System Schutz | I13: Protector del Sistema de Refrigeración | J13: =F13 -> 2020 | K13: =G13 -> 300 | L13: 3.3 | M13: 0.3 | N13: 0 | O13: 0.3 | P13: 0.3 | Q13: =+L13+M13+N13+O13+P13 -> 4.2 | R13: 7.7 | S13: =ROUND(R13*1.1,2) -> 8.47 | T13: 14.65 | U13: =R13-Q13 -> 3.5 | V13: =U13*0.6 -> 2.1 | W13: =U13*0.4 -> 1.4 | Z13: 1 | AA13: =INT(AC13/3) -> 8 | AB13: 5 | AC13: 24 | AD13: =IF(AC13=24,15,IF(AC13=12,10,0)) -> 15 | AE13: 0.3 | AF13: =AE13*1.1 -> 0.33 | AG13: =AF13*AC13 -> 7.92 | AK13: 2 | AS13: =ROUND(S13*1.21,2) -> 10.25
A14: WEPP | B14: C | C14: 2 | D14: =IF(C14=1,"Motor y Transmisión",IF(C14=2,"Refrigeración",IF(C14=3,"Climatización",IF(C14=4,"Sistema de Combustión",IF(C14=5,"Frenos",IF(C14=6,"Mantenimiento y Cuidado",IF(C14=7,"Carrocería",""))))))) -> Refrigeración | E14: 1 | F14: 2021 | G14: =AE14*1000 -> 400 | H14: Kühlerdicht | I14: Tapafugas | J14: =F14 -> 2021 | K14: =G14 -> 400 | L14: 3 | M14: 0.3 | N14: 0 | O14: 0.3 | P14: 0.3 | Q14: =+L14+M14+N14+O14+P14 -> 3.9 | R14: 7.25 | S14: =ROUND(R14*1.1,2) -> 7.98 | T14: 13.15 | U14: =R14-Q14 -> 3.35 | V14: =U14*0.6 -> 2.01 | W14: =U14*0.4 -> 1.34 | Z14: 1 | AA14: =INT(AC14/3) -> 8 | AB14: 5 | AC14: 24 | AD14: =IF(AC14=24,15,IF(AC14=12,10,0)) -> 15 | AE14: 0.4 | AF14: =AE14*1.1 -> 0.44 | AG14: =AF14*AC14 -> 10.56 | AK14: 2 | AS14: =ROUND(S14*1.21,2) -> 9.66
A15: WEPP | B15: C | C15: 2 | D15: =IF(C15=1,"Motor y Transmisión",IF(C15=2,"Refrigeración",IF(C15=3,"Climatización",IF(C15=4,"Sistema de Combustión",IF(C15=5,"Frenos",IF(C15=6,"Mantenimiento y Cuidado",IF(C15=7,"Carrocería",""))))))) -> Refrigeración | E15: 1 | F15: 2023 | G15: =AE15*1000 -> 400 | H15: Kühlerreinigung | I15: Limpia Radiadores | J15: =F15 -> 2023 | K15: =G15 -> 400 | L15: 2.75 | M15: 0.3 | N15: 0 | O15: 0.3 | P15: 0.3 | Q15: =+L15+M15+N15+O15+P15 -> 3.65 | R15: 7.45 | S15: =ROUND(R15*1.1,2) -> 8.2 | T15: 14.15 | U15: =R15-Q15 -> 3.8 | V15: =U15*0.6 -> 2.28 | W15: =U15*0.4 -> 1.52 | Z15: 1 | AA15: =INT(AC15/3) -> 8 | AB15: 5 | AC15: 24 | AD15: =IF(AC15=24,15,IF(AC15=12,10,0)) -> 15 | AE15: 0.4 | AF15: =AE15*1.1 -> 0.44 | AG15: =AF15*AC15 -> 10.56 | AK15: 2 | AS15: =ROUND(S15*1.21,2) -> 9.92
A16: WEPP | B16: C | C16: 2 | D16: =IF(C16=1,"Motor y Transmisión",IF(C16=2,"Refrigeración",IF(C16=3,"Climatización",IF(C16=4,"Sistema de Combustión",IF(C16=5,"Frenos",IF(C16=6,"Mantenimiento y Cuidado",IF(C16=7,"Carrocería",""))))))) -> Refrigeración | E16: 1 | F16: 2123 | G16: =AE16*1000 -> 500 | H16: Thermoschutz | I16: Protector Térmico | J16: =F16 -> 2123 | K16: =G16 -> 500 | L16: 4.9 | M16: 0.3 | N16: 0 | O16: 0.3 | P16: 0.3 | Q16: =+L16+M16+N16+O16+P16 -> 5.8 | R16: 12 | S16: =ROUND(R16*1.1,2) -> 13.2 | U16: =R16-Q16 -> 6.2 | V16: =U16*0.6 -> 3.72 | W16: =U16*0.4 -> 2.48 | Z16: 1 | AA16: =INT(AC16/3) -> 4 | AB16: 5 | AC16: 12 | AD16: =IF(AC16=24,15,IF(AC16=12,10,0)) -> 10 | AE16: 0.5 | AF16: =AE16*1.1 -> 0.55 | AG16: =AF16*AC16 -> 6.6 | AS16: =ROUND(S16*1.21,2) -> 15.97
A17: WEPP | B17: C | C17: 3 | D17: =IF(C17=1,"Motor y Transmisión",IF(C17=2,"Refrigeración",IF(C17=3,"Climatización",IF(C17=4,"Sistema de Combustión",IF(C17=5,"Frenos",IF(C17=6,"Mantenimiento y Cuidado",IF(C17=7,"Carrocería",""))))))) -> Climatización | E17: 0 | F17: 2024-1000 | G17: =AE17*1000 -> 1000 | H17: Klimafresh | I17: Climafresh | J17: =F17 -> 2024-1000 | K17: =G17 -> 1000 | L17: 5.5 | M17: 0.3 | N17: 0 | O17: 0.3 | P17: 0.3 | Q17: =+L17+M17+N17+O17+P17 -> 6.4 | R17: 13.7 | S17: =ROUND(R17*1.1,2) -> 15.07 | U17: =R17-Q17 -> 7.3 | V17: =U17*0.6 -> 4.38 | W17: =U17*0.4 -> 2.92 | Z17: 1 | AA17: =INT(AC17/3) -> 4 | AB17: 5 | AC17: 12 | AD17: =IF(AC17=24,15,IF(AC17=12,10,0)) -> 10 | AE17: 1 | AF17: =AE17*1.1 -> 1.1 | AG17: =AF17*AC17 -> 13.2 | AK17: ? | AS17: =ROUND(S17*1.21,2) -> 18.23
A18: WEPP | B18: C | C18: 3 | D18: =IF(C18=1,"Motor y Transmisión",IF(C18=2,"Refrigeración",IF(C18=3,"Climatización",IF(C18=4,"Sistema de Combustión",IF(C18=5,"Frenos",IF(C18=6,"Mantenimiento y Cuidado",IF(C18=7,"Carrocería",""))))))) -> Climatización | E18: 1 | F18: 2025 | G18: =AE18*1000 -> 100 | H18: Airfresh | I18: Airfresh | J18: =F18 -> 2025 | K18: =G18 -> 100 | L18: 3.35 | M18: 0.3 | N18: 0 | O18: 0.3 | P18: 0.3 | Q18: =+L18+M18+N18+O18+P18 -> 4.25 | R18: 9.25 | S18: =ROUND(R18*1.1,2) -> 10.18 | T18: 15.2 | U18: =R18-Q18 -> 5 | V18: =U18*0.6 -> 3 | W18: =U18*0.4 -> 2 | Z18: 1 | AA18: =INT(AC18/3) -> 8 | AB18: 5 | AC18: 24 | AD18: =IF(AC18=24,15,IF(AC18=12,10,0)) -> 15 | AE18: 0.1 | AF18: =AE18*1.1 -> 0.11 | AG18: =AF18*AC18 -> 2.64 | AK18: 1 | AS18: =ROUND(S18*1.21,2) -> 12.32
A19: WEPP | B19: C | C19: 3 | D19: =IF(C19=1,"Motor y Transmisión",IF(C19=2,"Refrigeración",IF(C19=3,"Climatización",IF(C19=4,"Sistema de Combustión",IF(C19=5,"Frenos",IF(C19=6,"Mantenimiento y Cuidado",IF(C19=7,"Carrocería",""))))))) -> Climatización | E19: 0 | F19: 2125 | G19: =AE19*1000 -> 100 | H19: Airfresh Mint | I19: Airfresh Menta | J19: =F19 -> 2125 | K19: =G19 -> 100 | L19: 3.35 | M19: 0.3 | N19: 0 | O19: 0.3 | P19: 0.3 | Q19: =+L19+M19+N19+O19+P19 -> 4.25 | R19: 9.25 | S19: =ROUND(R19*1.1,2) -> 10.18 | T19: 15.2 | U19: =R19-Q19 -> 5 | V19: =U19*0.6 -> 3 | W19: =U19*0.4 -> 2 | Z19: 1 | AA19: =INT(AC19/3) -> 8 | AB19: 5 | AC19: 24 | AD19: =IF(AC19=24,15,IF(AC19=12,10,0)) -> 15 | AE19: 0.1 | AF19: =AE19*1.1 -> 0.11 | AG19: =AF19*AC19 -> 2.64 | AK19: 1 | AS19: =ROUND(S19*1.21,2) -> 12.32
A20: WEPP | B20: C | C20: 3 | D20: =IF(C20=1,"Motor y Transmisión",IF(C20=2,"Refrigeración",IF(C20=3,"Climatización",IF(C20=4,"Sistema de Combustión",IF(C20=5,"Frenos",IF(C20=6,"Mantenimiento y Cuidado",IF(C20=7,"Carrocería",""))))))) -> Climatización | E20: 0 | F20: 2127 | G20: 75 | H20: Airclean | I20: Airclean Limpiador de Conductos de Aire | J20: =F20 -> 2127 | K20: =G20 -> 75 | L20: 3.35 | M20: 0.3 | N20: 0 | O20: 0.3 | P20: 0.3 | Q20: =+L20+M20+N20+O20+P20 -> 4.25 | R20: 9.25 | S20: =ROUND(R20*1.1,2) -> 10.18 | T20: 15.2 | U20: =R20-Q20 -> 5 | V20: =U20*0.6 -> 3 | W20: =U20*0.4 -> 2 | Z20: 1 | AA20: =INT(AC20/3) -> 8 | AB20: 5 | AC20: 24 | AD20: =IF(AC20=24,15,IF(AC20=12,10,0)) -> 15 | AE20: 0.1 | AF20: =AE20*1.1 -> 0.11 | AG20: =AF20*AC20 -> 2.64 | AK20: 1 | AS20: =ROUND(S20*1.21,2) -> 12.32
A21: WEPP | B21: C | C21: 3 | D21: =IF(C21=1,"Motor y Transmisión",IF(C21=2,"Refrigeración",IF(C21=3,"Climatización",IF(C21=4,"Sistema de Combustión",IF(C21=5,"Frenos",IF(C21=6,"Mantenimiento y Cuidado",IF(C21=7,"Carrocería",""))))))) -> Climatización | E21: 1 | F21: 7020100 | G21: =AE21*1000 -> 100 | H21: Leckstopp und Indikator | I21: Tapafugas A/C con Indicador de Fugas | J21: =F21 -> 7020100 | K21: =G21 -> 100 | L21: 6.8 | M21: 0.3 | N21: 0 | O21: 0.3 | P21: 0.3 | Q21: =+L21+M21+N21+O21+P21 -> 7.7 | R21: 21.2 | S21: =ROUND(R21*1.1,2) -> 23.32 | T21: 33.7 | U21: =R21-Q21 -> 13.5 | V21: =U21*0.6 -> 8.1 | W21: =U21*0.4 -> 5.4 | Z21: 1 | AA21: =INT(AC21/3) -> 8 | AB21: 5 | AC21: 24 | AD21: =IF(AC21=24,15,IF(AC21=12,10,0)) -> 15 | AE21: 0.1 | AF21: =AE21*1.1 -> 0.11 | AG21: =AF21*AC21 -> 2.64 | AJ21: 1 | AS21: =ROUND(S21*1.21,2) -> 28.22
A22: WEPP | B22: C | C22: 3 | D22: =IF(C22=1,"Motor y Transmisión",IF(C22=2,"Refrigeración",IF(C22=3,"Climatización",IF(C22=4,"Sistema de Combustión",IF(C22=5,"Frenos",IF(C22=6,"Mantenimiento y Cuidado",IF(C22=7,"Carrocería",""))))))) -> Climatización | E22: 1 | F22: 1711 | G22: =AE22*1000 -> 100 | H22: AC Aerosol Adapter | I22: Adaptador tapafugas | J22: =F22 -> 1711 | K22: =G22 -> 100 | L22: 2.5 | M22: 0.3 | N22: 0 | O22: 0.3 | P22: 0.3 | Q22: =+L22+M22+N22+O22+P22 -> 3.4 | R22: 7 | S22: =ROUND(R22*1.1,2) -> 7.7 | U22: =R22-Q22 -> 3.6 | V22: =U22*0.6 -> 2.16 | W22: =U22*0.4 -> 1.44 | Z22: 1 | AA22: =INT(AC22/3) -> 0 | AB22: 5 | AC22: 1 | AD22: =IF(AC22=24,15,IF(AC22=12,10,0)) -> 0 | AE22: 0.1 | AF22: =AE22*1.1 -> 0.11 | AG22: =AF22*AC22 -> 0.11 | AK22: 1 | AS22: =ROUND(S22*1.21,2) -> 9.32
A23: WEPP | B23: C | C23: 3 | D23: =IF(C23=1,"Motor y Transmisión",IF(C23=2,"Refrigeración",IF(C23=3,"Climatización",IF(C23=4,"Sistema de Combustión",IF(C23=5,"Frenos",IF(C23=6,"Mantenimiento y Cuidado",IF(C23=7,"Carrocería",""))))))) -> Climatización | E23: 1 | F23: 7021100 | G23: =AE23*1000 -> 100 | H23: Leckstopp komplett | I23: Tapafugas A/C sin Indicador de Fugas 100 | J23: =F23 -> 7021100 | K23: =G23 -> 100 | L23: 15.5 | M23: 0.3 | N23: 0 | O23: 0.3 | P23: 0.3 | Q23: =+L23+M23+N23+O23+P23 -> 16.4 | R23: 44.7 | S23: =ROUND(R23*1.1,2) -> 49.17 | T23: 71.7 | U23: =R23-Q23 -> 28.3 | V23: =U23*0.6 -> 16.98 | W23: =U23*0.4 -> 11.32 | Z23: 1 | AA23: =INT(AC23/3) -> 8 | AB23: 5 | AC23: 24 | AD23: =IF(AC23=24,15,IF(AC23=12,10,0)) -> 15 | AE23: 0.1 | AF23: =AE23*1.1 -> 0.11 | AG23: =AF23*AC23 -> 2.64 | AJ23: 6 | AS23: =ROUND(S23*1.21,2) -> 59.5
